Workbook

Sheet swiss_qna
A2: Staatssekretariat für Wirtschaft SECO
A3: Secrétariat d'Etat à l'économie SECO
A4: Segreteria di Stato dell’economia SECO
A5: Secretariat da stadi per l'economia SECO
A6: State Secretariat for Economic Affairs SECO
A8: You may choose the language to label the Swiss GDP and its expenditure components in the dropdown-menu below.
A9: Pages labelled at the end with "_q" contain quarterly data, pages with "_y" contain yearly figures.
A10: Pages labelled at the beginning with "nom" contain figures at current prices, pages with "real" contain values at prices of the preceding year (chained values, reference year 2020), pages with "defl" contain implicit price deflators and those with "gc" contain contributions to real GDP-growth.
A12: Sie können im Dropdown-Menu die Sprache wählen, im welcher Sie das BIP der Schweiz gemäss Verwendungsseite beschriftet haben möchten.
A13: Seiten mit der Endbezeichnung "_q" enthalten Quartalszahlen, diejenigen mit "_y" Jahreszahlen.
A14: Seiten mit der Anfangsbezeichnung "nom" enthalten Werte zu laufenden Preisen, diejenigen mit "real" Werte zu Preisen des Vorjahres (verkettet, Referenzjahr 2020), diejenigen mit "defl" implizite Deflatoren und diejenigen mit "gc" Beiträge zum realen BIP-Wachstum.
A16: Vous pouvez choisir ci-dessous la langue avec laquelle vous souhaitez visualiser le PIB de la Suisse selon l'approche par la dépense.
... A22: Le pagine contrassegnate all'inizio con "nom" contengono dati ai prezzi correnti, pagine con "real" contengono valori ai prezzi dell'anno precedente (serie concatenate, anno di riferimento 2020), pagine con "defl" contengono i deflatori impliciti, pagine con "gc" contengono i contributi alla crescita reale del PIL.

Sheet nom_q
A1: =IF(INDIRECT("beschriftung!"&ADDRESS(beschriftung!$C$1*12+ROW(beschriftung!$A1)-1,COLUMN(beschriftung!A$1)))="","",INDIRECT("beschriftung!"&ADDRESS(beschriftung!$C$1*12+ROW(beschriftung!$A1)-1,COLUMN(beschriftung!A$1)))) -> ESA 2010, Quarterly aggregates of Gross Domestic Product, expenditure approach, raw data
A2: =IF(INDIRECT("beschriftung!"&ADDRESS(beschriftung!$C$1*12+ROW(beschriftung!$A2)-1,COLUMN(beschriftung!A$1)))="","",INDIRECT("beschriftung!"&ADDRESS(beschriftung!$C$1*12+ROW(beschriftung!$A2)-1,COLUMN(beschriftung!A$1)))) -> In Mio. Swiss Francs, at current prices, percentage change to previous year
A3: =IF(INDIRECT("beschriftung!"&ADDRESS(beschriftung!$C$1*12+ROW(beschriftung!$A5)-1,COLUMN(beschriftung!A$1)))="","",INDIRECT("beschriftung!"&ADDRESS(beschriftung!$C$1*12+ROW(beschriftung!$A5)-1,COLUMN(beschriftung!A$1))))
C4: =IF(INDIRECT("beschriftung!"&ADDRESS(beschriftung!$C$1*12+ROW(beschriftung!$A5)-1,COLUMN(beschriftung!C$1)))="","",INDIRECT("beschriftung!"&ADDRESS(beschriftung!$C$1*12+ROW(beschriftung!$A5)-1,COLUMN(beschriftung!C$1)))) -> Gross domestic product
E5: =IF(INDIRECT("beschriftung!"&ADDRESS(beschriftung!$C$1*12+ROW(beschriftung!$A6)-1,COLUMN(beschriftung!E$1)))="","",INDIRECT("beschriftung!"&ADDRESS(beschriftung!$C$1*12+ROW(beschriftung!$A6)-1,COLUMN(beschriftung!E$1)))) -> Internal demand | Y5: =IF(INDIRECT("beschriftung!"&ADDRESS(beschriftung!$C$1*12+ROW(beschriftung!$A6)-1,COLUMN(beschriftung!Y$1)))="","",INDIRECT("beschriftung!"&ADDRESS(beschriftung!$C$1*12+ROW(beschriftung!$A6)-1,COLUMN(beschriftung!Y$1)))) -> Trade balance (goods and services) | AU5: =IF(INDIRECT("beschriftung!"&ADDRESS(beschriftung!$C$1*12+ROW(beschriftung!$A6)-1,COLUMN(beschriftung!AU$1)))="","",INDIRECT("beschriftung!"&ADDRESS(beschriftung!$C$1*12+ROW(beschriftung!$A6)-1,COLUMN(beschriftung!AU$1)))) -> Global demand excluding inventories change, stat. discrepancies and valuables
G6: =IF(INDIRECT("beschriftung!"&ADDRESS(beschriftung!$C$1*12+ROW(beschriftung!$A7)-1,COLUMN(beschriftung!G$1)))="","",INDIRECT("beschriftung!"&ADDRESS(beschriftung!$C$1*12+ROW(beschriftung!$A7)-1,COLUMN(beschriftung!G$1)))) -> Final consumption expenditure | M6: =IF(INDIRECT("beschriftung!"&ADDRESS(beschriftung!$C$1*12+ROW(beschriftung!$A7)-1,COLUMN(beschriftung!M$1)))="","",INDIRECT("beschriftung!"&ADDRESS(beschriftung!$C$1*12+ROW(beschriftung!$A7)-1,COLUMN(beschriftung!M$1)))) -> Gross capital formation | AA6: =IF(INDIRECT("beschriftung!"&ADDRESS(beschriftung!$C$1*12+ROW(beschriftung!$A7)-1,COLUMN(beschriftung!AA$1)))="","",INDIRECT("beschriftung!"&ADDRESS(beschriftung!$C$1*12+ROW(beschriftung!$A7)-1,COLUMN(beschriftung!AA$1)))) -> Exports of goods and services | AK6: =IF(INDIRECT("beschriftung!"&ADDRESS(beschriftung!$C$1*12+ROW(beschriftung!$A7)-1,COLUMN(beschriftung!AK$1)))="","",INDIRECT("beschriftung!"&ADDRESS(beschriftung!$C$1*12+ROW(beschriftung!$A7)-1,COLUMN(beschriftung!AK$1)))) -> Imports of goods and services | AW6: =IF(INDIRECT("beschriftung!"&ADDRESS(beschriftung!$C$1*12+ROW(beschriftung!$A7)-1,COLUMN(beschriftung!AW$1)))="","",INDIRECT("beschriftung!"&ADDRESS(beschriftung!$C$1*12+ROW(beschriftung!$A7)-1,COLUMN(beschriftung!AW$1)))) -> Final domestic demand | AY6: =IF(INDIRECT("beschriftung!"&ADDRESS(beschriftung!$C$1*12+ROW(beschriftung!$A7)-1,COLUMN(beschriftung!AY$1)))="","",INDIRECT("beschriftung!"&ADDRESS(beschriftung!$C$1*12+ROW(beschriftung!$A7)-1,COLUMN(beschriftung!AY$1)))) -> Exports of goods and services (excluding valuables) | BC6: =IF(INDIRECT("beschriftung!"&ADDRESS(beschriftung!$C$1*12+ROW(beschriftung!$A7)-1,COLUMN(beschriftung!BC$1)))="","",INDIRECT("beschriftung!"&ADDRESS(beschriftung!$C$1*12+ROW(beschriftung!$A7)-1,COLUMN(beschriftung!BC$1)))) -> Imports of goods and services (excluding valuables)
I7: =IF(INDIRECT("beschriftung!"&ADDRESS(beschriftung!$C$1*12+ROW(beschriftung!$A8)-1,COLUMN(beschriftung!I$1)))="","",INDIRECT("beschriftung!"&ADDRESS(beschriftung!$C$1*12+ROW(beschriftung!$A8)-1,COLUMN(beschriftung!I$1)))) -> Households and NPISH | K7: =IF(INDIRECT("beschriftung!"&ADDRESS(beschriftung!$C$1*12+ROW(beschriftung!$A8)-1,COLUMN(beschriftung!K$1)))="","",INDIRECT("beschriftung!"&ADDRESS(beschriftung!$C$1*12+ROW(beschriftung!$A8)-1,COLUMN(beschriftung!K$1)))) -> General government | O7: =IF(INDIRECT("beschriftung!"&ADDRESS(beschriftung!$C$1*12+ROW(beschriftung!$A8)-1,COLUMN(beschriftung!O$1)))="","",INDIRECT("beschriftung!"&ADDRESS(beschriftung!$C$1*12+ROW(beschriftung!$A8)-1,COLUMN(beschriftung!O$1)))) -> Gross fixed capital formation | U7: =IF(INDIRECT("beschriftung!"&ADDRESS(beschriftung!$C$1*12+ROW(beschriftung!$A8)-1,COLUMN(beschriftung!U$1)))="","",INDIRECT("beschriftung!"&ADDRESS(beschriftung!$C$1*12+ROW(beschriftung!$A8)-1,COLUMN(beschriftung!U$1)))) -> Changes in inventories and statistical discrepancies | W7: =IF(INDIRECT("beschriftung!"&ADDRESS(beschriftung!$C$1*12+ROW(beschriftung!$A8)-1,COLUMN(beschriftung!W$1)))="","",INDIRECT("beschriftung!"&ADDRESS(beschriftung!$C$1*12+ROW(beschriftung!$A8)-1,COLUMN(beschriftung!W$1)))) -> Acquisitions less disposals of valuables (including non-monetary gold) | AC7: =IF(INDIRECT("beschriftung!"&ADDRESS(beschriftung!$C$1*12+ROW(beschriftung!$A8)-1,COLUMN(beschriftung!AC$1)))="","",INDIRECT("beschriftung!"&ADDRESS(beschriftung!$C$1*12+ROW(beschriftung!$A8)-1,COLUMN(beschriftung!AC$1)))) -> Exports (exp.) of goods | AI7: =IF(INDIRECT("beschriftung!"&ADDRESS(beschriftung!$C$1*12+ROW(beschriftung!$A8)-1,COLUMN(beschriftung!AI$1)))="","",INDIRECT("beschriftung!"&ADDRESS(beschriftung!$C$1*12+ROW(beschriftung!$A8)-1,COLUMN(beschriftung!AI$1)))) -> Exports of services | AM7: =IF(INDIRECT("beschriftung!"&ADDRESS(beschriftung!$C$1*12+ROW(beschriftung!$A8)-1,COLUMN(beschriftung!AM$1)))="","",INDIRECT("beschriftung!"&ADDRESS(beschriftung!$C$1*12+ROW(beschriftung!$A8)-1,COLUMN(beschriftung!AM$1)))) -> Imports (imp.) of goods | AS7: =IF(INDIRECT("beschriftung!"&ADDRESS(beschriftung!$C$1*12+ROW(beschriftung!$A8)-1,COLUMN(beschriftung!AS$1)))="","",INDIRECT("beschriftung!"&ADDRESS(beschriftung!$C$1*12+ROW(beschriftung!$A8)-1,COLUMN(beschriftung!AS$1)))) -> Imports of services | BA7: =IF(INDIRECT("beschriftung!"&ADDRESS(beschriftung!$C$1*12+ROW(beschriftung!$A8)-1,COLUMN(beschriftung!BA$1)))="","",INDIRECT("beschriftung!"&ADDRESS(beschriftung!$C$1*12+ROW(beschriftung!$A8)-1,COLUMN(beschriftung!BA$1)))) -> thereof exports of goods excluding valuables
Q8: =IF(INDIRECT("beschriftung!"&ADDRESS(beschriftung!$C$1*12+ROW(beschriftung!$A9)-1,COLUMN(beschriftung!Q$1)))="","",INDIRECT("beschriftung!"&ADDRESS(beschriftung!$C$1*12+ROW(beschriftung!$A9)-1,COLUMN(beschriftung!Q$1)))) -> Construction | S8: =IF(INDIRECT("beschriftung!"&ADDRESS(beschriftung!$C$1*12+ROW(beschriftung!$A9)-1,COLUMN(beschriftung!S$1)))="","",INDIRECT("beschriftung!"&ADDRESS(beschriftung!$C$1*12+ROW(beschriftung!$A9)-1,COLUMN(beschriftung!S$1)))) -> Fixed assets and software | AE8: =IF(INDIRECT("beschriftung!"&ADDRESS(beschriftung!$C$1*12+ROW(beschriftung!$A9)-1,COLUMN(beschriftung!AE$1)))="","",INDIRECT("beschriftung!"&ADDRESS(beschriftung!$C$1*12+ROW(beschriftung!$A9)-1,COLUMN(beschriftung!AE$1)))) -> thereof exp. of goods excluding non-monetary gold | AG8: =IF(INDIRECT("beschriftung!"&ADDRESS(beschriftung!$C$1*12+ROW(beschriftung!$A9)-1,COLUMN(beschriftung!AG$1)))="","",INDIRECT("beschriftung!"&ADDRESS(beschriftung!$C$1*12+ROW(beschriftung!$A9)-1,COLUMN(beschriftung!AG$1)))) -> thereof exp. of goods excluding valuables and merchanting | AO8: =IF(INDIRECT("beschriftung!"&ADDRESS(beschriftung!$C$1*12+ROW(beschriftung!$A9)-1,COLUMN(beschriftung!AO$1)))="","",INDIRECT("beschriftung!"&ADDRESS(beschriftung!$C$1*12+ROW(beschriftung!$A9)-1,COLUMN(beschriftung!AO$1)))) -> thereof imp. of goods excluding non-monetary gold | AQ8: =IF(INDIRECT("beschriftung!"&ADDRESS(beschriftung!$C$1*12+ROW(beschriftung!$A9)-1,COLUMN(beschriftung!AQ$1)))="","",INDIRECT("beschriftung!"&ADDRESS(beschriftung!$C$1*12+ROW(beschriftung!$A9)-1,COLUMN(beschriftung!AQ$1)))) -> thereof imp. of goods excluding valuables
C11: B1GQ | E11: P3_P5 | G11: P3 | I11: P31_S14_S15 | K11: P3_S13 | M11: P5 | O11: P51G | Q11: P5111_N111_112G | S11: P5111_N113T117G | U11: P52_YA0 | W11: P53 | Y11: B11 | AA11: P6 | AC11: P61 | AE11: P61XF11 | AI11: P62 | AK11: P7 | AM11: P71 | AO11: P71XF11 | AS11: P72 | AU11: P3_P51G_P6 | AW11: P3_P51G
A12: 1980 | B12: 1 | C12: 49949.522 | E12: 53377.882 | G12: 34114.172 | I12: 29329.145 | K12: 4785.0268 | M12: 19263.711 | O12: 15311.825 | Q12: 5993.4116 | S12: 9318.4131 | U12: 1546.7862 | W12: 2405.0998 | Y12: -3428.3608 | AA12: 22690.424 | AC12: 17301.694 | AE12: 12216.417 | AG12: 10833.144 | AI12: 5388.73 | AK12: 26118.785 | AM12: 22332.686 | AO12: 15273.155 | AQ12: 13660.879 | AS12: 3786.0983 | AU12: 65849.712 | AW12: 49425.996 | AY12: 16423.716 | BA12: 11034.986 | BC12: 17446.977
A13: 1980 | B13: 2 | C13: 51718.735 | E13: 53088.697 | G13: 34493.289 | I13: 29571.491 | K13: 4921.7984 | M13: 18595.408 | O13: 16858.367 | Q13: 7541.4991 | S13: 9316.8674 | U13: 1542.6461 | W13: 194.39491 | Y13: -1369.9618 | AA13: 23021.907 | AC13: 17437.254 | AE13: 12440.383 | AG13: 11149.811 | AI13: 5584.6525 | AK13: 24391.869 | AM13: 20005.745 | AO13: 14981.199 | AQ13: 13731.093 | AS13: 4386.1234 | AU13: 68293.305 | AW13: 51351.656 | AY13: 16941.649 | BA13: 11356.997 | BC13: 18117.216
A14: 1980 | B14: 3 | C14: 52002.73 | E14: 51918.6 | G14: 34865.014 | I14: 29856.173 | K14: 5008.8404 | M14: 17053.586 | O14: 16920.854 | Q14: 7747.7931 | S14: 9173.0609 | U14: 1063.6076 | W14: -930.87571 | Y14: 84.130231 | AA14: 24407.625 | AC14: 17966.476 | AE14: 12085.253 | AG14: 10876.17 | AI14: 6441.1494 | AK14: 24323.495 | AM14: 19619.425 | AO14: 14770.61 | AQ14: 13675.1 | AS14: 4704.07 | AU14: 69318.293 | AW14: 51785.868 | AY14: 17532.425 | BA14: 11091.276 | BC14: 18379.171
A15: 1980 | B15: 4 | C15: 54793.818 | E15: 55568.64 | G15: 36483.276 | I15: 31374.417 | K15: 5108.8593 | M15: 19085.364 | O15: 14435.029 | Q15: 4808.8753 | S15: 9626.1537 | U15: 5212.9916 | W15: -562.65692 | Y15: -774.82206 | AA15: 24580.705 | AC15: 19330.718 | AE15: 13366.489 | AG15: 11885.365 | AI15: 5249.9868 | AK15: 25355.527 | AM15: 21020.647 | AO15: 15726.542 | AQ15: 14368.991 | AS15: 4334.8798 | AU15: 68284.697 | AW15: 50918.305 | AY15: 17366.392 | BA15: 12116.405 | BC15: 18703.871
A16: 1981 | B16: 1 | C16: 52977.659 | D16: 0.060623949 | E16: 52852.973 | F16: -0.0098338375 | G16: 36161.29 | H16: 0.060007868 | I16: 30931.21 | J16: 0.054623673 | K16: 5230.0799 | L16: 0.093009527 | M16: 16691.683 | N16: -0.13351675 | O16: 16761.881 | P16: 0.094701744 | Q16: 7135.3293 | R16: 0.19052883 | S16: 9626.5519 | T16: 0.033067733 | U16: 777.39732 | W16: -847.59597 | Y16: 124.68593 | AA16: 25071.567 | AB16: 0.10494044 | AC16: 19110.778 | AD16: 0.10456112 | AE16: 12982.685 | AF16: 0.062724392 | AG16: 11523.117 | AH16: 0.063690988 | AI16: 5960.7887 | AJ16: 0.10615834 | AK16: 24946.881 | AL16: -0.044868226 | AM16: 20716.346 | AN16: -0.072375562 | AO16: 14993.45 | AP16: -0.018313498 | AQ16: 14224.32 | AR16: 0.041244876 | AS16: 4230.5355 | AT16: 0.1173866 | AU16: 70655.117 | AV16: 0.072975331 | AW16: 52923.172 | AX16: 0.070755786 | AY16: 17731.945 | AZ16: 0.079654894 | BA16: 11771.157 | BB16: 0.066712428 | BC16: 18454.855 | BD16: 0.057768085
A17: 1981 | B17: 2 | C17: 55522.014 | D17: 0.073537736 | E17: 55073.209 | F17: 0.037381076 | G17: 37131.589 | H17: 0.076487339 | I17: 31760.266 | J17: 0.074016396 | K17: 5371.3231 | L17: 0.091333429 | M17: 17941.62 | N17: -0.035158536 | O17: 18275.534 | P17: 0.084063166 | Q17: 8381.451 | R17: 0.1113773 | S17: 9894.0833 | T17: 0.061953851 | U17: 1039.45 | W17: -1373.3639 | Y17: 448.80429 | AA17: 26037.892 | AB17: 0.13100502 | AC17: 19808.34 | AD17: 0.13597818 | AE17: 13665.408 | AF17: 0.09847167 | AG17: 12055.619 | AH17: 0.081239819 | AI17: 6229.5517 | AJ17: 0.11547706 | AK17: 25589.088 | AL17: 0.049082716 | AM17: 20701.129 | AN17: 0.034759178 | AO17: 15599.046 | AP17: 0.041241548 | AQ17: 14581.932 | AR17: 0.061964405 | AS17: 4887.9593 | AT17: 0.11441445 | AU17: 73952.455 | AV17: 0.082865367 | AW17: 55407.123 | AX17: 0.078974426 | AY17: 18545.331 | AZ17: 0.094659155 | BA17: 12315.78 | BB17: 0.084422229 | BC17: 19469.891 | BD17: 0.074662403
A18: 1981 | B18: 3 | C18: 56051.232 | D18: 0.077851716 | E18: 56267.643 | F18: 0.083766569 | G18: 37611.005 | H18: 0.078760638 | I18: 32152.956 | J18: 0.076928235 | K18: 5458.0484 | L18: 0.089683038 | M18: 18656.638 | N18: 0.094000888 | O18: 18517.487 | P18: 0.094358914 | Q18: 8450.9974 | R18: 0.090761887 | S18: 10066.49 | T18: 0.097397051 | U18: 326.09405 | W18: -186.94338 | Y18: -216.41097 | AA18: 28182.214 | AB18: 0.15464793 | AC18: 20973.363 | AD18: 0.16736101 | AE18: 13825.796 | AF18: 0.14402204 | AG18: 12120.607 | AH18: 0.11441866 | AI18: 7208.8505 | AJ18: 0.11918698 | AK18: 28398.625 | AL18: 0.16753883 | AM18: 23195.805 | AN18: 0.18228769 | AO18: 15806.379 | AP18: 0.070123611 | AQ18: 14791.516 | AR18: 0.081638534 | AS18: 5202.8203 | AT18: 0.10602526 | AU18: 75719.474 | AV18: 0.092344754 | AW18: 56128.492 | AX18: 0.083857321 | AY18: 19590.982 | AZ18: 0.11741425 | BA18: 12382.131 | BB18: 0.11638475 | BC18: 19994.336 | BD18: 0.087880211
A19: 1981 | B19: 4 | C19: 59242.518 | D19: 0.081189828 | E19: 59457.952 | F19: 0.069991141 | G19: 39253.144 | H19: 0.075921588 | I19: 33672.639 | J19: 0.073251475 | K19: 5580.5052 | L19: 0.092319228 | M19: 20204.808 | N19: 0.058654594 | O19: 15297.362 | P19: 0.059738934 | Q19: 5215.8312 | R19: 0.084625993 | S19: 10081.531 | T19: 0.047306266 | U19: 5325.9801 | W19: -418.53436 | Y19: -215.43393 | AA19: 26587.652 | AB19: 0.081647234 | AC19: 20557.598 | AD19: 0.063467912 | AE19: 14304.692 | AF19: 0.070190685 | AG19: 12854.598 | AH19: 0.081548447 | AI19: 6030.0531 | AJ19: 0.14858442 | AK19: 26803.085 | AL19: 0.05709045 | AM19: 22011.669 | AN19: 0.047145182 | AO19: 15860.16 | AP19: 0.0084963442 | AQ19: 14983.688 | AR19: 0.042779429 | AS19: 4791.416 | AT19: 0.10531693 | AU19: 73691.643 | AV19: 0.079182392 | AW19: 54550.506 | AX19: 0.071333904 | AY19: 19141.136 | AZ19: 0.10219418 | BA19: 13111.083 | BB19: 0.082093481 | BC19: 19775.104 | BD19: 0.057273356
A20: 1982 | B20: 1 | C20: 57055.029 | D20: 0.076963957 | E20: 56665.379 | F20: 0.072132289 | G20: 38668.238 | H20: 0.069326843 | I20: 32953.116 | J20: 0.065367807 | K20: 5715.1226 | L20: 0.092740977 | M20: 17997.14 | N20: 0.078210078 | O20: 17060.528 | P20: 0.01781705 | Q20: 7351.8817 | R20: 0.030349311 | S20: 9708.6468 | T20: 0.0085279711 | U20: 705.06646 | W20: 231.5454 | Y20: 389.65028 | AA20: 25125.498 | AB20: 0.0021510712 | AC20: 18339.545 | AD20: -0.040355942 | AE20: 13400.831 | AF20: 0.032208024 | AG20: 11947.988 | AH20: 0.036871163 | AI20: 6785.9529 | AJ20: 0.13843205 | AK20: 24735.848 | AL20: -0.0084593188 | AM20: 20168.824 | AN20: -0.026429457 | AO20: 14592.219 | AP20: -0.026760458 | AQ20: 13786.168 | AR20: -0.030803006 | AS20: 4567.0237 | AT20: 0.079537955 | AU20: 74703.154 | AV20: 0.057292913 | AW20: 55728.767 | AX20: 0.053012609 | AY20: 18974.387 | AZ20: 0.070068007 | BA20: 12188.434 | BB20: 0.035449182 | BC20: 18353.192 | BD20: -0.0055087757
A21: 1982 | B21: 2 | C21: 59324.427 | D21: 0.068484787 | E21: 59939.517 | F21: 0.088360708 | G21: 39531.06 | H21: 0.064620748 | I21: 33696.693 | J21: 0.060970106 | K21: 5834.3674 | L21: 0.086206742 | M21: 20408.457 | N21: 0.13749242 | O21: 18347.307 | P21: 0.003927247 | Q21: 8251.177 | R21: -0.015543135 | S21: 10096.13 | T21: 0.020420948 | U21: 1285.6367 | W21: 775.51363 | Y21: -615.09018 | AA21: 25087.488 | AB21: -0.036500821 | AC21: 18114.704 | AD21: -0.085501184 | AE21: 13810.526 | AF21: 0.010619373 | AG21: 12408.487 | AH21: 0.029269974 | AI21: 6972.7838 | AJ21: 0.11930748 | AK21: 25702.578 | AL21: 0.0044350946 | AM21: 20590.093 | AN21: -0.0053637488 | AO21: 15100.584 | AP21: -0.031954651 | AQ21: 14339.22 | AR21: -0.016644665 | AS21: 5112.4849 | AT21: 0.045934442 | AU21: 77490.496 | AV21: 0.047842103 | AW21: 57878.367 | AX21: 0.04460155 | AY21: 19612.129 | AZ21: 0.057523769 | BA21: 12639.345 | BB21: 0.026272413 | BC21: 19451.705 | BD21: -0.00093404154
A22: 1982 | B22: 3 | C22: 59074.572 | D22: 0.053938874 | E22: 58853.631 | F22: 0.045958719 | G22: 39983.555 | H22: 0.063081291 | I22: 34077.632 | J22: 0.05985999 | K22: 5905.9235 | L22: 0.082057735 | M22: 18870.076 | N22: 0.011440326 | O22: 18091.596 | P22: -0.022999389 | Q22: 8301.8515 | R22: -0.01764832 | S22: 9789.745 | T22: -0.027491706 | U22: -87.38829 | W22: 865.86788 | Y22: 220.9406 | AA22: 26227.507 | AB22: -0.069359587 | AC22: 18319.937 | AD22: -0.12651412 | AE22: 12942.738 | AF22: -0.063870295 | AG22: 11980.701 | AH22: -0.011542799 | AI22: 7907.5704 | AJ22: 0.096925288 | AK22: 26006.567 | AL22: -0.084231483 | AM22: 20563.73 | AN22: -0.113472 | AO22: 14297.753 | AP22: -0.095444129 | AQ22: 13585.03 | AR22: -0.081566064 | AS22: 5442.8362 | AT22: 0.046131891 | AU22: 78189.826 | AV22: 0.032625067 | AW22: 58075.152 | AX22: 0.034682205 | AY22: 20114.675 | AZ22: 0.026731333 | BA22: 12207.104 | BB22: -0.014135439 | BC22: 19027.866 | BD22: -0.048337178
A23: 1982 | B23: 4 | C23: 61638.11 | D23: 0.040437042 | E23: 61432.631 | F23: 0.03321135 | G23: 41637.118 | H23: 0.060733332 | I23: 35587.426 | J23: 0.056864786 | K23: 6049.692 | L23: 0.084076052 | M23: 19795.513 | N23: -0.020257326 | O23: 15722.015 | P23: 0.027759862 | Q23: 5672.3045 | R23: 0.087516898 | S23: 10049.71 | T23: -0.0031563359 | U23: 4074.4915 | W23: -0.99383635 | Y23: 205.47937 | AA23: 26660.41 | AB23: 0.0027365421 | AC23: 19885.546 | AD23: -0.032691188 | AE23: 14330.536 | AF23: 0.0018066797 | AG23: 12969.484 | AH23: 0.0089373523 | AI23: 6774.8636 | AJ23: 0.12351641 | AK23: 26454.93 | AL23: -0.012989366 | AM23: 21360.536 | AN23: -0.029581263 | AO23: 15663.774 | AP23: -0.012382324 | AQ23: 14671.349 | AR23: -0.020845311 | AS23: 5094.3939 | AT23: 0.063233481 | AU23: 77329.362 | AV23: 0.049364065 | AW23: 57359.133 | AX23: 0.051486725 | AY23: 19970.228 | AZ23: 0.043314675 | BA23: 13195.365 | BB23: 0.0064282678 | BC23: 19765.743 | BD23: -0.00047341044
A24: 1983 | B24: 1 | C24: 59277.027 | D24: 0.038944827 | E24: 60218.675 | F24: 0.062706649 | G24: 41299.978 | H24: 0.068059461 | I24: 35184.502 | J24: 0.067713971 | K24: 6115.4758 | L24: 0.070051541 | M24: 18918.697 | N24: 0.051205723 | O24: 17567.462 | P24: 0.02971385 | Q24: 7345.011 | R24: -0.00093455274 | S24: 10222.452 | T24: 0.052922381 | U24: -218.21226 | W24: 1569.4467 | Y24: -941.64753 | AA24: 25447.678 | AB24: 0.012822825 | AC24: 18000.733 | AD24: -0.018474371 | AE24: 13508.261 | AF24: 0.0080166293 | AG24: 12355.302 | AH24: 0.034090587 | AI24: 7446.9443 | AJ24: 0.097405836 | AK24: 26389.325 | AL24: 0.066845402 | AM24: 21437.117 | AN24: 0.06288385 | AO24: 15347.991 | AP24: 0.051792833 | AQ24: 14439.456 | AR24: 0.047387243 | AS24: 4952.208 | AT24: 0.08434035 | AU24: 78886.904 | AV24: 0.056004996 | AW24: 58867.44 | AX24: 0.056320526 | AY24: 20019.464 | AZ24: 0.055078267 | BA24: 12572.519 | BB24: 0.031512248 | BC24: 19391.665 | BD24: 0.056582685
A25: 1983 | B25: 2 | C25: 60666.89 | D25: 0.022629169 | E25: 61588.187 | F25: 0.027505548 | G25: 41277.565 | H25: 0.044180563 | I25: 35058.161 | J25: 0.040403621 | K25: 6219.4034 | L25: 0.065994489 | M25: 20310.622 | N25: -0.0047938552 | O25: 19330.39 | P25: 0.053581873 | Q25: 8588.0116 | R25: 0.040822615 | S25: 10742.378 | T25: 0.064009523 | U25: -144.88494 | W25: 1125.117 | Y25: -921.29698 | AA25: 25670.539 | AB25: 0.023240712 | AC25: 18224.574 | AD25: 0.0060652727 | AE25: 13898.091 | AF25: 0.0063404185 | AG25: 12505.357 | AH25: 0.0078068002 | AI25: 7445.9643 | AJ25: 0.067861054 | AK25: 26591.836 | AL25: 0.034598003 | AM25: 21382.689 | AN25: 0.038494049 | AO25: 15818.377 | AP25: 0.047534076 | AQ25: 14758.348 | AR25: 0.029229492 | AS25: 5209.1468 | AT25: 0.018907015 | AU25: 80779.27 | AV25: 0.042440999 | AW25: 60607.955 | AX25: 0.047160756 | AY25: 20171.315 | AZ25: 0.028512279 | BA25: 12725.351 | BB25: 0.0068046264 | BC25: 19967.495 | BD25: 0.026516439
A26: 1983 | B26: 3 | C26: 60588.291 | D26: 0.025623865 | E26: 61056.068 | F26: 0.03742227 | G26: 41564.015 | H26: 0.03952773 | I26: 35303.227 | J26: 0.035964789 | K26: 6260.7879 | L26: 0.060086174 | M26: 19492.053 | N26: 0.032961038 | O26: 19026.492 | P26: 0.051675694 | Q26: 8858.7234 | R26: 0.067078034 | S26: 10167.769 | T26: 0.038614277 | U26: -1075.0877 | W26: 1540.6487 | Y26: -467.77707 | AA26: 25722.939 | AB26: -0.01923813 | AC26: 17622.553 | AD26: -0.038066911 | AE26: 13330.107 | AF26: 0.029929445 | AG26: 12216.929 | AH26: 0.019717368 | AI26: 8100.3856 | AJ26: 0.024383621 | AK26: 26190.716 | AL26: 0.0070808833 | AM26: 20768.892 | AN26: 0.0099768622 | AO26: 15092.786 | AP26: 0.055605446 | AQ26: 14047.291 | AR26: 0.034027262 | AS26: 5421.8242 | AT26: -0.0038604947 | AU26: 81132.494 | AV26: 0.037634916 | AW26: 60590.507 | AX26: 0.043312069 | AY26: 20541.987 | AZ26: 0.021243819 | BA26: 12441.601 | BB26: 0.019209905 | BC26: 19469.115 | BD26: 0.023189638
A27: 1983 | B27: 4 | C27: 63722.697 | D27: 0.033819774 | E27: 64983.683 | F27: 0.057804007 | G27: 43282.429 | H27: 0.039515468 | I27: 36974.129 | J27: 0.038966075 | K27: 6308.2999 | L27: 0.042747279 | M27: 21701.255 | N27: 0.096271415 | O27: 17045.865 | P27: 0.084203561 | Q27: 6432.088 | R27: 0.13394617 | S27: 10613.777 | T27: 0.056127604 | U27: 3362.7997 | W27: 1292.5903 | Y27: -1260.9859 | AA27: 26266.638 | AB27: -0.014769907 | AC27: 19237.882 | AD27: -0.032569616 | AE27: 14784.884 | AF27: 0.03170489 | AG27: 13372.076 | AH27: 0.031041514 | AI27: 7028.7565 | AJ27: 0.037475712 | AK27: 27527.624 | AL27: 0.04054796 | AM27: 22234.465 | AN27: 0.040913226 | AO27: 16473.367 | AP27: 0.051685681 | AQ27: 15312.119 | AR27: 0.043674932 | AS27: 5293.1589 | AT27: 0.03901642 | AU27: 80965.176 | AV27: 0.04701725 | AW27: 60328.293 | AX27: 0.051764378 | AY27: 20636.882 | AZ27: 0.033382398 | BA27: 13608.126 | BB27: 0.031280778 | BC27: 20605.278 | BD27: 0.042474254
... A195: 2025 | B195: 4 | C195: 218871.5 | D195: 0.0042451134 | E195: 210061.77 | F195: 0.090250895 | G195: 135805.63 | H195: 0.017690049 | I195: 109492.63 | J195: 0.017756443 | K195: 26313 | L195: 0.017413866 | M195: 74256.132 | N195: 0.25373608 | O195: 58778.431 | P195: 0.010194846 | Q195: 17784.795 | R195: 0.026636236 | S195: 40993.636 | T195: 0.0032245297 | U195: 11185.451 | W195: 4292.2498 | Y195: 8809.7384 | AA195: 169838.97 | AB195: 0.075179931 | AC195: 129180.69 | AD195: 0.12537139 | AE195: 88381.99 | AF195: -0.00077957923 | AG195: 67145.341 | AH195: -0.065598147 | AI195: 40658.286 | AJ195: -0.058267452 | AK195: 161029.24 | AL195: 0.21357592 | AM195: 114717.09 | AN195: 0.33864598 | AO195: 65452.501 | AP195: 0.080739664 | AQ195: 62174.455 | AR195: 0.073279963 | AS195: 46312.145 | AT195: -0.014499151 | AU195: 316172.65 | AV195: -0.0082036806 | AW195: 194584.07 | AX195: 0.015414259 | AY195: 121588.59 | AZ195: -0.043796591 | BA195: 80930.303 | BB195: -0.036357486 | BC195: 108486.6 | BD195: 0.033964917

Sheet real_q
A1: =IF(INDIRECT("beschriftung!"&ADDRESS(beschriftung!$C$1*12+ROW(beschriftung!$A1)-1,COLUMN(beschriftung!A$1)))="","",INDIRECT("beschriftung!"&ADDRESS(beschriftung!$C$1*12+ROW(beschriftung!$A1)-1,COLUMN(beschriftung!A$1)))) -> ESA 2010, Quarterly aggregates of Gross Domestic Product, expenditure approach, raw data
A2: =IF(INDIRECT("beschriftung!"&ADDRESS(beschriftung!$C$1*12+ROW(beschriftung!$A3)-1,COLUMN(beschriftung!A$1)))="","",INDIRECT("beschriftung!"&ADDRESS(beschriftung!$C$1*12+ROW(beschriftung!$A3)-1,COLUMN(beschriftung!A$1)))) -> In Mio. Swiss Francs, at prices of preceding year, chained values, reference year 2020, percentage change to previous year
A3: =IF(INDIRECT("beschriftung!"&ADDRESS(beschriftung!$C$1*12+ROW(beschriftung!$A5)-1,COLUMN(beschriftung!A$1)))="","",INDIRECT("beschriftung!"&ADDRESS(beschriftung!$C$1*12+ROW(beschriftung!$A5)-1,COLUMN(beschriftung!A$1))))
C4: =IF(INDIRECT("beschriftung!"&ADDRESS(beschriftung!$C$1*12+ROW(beschriftung!$A5)-1,COLUMN(beschriftung!C$1)))="","",INDIRECT("beschriftung!"&ADDRESS(beschriftung!$C$1*12+ROW(beschriftung!$A5)-1,COLUMN(beschriftung!C$1)))) -> Gross domestic product
E5: =IF(INDIRECT("beschriftung!"&ADDRESS(beschriftung!$C$1*12+ROW(beschriftung!$A6)-1,COLUMN(beschriftung!E$1)))="","",INDIRECT("beschriftung!"&ADDRESS(beschriftung!$C$1*12+ROW(beschriftung!$A6)-1,COLUMN(beschriftung!E$1)))) -> Internal demand | Y5: =IF(INDIRECT("beschriftung!"&ADDRESS(beschriftung!$C$1*12+ROW(beschriftung!$A6)-1,COLUMN(beschriftung!Y$1)))="","",INDIRECT("beschriftung!"&ADDRESS(beschriftung!$C$1*12+ROW(beschriftung!$A6)-1,COLUMN(beschriftung!Y$1)))) -> Trade balance (goods and services) | AU5: =IF(INDIRECT("beschriftung!"&ADDRESS(beschriftung!$C$1*12+ROW(beschriftung!$A6)-1,COLUMN(beschriftung!AU$1)))="","",INDIRECT("beschriftung!"&ADDRESS(beschriftung!$C$1*12+ROW(beschriftung!$A6)-1,COLUMN(beschriftung!AU$1)))) -> Global demand excluding inventories change, stat. discrepancies and valuables
G6: =IF(INDIRECT("beschriftung!"&ADDRESS(beschriftung!$C$1*12+ROW(beschriftung!$A7)-1,COLUMN(beschriftung!G$1)))="","",INDIRECT("beschriftung!"&ADDRESS(beschriftung!$C$1*12+ROW(beschriftung!$A7)-1,COLUMN(beschriftung!G$1)))) -> Final consumption expenditure | M6: =IF(INDIRECT("beschriftung!"&ADDRESS(beschriftung!$C$1*12+ROW(beschriftung!$A7)-1,COLUMN(beschriftung!M$1)))="","",INDIRECT("beschriftung!"&ADDRESS(beschriftung!$C$1*12+ROW(beschriftung!$A7)-1,COLUMN(beschriftung!M$1)))) -> Gross capital formation | AA6: =IF(INDIRECT("beschriftung!"&ADDRESS(beschriftung!$C$1*12+ROW(beschriftung!$A7)-1,COLUMN(beschriftung!AA$1)))="","",INDIRECT("beschriftung!"&ADDRESS(beschriftung!$C$1*12+ROW(beschriftung!$A7)-1,COLUMN(beschriftung!AA$1)))) -> Exports of goods and services | AK6: =IF(INDIRECT("beschriftung!"&ADDRESS(beschriftung!$C$1*12+ROW(beschriftung!$A7)-1,COLUMN(beschriftung!AK$1)))="","",INDIRECT("beschriftung!"&ADDRESS(beschriftung!$C$1*12+ROW(beschriftung!$A7)-1,COLUMN(beschriftung!AK$1)))) -> Imports of goods and services | AW6: =IF(INDIRECT("beschriftung!"&ADDRESS(beschriftung!$C$1*12+ROW(beschriftung!$A7)-1,COLUMN(beschriftung!AW$1)))="","",INDIRECT("beschriftung!"&ADDRESS(beschriftung!$C$1*12+ROW(beschriftung!$A7)-1,COLUMN(beschriftung!AW$1)))) -> Final domestic demand | AY6: =IF(INDIRECT("beschriftung!"&ADDRESS(beschriftung!$C$1*12+ROW(beschriftung!$A7)-1,COLUMN(beschriftung!AY$1)))="","",INDIRECT("beschriftung!"&ADDRESS(beschriftung!$C$1*12+ROW(beschriftung!$A7)-1,COLUMN(beschriftung!AY$1)))) -> Exports of goods and services (excluding valuables) | BC6: =IF(INDIRECT("beschriftung!"&ADDRESS(beschriftung!$C$1*12+ROW(beschriftung!$A7)-1,COLUMN(beschriftung!BC$1)))="","",INDIRECT("beschriftung!"&ADDRESS(beschriftung!$C$1*12+ROW(beschriftung!$A7)-1,COLUMN(beschriftung!BC$1)))) -> Imports of goods and services (excluding valuables)
I7: =IF(INDIRECT("beschriftung!"&ADDRESS(beschriftung!$C$1*12+ROW(beschriftung!$A8)-1,COLUMN(beschriftung!I$1)))="","",INDIRECT("beschriftung!"&ADDRESS(beschriftung!$C$1*12+ROW(beschriftung!$A8)-1,COLUMN(beschriftung!I$1)))) -> Households and NPISH | K7: =IF(INDIRECT("beschriftung!"&ADDRESS(beschriftung!$C$1*12+ROW(beschriftung!$A8)-1,COLUMN(beschriftung!K$1)))="","",INDIRECT("beschriftung!"&ADDRESS(beschriftung!$C$1*12+ROW(beschriftung!$A8)-1,COLUMN(beschriftung!K$1)))) -> General government | O7: =IF(INDIRECT("beschriftung!"&ADDRESS(beschriftung!$C$1*12+ROW(beschriftung!$A8)-1,COLUMN(beschriftung!O$1)))="","",INDIRECT("beschriftung!"&ADDRESS(beschriftung!$C$1*12+ROW(beschriftung!$A8)-1,COLUMN(beschriftung!O$1)))) -> Gross fixed capital formation | U7: =IF(INDIRECT("beschriftung!"&ADDRESS(beschriftung!$C$1*12+ROW(beschriftung!$A8)-1,COLUMN(beschriftung!U$1)))="","",INDIRECT("beschriftung!"&ADDRESS(beschriftung!$C$1*12+ROW(beschriftung!$A8)-1,COLUMN(beschriftung!U$1)))) -> Changes in inventories and statistical discrepancies | W7: =IF(INDIRECT("beschriftung!"&ADDRESS(beschriftung!$C$1*12+ROW(beschriftung!$A8)-1,COLUMN(beschriftung!W$1)))="","",INDIRECT("beschriftung!"&ADDRESS(beschriftung!$C$1*12+ROW(beschriftung!$A8)-1,COLUMN(beschriftung!W$1)))) -> Acquisitions less disposals of valuables (including non-monetary gold) | AC7: =IF(INDIRECT("beschriftung!"&ADDRESS(beschriftung!$C$1*12+ROW(beschriftung!$A8)-1,COLUMN(beschriftung!AC$1)))="","",INDIRECT("beschriftung!"&ADDRESS(beschriftung!$C$1*12+ROW(beschriftung!$A8)-1,COLUMN(beschriftung!AC$1)))) -> Exports (exp.) of goods | AI7: =IF(INDIRECT("beschriftung!"&ADDRESS(beschriftung!$C$1*12+ROW(beschriftung!$A8)-1,COLUMN(beschriftung!AI$1)))="","",INDIRECT("beschriftung!"&ADDRESS(beschriftung!$C$1*12+ROW(beschriftung!$A8)-1,COLUMN(beschriftung!AI$1)))) -> Exports of services | AM7: =IF(INDIRECT("beschriftung!"&ADDRESS(beschriftung!$C$1*12+ROW(beschriftung!$A8)-1,COLUMN(beschriftung!AM$1)))="","",INDIRECT("beschriftung!"&ADDRESS(beschriftung!$C$1*12+ROW(beschriftung!$A8)-1,COLUMN(beschriftung!AM$1)))) -> Imports (imp.) of goods | AS7: =IF(INDIRECT("beschriftung!"&ADDRESS(beschriftung!$C$1*12+ROW(beschriftung!$A8)-1,COLUMN(beschriftung!AS$1)))="","",INDIRECT("beschriftung!"&ADDRESS(beschriftung!$C$1*12+ROW(beschriftung!$A8)-1,COLUMN(beschriftung!AS$1)))) -> Imports of services | BA7: =IF(INDIRECT("beschriftung!"&ADDRESS(beschriftung!$C$1*12+ROW(beschriftung!$A8)-1,COLUMN(beschriftung!BA$1)))="","",INDIRECT("beschriftung!"&ADDRESS(beschriftung!$C$1*12+ROW(beschriftung!$A8)-1,COLUMN(beschriftung!BA$1)))) -> thereof exports of goods excluding valuables
Q8: =IF(INDIRECT("beschriftung!"&ADDRESS(beschriftung!$C$1*12+ROW(beschriftung!$A9)-1,COLUMN(beschriftung!Q$1)))="","",INDIRECT("beschriftung!"&ADDRESS(beschriftung!$C$1*12+ROW(beschriftung!$A9)-1,COLUMN(beschriftung!Q$1)))) -> Construction | S8: =IF(INDIRECT("beschriftung!"&ADDRESS(beschriftung!$C$1*12+ROW(beschriftung!$A9)-1,COLUMN(beschriftung!S$1)))="","",INDIRECT("beschriftung!"&ADDRESS(beschriftung!$C$1*12+ROW(beschriftung!$A9)-1,COLUMN(beschriftung!S$1)))) -> Fixed assets and software | AE8: =IF(INDIRECT("beschriftung!"&ADDRESS(beschriftung!$C$1*12+ROW(beschriftung!$A9)-1,COLUMN(beschriftung!AE$1)))="","",INDIRECT("beschriftung!"&ADDRESS(beschriftung!$C$1*12+ROW(beschriftung!$A9)-1,COLUMN(beschriftung!AE$1)))) -> thereof exp. of goods excluding non-monetary gold | AG8: =IF(INDIRECT("beschriftung!"&ADDRESS(beschriftung!$C$1*12+ROW(beschriftung!$A9)-1,COLUMN(beschriftung!AG$1)))="","",INDIRECT("beschriftung!"&ADDRESS(beschriftung!$C$1*12+ROW(beschriftung!$A9)-1,COLUMN(beschriftung!AG$1)))) -> thereof exp. of goods excluding valuables and merchanting | AO8: =IF(INDIRECT("beschriftung!"&ADDRESS(beschriftung!$C$1*12+ROW(beschriftung!$A9)-1,COLUMN(beschriftung!AO$1)))="","",INDIRECT("beschriftung!"&ADDRESS(beschriftung!$C$1*12+ROW(beschriftung!$A9)-1,COLUMN(beschriftung!AO$1)))) -> thereof imp. of goods excluding non-monetary gold | AQ8: =IF(INDIRECT("beschriftung!"&ADDRESS(beschriftung!$C$1*12+ROW(beschriftung!$A9)-1,COLUMN(beschriftung!AQ$1)))="","",INDIRECT("beschriftung!"&ADDRESS(beschriftung!$C$1*12+ROW(beschriftung!$A9)-1,COLUMN(beschriftung!AQ$1)))) -> thereof imp. of goods excluding valuables
C11: B1GQ | E11: P3_P5 | G11: P3 | I11: P31_S14_S15 | K11: P3_S13 | M11: P5 | O11: P51G | Q11: P5111_N111_112G | S11: P5111_N113T117G | U11: P52_YA0 | W11: P53 | Y11: B11 | AA11: P6 | AC11: P61 | AE11: P61XF11 | AI11: P62 | AK11: P7 | AM11: P71 | AO11: P71XF11 | AS11: P72 | AU11: P3_P51G_P6 | AW11: P3_P51G
A12: 1980 | B12: 1 | C12: 89202.399 | E12: 92357.382 | G12: 60814.338 | I12: 50068.035 | K12: 10535.181 | M12: 31468.772 | O12: 20462.884 | Q12: 9713.5761 | S12: 11334.433 | AA12: 26200.076 | AC12: 17667.739 | AE12: 13357.215 | AG12: 12475.509 | AI12: 8673.1772 | AK12: 26587.017 | AM12: 21377.174 | AO12: 13558.444 | AQ12: 12525.712 | AS12: 5213.9907 | AU12: 100518.77 | AW12: 80947.185 | AY12: 21695.315 | BA12: 13108.949 | BC12: 18178.392
A13: 1980 | B13: 2 | C13: 91839.7 | E13: 90963.012 | G13: 60954.519 | I13: 50042.452 | K13: 10741.307 | M13: 30010.45 | O13: 22306.056 | Q13: 12014.786 | S13: 11283.842 | AA13: 26912.388 | AC13: 18047.76 | AE13: 13305.687 | AG13: 12559.107 | AI13: 9062.7049 | AK13: 24943.184 | AM13: 19362.38 | AO13: 13038.872 | AQ13: 12324.476 | AS13: 5884.8215 | AU13: 103234.15 | AW13: 83333.965 | AY13: 22122.499 | BA13: 13199.873 | BC13: 18459.329
A14: 1980 | B14: 3 | C14: 91077.899 | E14: 87721.607 | G14: 60916.406 | I14: 49915.605 | K14: 10857.658 | M14: 26994.173 | O14: 22278.056 | Q14: 12338.989 | S14: 11012.279 | AA14: 27963.718 | AC14: 18069.741 | AE14: 13152.381 | AG14: 12479.405 | AI14: 10537.441 | AK14: 24361.273 | AM14: 18523.582 | AO14: 13039.536 | AQ14: 12416.344 | AS14: 6293.7505 | AU14: 104462.54 | AW14: 83264.98 | AY14: 23227.076 | BA14: 13125.104 | BC14: 18872.175
A15: 1980 | B15: 4 | C15: 95603.79 | E15: 93337.065 | G15: 63231.804 | I15: 52086.789 | K15: 10917.06 | M15: 30165.098 | O15: 18701.035 | Q15: 7518.3853 | S15: 11386.866 | AA15: 27605.89 | AC15: 18980.141 | AE15: 14164.268 | AG15: 13097.336 | AI15: 8578.3288 | AK15: 24798.015 | AM15: 19385.905 | AO15: 13480.804 | AQ15: 12543.022 | AS15: 5655.5234 | AU15: 101374.06 | AW15: 81012.242 | AY15: 22384.597 | BA15: 13777.245 | BC15: 18532.853
A16: 1981 | B16: 1 | C16: 90183.601 | D16: 0.010999723 | E16: 86051.538 | F16: -0.068276558 | G16: 61421.521 | H16: 0.0099842205 | I16: 50333.656 | J16: 0.0053052172 | K16: 10942.568 | L16: 0.038669217 | M16: 24964.643 | N16: -0.20668518 | O16: 21103.965 | P16: 0.031328933 | Q16: 10765.542 | R16: 0.10829854 | S16: 11128.156 | T16: -0.018199135 | AA16: 28798.628 | AB16: 0.099181091 | AC16: 19418.117 | AD16: 0.09907198 | AE16: 13791.255 | AF16: 0.032494799 | AG16: 12630.333 | AH16: 0.012410253 | AI16: 9544.909 | AJ16: 0.10050893 | AK16: 24617.61 | AL16: -0.074074018 | AM16: 19375.903 | AN16: -0.093617189 | AO16: 12560.464 | AP16: -0.073605792 | AQ16: 12074.625 | AR16: -0.036012927 | AS16: 5427.3877 | AT16: 0.040927773 | AU16: 102857.66 | AV16: 0.023268212 | AW16: 82291.017 | AX16: 0.016601338 | AY16: 22634.576 | AZ16: 0.043293285 | BA16: 13311.445 | BB16: 0.015447155 | BC16: 17827.487 | BD16: -0.019303464
A17: 1981 | B17: 2 | C17: 93716.463 | D17: 0.020435211 | E17: 88386.639 | F17: -0.028323305 | G17: 61958.844 | H17: 0.016476626 | I17: 50781.396 | J17: 0.014766331 | K17: 11028.725 | L17: 0.026758182 | M17: 26672.617 | N17: -0.11122236 | O17: 22585.689 | P17: 0.012536182 | Q17: 12421.397 | R17: 0.033842506 | S17: 11230.415 | T17: -0.0047347781 | AA17: 30143.463 | AB17: 0.120059 | AC17: 20421.716 | AD17: 0.13153742 | AE17: 14629.804 | AF17: 0.099515184 | AG17: 13122.235 | AH17: 0.044838293 | AI17: 9834.7977 | AJ17: 0.085194524 | AK17: 25160.442 | AL17: 0.00871011 | AM17: 19413.689 | AN17: 0.0026499546 | AO17: 13008.758 | AP17: -0.0023095908 | AQ17: 12135.781 | AR17: -0.015310595 | AS17: 6097.3185 | AT17: 0.036109333 | AU17: 105948.74 | AV17: 0.026295415 | AW17: 84599.599 | AX17: 0.015187487 | AY17: 23448.196 | AZ17: 0.059925267 | BA17: 13828.124 | BB17: 0.047595228 | BC17: 18406.74 | BD17: -0.0028488992
A18: 1981 | B18: 3 | C18: 92951.665 | D18: 0.020573229 | E18: 89214.869 | F18: 0.017022746 | G18: 61637.068 | H18: 0.011830341 | I18: 50474.767 | J18: 0.01120216 | K18: 11026.823 | L18: 0.015580318 | M18: 27745.912 | N18: 0.027848196 | O18: 22677.54 | P18: 0.017931762 | Q18: 12510.82 | R18: 0.013925798 | S18: 11246.731 | T18: 0.02129004 | AA18: 33580.996 | AB18: 0.20087735 | AC18: 22650.926 | AD18: 0.25352798 | AE18: 15202.877 | AF18: 0.15590302 | AG18: 13334.22 | AH18: 0.068498063 | AI18: 11116.774 | AJ18: 0.054978587 | AK18: 29095.168 | AL18: 0.19432052 | AM18: 22777.542 | AN18: 0.22965101 | AO18: 13378.605 | AP18: 0.02600313 | AQ18: 12358.229 | AR18: -0.0046804924 | AS18: 6587.6688 | AT18: 0.046700019 | AU18: 107244.74 | AV18: 0.026633466 | AW18: 84416.404 | AX18: 0.013828424 | AY18: 24723.266 | AZ18: 0.064415751 | BA18: 14043.838 | BB18: 0.069998219 | BC18: 19032.275 | BD18: 0.0084833648
A19: 1981 | B19: 4 | C19: 96760.551 | D19: 0.012099533 | E19: 94570.787 | F19: 0.013217918 | G19: 63725.908 | H19: 0.0078141691 | I19: 52469.429 | J19: 0.007346198 | K19: 11033.805 | L19: 0.010693768 | M19: 30881.991 | N19: 0.023765675 | O19: 18482.387 | P19: -0.011691751 | Q19: 7620.1404 | R19: 0.01353417 | S19: 11110.01 | T19: -0.024313637 | AA19: 32651.693 | AB19: 0.18277994 | AC19: 23030.385 | AD19: 0.21339381 | AE19: 15346.841 | AF19: 0.083489866 | AG19: 13607.502 | AH19: 0.03895195 | AI19: 9189.3434 | AJ19: 0.071227697 | AK19: 29271.867 | AL19: 0.1804117 | AM19: 23176.549 | AN19: 0.19553612 | AO19: 13938.196 | AP19: 0.033929151 | AQ19: 12949.401 | AR19: 0.032398821 | AS19: 6259.3785 | AT19: 0.10677264 | AU19: 102801.47 | AV19: 0.014080657 | AW19: 81197.716 | AX19: 0.0022894667 | AY19: 23472.774 | AZ19: 0.048612744 | BA19: 14313.247 | BB19: 0.038904829 | BC19: 19453.005 | BD19: 0.049649754
A20: 1982 | B20: 1 | C20: 90694.538 | D20: 0.0056655212 | E20: 88608.207 | F20: 0.029710898 | G20: 61745.137 | H20: 0.0052687646 | I20: 50591.347 | J20: 0.0051196523 | K20: 11009.336 | L20: 0.0061016384 | M20: 27077.666 | N20: 0.084640639 | O20: 20276.338 | P20: -0.039216649 | Q20: 10476.565 | R20: -0.026842758 | S20: 10590.624 | T20: -0.048303759 | AA20: 31243.201 | AB20: 0.08488505 | AC20: 21311.327 | AD20: 0.097497111 | AE20: 14592.434 | AF20: 0.058093194 | AG20: 12633.968 | AH20: 0.00028774276 | AI20: 9956.039 | AJ20: 0.043073227 | AK20: 28046.749 | AL20: 0.1392962 | AM20: 22167.832 | AN20: 0.14409283 | AO20: 13156.955 | AP20: 0.047489582 | AQ20: 12146.645 | AR20: 0.0059645877 | AS20: 6072.8861 | AT20: 0.11893354 | AU20: 102534.88 | AV20: -0.0031381286 | AW20: 81569.082 | AX20: -0.0087729451 | AY20: 22936.913 | AZ20: 0.013357274 | BA20: 13285.825 | BB20: -0.0019245972 | BC20: 18399.815 | BD20: 0.0321037
A21: 1982 | B21: 2 | C21: 92530.262 | D21: -0.012657346 | E21: 91764.07 | F21: 0.038212014 | G21: 62041.935 | H21: 0.0013410581 | I21: 50857.942 | J21: 0.0015073804 | K21: 11032.254 | L21: 0.00031995186 | M21: 29764.955 | N21: 0.11593681 | O21: 21563.285 | P21: -0.04526781 | Q21: 11634.695 | R21: -0.063334394 | S21: 10888.287 | T21: -0.030464406 | AA21: 30591.141 | AB21: 0.014851597 | AC21: 20764.738 | AD21: 0.016796935 | AE21: 14858.105 | AF21: 0.015605169 | AG21: 12736.193 | AH21: -0.02941896 | AI21: 9897.7224 | AJ21: 0.0063981689 | AK21: 28373.191 | AL21: 0.12769047 | AM21: 22143.205 | AN21: 0.14059749 | AO21: 13222.165 | AP21: 0.016404924 | AQ21: 12163.666 | AR21: 0.0022976855 | AS21: 6511.9836 | AT21: 0.068007784 | AU21: 104339.57 | AV21: -0.015188205 | AW21: 83426.588 | AX21: -0.013865437 | AY21: 22991.395 | AZ21: -0.01948126 | BA21: 13376.171 | BB21: -0.032683611 | BC21: 18750.343 | BD21: 0.018667252
A22: 1982 | B22: 3 | C22: 90924.24 | D22: -0.021811611 | E22: 88517.022 | F22: -0.0078220978 | G22: 61794.252 | H22: 0.0025501487 | I22: 50610.16 | J22: 0.0026823922 | K22: 11045.555 | L22: 0.0016987174 | M22: 26947.771 | N22: -0.028766074 | O22: 21188.398 | P22: -0.065665953 | Q22: 11745.181 | R22: -0.061198088 | S22: 10461.474 | T22: -0.069820834 | AA22: 30430.323 | AB22: -0.093823079 | AC22: 19796.021 | AD22: -0.1260392 | AE22: 13770.343 | AF22: -0.094227816 | AG22: 12286.185 | AH22: -0.078597389 | AI22: 11107.602 | AJ22: -0.00082505971 | AK22: 27144.571 | AL22: -0.067041982 | AM22: 20670.055 | AN22: -0.092524743 | AO22: 12395.896 | AP22: -0.073453747 | AQ22: 11352.61 | AR22: -0.081372402 | AS22: 6900.3752 | AT22: 0.047468453 | AU22: 104197.87 | AV22: -0.028410388 | AW22: 82737.736 | AX22: -0.019885564 | AY22: 23436.661 | AZ22: -0.052040224 | BA22: 12904.946 | BB22: -0.08109549 | BC22: 18120.497 | BD22: -0.047906943
A23: 1982 | B23: 4 | C23: 94571.097 | D23: -0.02262755 | E23: 91751.514 | F23: -0.029811243 | G23: 63926.193 | H23: 0.0031429188 | I23: 52514.261 | J23: 0.00085443129 | K23: 11224.136 | L23: 0.017249841 | M23: 28046.652 | N23: -0.091812054 | O23: 18306.581 | P23: -0.0095120551 | Q23: 8032.031 | R23: 0.054052888 | S23: 10645.315 | T23: -0.041826683 | AA23: 30431.029 | AB23: -0.068010675 | AC23: 21004.009 | AD23: -0.087987089 | AE23: 15467.268 | AF23: 0.0078469858 | AG23: 13221.311 | AH23: -0.028380795 | AI23: 9335.0903 | AJ23: 0.015860426 | AK23: 26976.367 | AL23: -0.078420014 | AM23: 20906.478 | AN23: -0.097946901 | AO23: 13634.556 | AP23: -0.021784778 | AQ23: 12221.056 | AR23: -0.05624548 | AS23: 6382.4942 | AT23: 0.019668999 | AU23: 102307.07 | AV23: -0.0048093243 | AW23: 81141.305 | AX23: -0.00069474074 | AY23: 23090.059 | AZ23: -0.016304605 | BA23: 13867.572 | BB23: -0.031137189 | BC23: 18717.979 | BD23: -0.037784693
A24: 1983 | B24: 1 | C24: 90386.127 | D24: -0.0034005457 | E24: 89538.426 | F24: 0.010498117 | G24: 63092.818 | H24: 0.021826517 | I24: 51667.373 | J24: 0.02126897 | K24: 11284.181 | L24: 0.024964743 | M24: 26701.153 | N24: -0.013904941 | O24: 20375.671 | P24: 0.0048989597 | Q24: 10384.757 | R24: -0.0087632414 | S24: 10751.103 | T24: 0.015152927 | AA24: 29626.006 | AB24: -0.05176149 | AC24: 19448.626 | AD24: -0.087404297 | AE24: 14778.233 | AF24: 0.012732558 | AG24: 12930.691 | AH24: 0.023486144 | AI24: 10447.999 | AJ24: 0.049413258 | AK24: 27489.682 | AL24: -0.019862092 | AM24: 21403.413 | AN24: -0.034483223 | AO24: 13621.03 | AP24: 0.03527221 | AQ24: 12415.584 | AR24: 0.022141011 | AS24: 6377.9407 | AT24: 0.050232219 | AU24: 104617.13 | AV24: 0.02030776 | AW24: 82928.504 | AX24: 0.016665896 | AY24: 23645.794 | AZ24: 0.030905714 | BA24: 13559.505 | BB24: 0.020599388 | BC24: 18935.628 | BD24: 0.029120601
A25: 1983 | B25: 2 | C25: 92476.622 | D25: -0.00057969777 | E25: 92114.942 | F25: 0.0038236292 | G25: 62578.294 | H25: 0.0086451181 | I25: 51076.894 | J25: 0.0043051578 | K25: 11404.613 | L25: 0.033751894 | M25: 29635.236 | N25: -0.0043581111 | O25: 22336.795 | P25: 0.035871654 | Q25: 12132.219 | R25: 0.042762079 | S25: 11218.573 | T25: 0.030334084 | AA25: 29389.321 | AB25: -0.039286565 | AC25: 19179.883 | AD25: -0.076324354 | AE25: 14618.401 | AF25: -0.016132877 | AG25: 12563.269 | AH25: -0.013577405 | AI25: 10509.225 | AJ25: 0.061782168 | AK25: 27650.081 | AL25: -0.025485673 | AM25: 21382.875 | AN25: -0.034336962 | AO25: 13932.818 | AP25: 0.053747067 | AQ25: 12621.941 | AR25: 0.037675765 | AS25: 6594.2866 | AT25: 0.012638688 | AU25: 105998.02 | AV25: 0.015894788 | AW25: 84851.829 | AX25: 0.017083775 | AY25: 23279.636 | AZ25: 0.012536896 | BA25: 13182.09 | BB25: -0.014509472 | BC25: 19333.651 | BD25: 0.031109155
A26: 1983 | B26: 3 | C26: 92015.746 | D26: 0.012004566 | E26: 90686.05 | F26: 0.024504084 | G26: 62673.221 | H26: 0.014224133 | I26: 51174.585 | J26: 0.011152394 | K26: 11396.525 | L26: 0.031774804 | M26: 28185.035 | N26: 0.045913401 | O26: 21929.527 | P26: 0.034978049 | Q26: 12513.264 | R26: 0.065395539 | S26: 10557.225 | T26: 0.0091527143 | AA26: 29954.14 | AB26: -0.015648317 | AC26: 18960.395 | AD26: -0.042211817 | AE26: 14406.048 | AF26: 0.04616479 | AG26: 12659.244 | AH26: 0.030364103 | AI26: 11461.826 | AJ26: 0.031890177 | AK26: 27470.016 | AL26: 0.011989326 | AM26: 20915.699 | AN26: 0.011884053 | AO26: 13423.994 | AP26: 0.082938601 | AQ26: 12142.866 | AR26: 0.06961005 | AS26: 6955.2741 | AT26: 0.0079559221 | AU26: 106649.03 | AV26: 0.023524089 | AW26: 84441.443 | AX26: 0.020591663 | AY26: 24185.026 | AZ26: 0.031931389 | BA26: 13286.413 | BB26: 0.029559762 | BC26: 19061.291 | BD26: 0.051918771
A27: 1983 | B27: 4 | C27: 96198.056 | D27: 0.017203556 | E27: 96615.64 | F27: 0.053014119 | G27: 64797.946 | H27: 0.013636861 | I27: 53229.311 | J27: 0.013616313 | K27: 11381.135 | L27: 0.013987602 | M27: 31862.012 | N27: 0.1360362 | O27: 19529.533 | P27: 0.066803905 | Q27: 9074.1529 | R27: 0.12974575 | S27: 10971.622 | T27: 0.030652621 | AA27: 30304.336 | AB27: -0.0041632807 | AC27: 20534.08 | AD27: -0.022373301 | AE27: 15495.956 | AF27: 0.0018548059 | AG27: 13417.823 | AH27: 0.014863336 | AI27: 9870.1531 | AJ27: 0.057317364 | AK27: 29081.299 | AL27: 0.078028769 | AM27: 22653.539 | AN27: 0.083565503 | AO27: 14545.874 | AP27: 0.06683886 | AQ27: 13111.772 | AR27: 0.072883686 | AS27: 6733.7946 | AT27: 0.05504124 | AU27: 105224.3 | AV27: 0.028514484 | AW27: 83462.768 | AX27: 0.028610121 | AY27: 23739.672 | AZ27: 0.028133869 | BA27: 14078.343 | BB27: 0.015198806 | BC27: 19996.075 | BD27: 0.068281733
... A195: 2025 | B195: 4 | C195: 205191.95 | D195: 0.007063965 | E195: 196665.9 | F195: 0.067954166 | G195: 127143.93 | H195: 0.012378829 | I195: 103828.36 | J195: 0.014874679 | K195: 23363.178 | L195: 0.0020727344 | M195: 69872.14 | N195: 0.19297124 | O195: 54593.488 | P195: 0.0061968496 | Q195: 15317.197 | R195: 0.017940704 | S195: 39338.985 | T195: 0.0011816247 | AA195: 139079.32 | AB195: 0.0060403848 | AC195: 102570.69 | AD195: 0.030284284 | AE195: 82586.854 | AF195: 0.016600899 | AG195: 67736.032 | AH195: -0.053303777 | AI195: 36545.978 | AJ195: -0.055147528 | AK195: 129793.97 | AL195: 0.096426733 | AM195: 89318.476 | AN195: 0.16735252 | AO195: 63997.703 | AP195: 0.092464269 | AQ195: 61746.468 | AR195: 0.099759874 | AS195: 40556.906 | AT195: -0.031096421 | AU195: 294227.29 | AV195: -0.0053880515 | AW195: 181725.07 | AX195: 0.010480761 | AY195: 112691.99 | AZ195: -0.029417014 | BA195: 76251.668 | BB195: -0.016442904 | BC195: 102145.27 | BD195: 0.042045911

Sheet defl_q
A1: =IF(INDIRECT("beschriftung!"&ADDRESS(beschriftung!$C$1*12+ROW(beschriftung!$A1)-1,COLUMN(beschriftung!A$1)))="","",INDIRECT("beschriftung!"&ADDRESS(beschriftung!$C$1*12+ROW(beschriftung!$A1)-1,COLUMN(beschriftung!A$1)))) -> ESA 2010, Quarterly aggregates of Gross Domestic Product, expenditure approach, raw data
A2: =IF(INDIRECT("beschriftung!"&ADDRESS(beschriftung!$C$1*12+ROW(beschriftung!$A4)-1,COLUMN(beschriftung!A$1)))="","",INDIRECT("beschriftung!"&ADDRESS(beschriftung!$C$1*12+ROW(beschriftung!$A4)-1,COLUMN(beschriftung!A$1)))) -> Implicit chain price indexes, year-on-year growth rates
A3: =IF(INDIRECT("beschriftung!"&ADDRESS(beschriftung!$C$1*12+ROW(beschriftung!$A5)-1,COLUMN(beschriftung!A$1)))="","",INDIRECT("beschriftung!"&ADDRESS(beschriftung!$C$1*12+ROW(beschriftung!$A5)-1,COLUMN(beschriftung!A$1))))
C4: =IF(INDIRECT("beschriftung!"&ADDRESS(beschriftung!$C$1*12+ROW(beschriftung!$A5)-1,COLUMN(beschriftung!C$1)))="","",INDIRECT("beschriftung!"&ADDRESS(beschriftung!$C$1*12+ROW(beschriftung!$A5)-1,COLUMN(beschriftung!C$1)))) -> Gross domestic product
E5: =IF(INDIRECT("beschriftung!"&ADDRESS(beschriftung!$C$1*12+ROW(beschriftung!$A6)-1,COLUMN(beschriftung!E$1)))="","",INDIRECT("beschriftung!"&ADDRESS(beschriftung!$C$1*12+ROW(beschriftung!$A6)-1,COLUMN(beschriftung!E$1)))) -> Internal demand | Y5: =IF(INDIRECT("beschriftung!"&ADDRESS(beschriftung!$C$1*12+ROW(beschriftung!$A6)-1,COLUMN(beschriftung!Y$1)))="","",INDIRECT("beschriftung!"&ADDRESS(beschriftung!$C$1*12+ROW(beschriftung!$A6)-1,COLUMN(beschriftung!Y$1)))) -> Trade balance (goods and services) | AU5: =IF(INDIRECT("beschriftung!"&ADDRESS(beschriftung!$C$1*12+ROW(beschriftung!$A6)-1,COLUMN(beschriftung!AU$1)))="","",INDIRECT("beschriftung!"&ADDRESS(beschriftung!$C$1*12+ROW(beschriftung!$A6)-1,COLUMN(beschriftung!AU$1)))) -> Global demand excluding inventories change, stat. discrepancies and valuables
G6: =IF(INDIRECT("beschriftung!"&ADDRESS(beschriftung!$C$1*12+ROW(beschriftung!$A7)-1,COLUMN(beschriftung!G$1)))="","",INDIRECT("beschriftung!"&ADDRESS(beschriftung!$C$1*12+ROW(beschriftung!$A7)-1,COLUMN(beschriftung!G$1)))) -> Final consumption expenditure | M6: =IF(INDIRECT("beschriftung!"&ADDRESS(beschriftung!$C$1*12+ROW(beschriftung!$A7)-1,COLUMN(beschriftung!M$1)))="","",INDIRECT("beschriftung!"&ADDRESS(beschriftung!$C$1*12+ROW(beschriftung!$A7)-1,COLUMN(beschriftung!M$1)))) -> Gross capital formation | AA6: =IF(INDIRECT("beschriftung!"&ADDRESS(beschriftung!$C$1*12+ROW(beschriftung!$A7)-1,COLUMN(beschriftung!AA$1)))="","",INDIRECT("beschriftung!"&ADDRESS(beschriftung!$C$1*12+ROW(beschriftung!$A7)-1,COLUMN(beschriftung!AA$1)))) -> Exports of goods and services | AK6: =IF(INDIRECT("beschriftung!"&ADDRESS(beschriftung!$C$1*12+ROW(beschriftung!$A7)-1,COLUMN(beschriftung!AK$1)))="","",INDIRECT("beschriftung!"&ADDRESS(beschriftung!$C$1*12+ROW(beschriftung!$A7)-1,COLUMN(beschriftung!AK$1)))) -> Imports of goods and services | AW6: =IF(INDIRECT("beschriftung!"&ADDRESS(beschriftung!$C$1*12+ROW(beschriftung!$A7)-1,COLUMN(beschriftung!AW$1)))="","",INDIRECT("beschriftung!"&ADDRESS(beschriftung!$C$1*12+ROW(beschriftung!$A7)-1,COLUMN(beschriftung!AW$1)))) -> Final domestic demand | AY6: =IF(INDIRECT("beschriftung!"&ADDRESS(beschriftung!$C$1*12+ROW(beschriftung!$A7)-1,COLUMN(beschriftung!AY$1)))="","",INDIRECT("beschriftung!"&ADDRESS(beschriftung!$C$1*12+ROW(beschriftung!$A7)-1,COLUMN(beschriftung!AY$1)))) -> Exports of goods and services (excluding valuables) | BC6: =IF(INDIRECT("beschriftung!"&ADDRESS(beschriftung!$C$1*12+ROW(beschriftung!$A7)-1,COLUMN(beschriftung!BC$1)))="","",INDIRECT("beschriftung!"&ADDRESS(beschriftung!$C$1*12+ROW(beschriftung!$A7)-1,COLUMN(beschriftung!BC$1)))) -> Imports of goods and services (excluding valuables)
I7: =IF(INDIRECT("beschriftung!"&ADDRESS(beschriftung!$C$1*12+ROW(beschriftung!$A8)-1,COLUMN(beschriftung!I$1)))="","",INDIRECT("beschriftung!"&ADDRESS(beschriftung!$C$1*12+ROW(beschriftung!$A8)-1,COLUMN(beschriftung!I$1)))) -> Households and NPISH | K7: =IF(INDIRECT("beschriftung!"&ADDRESS(beschriftung!$C$1*12+ROW(beschriftung!$A8)-1,COLUMN(beschriftung!K$1)))="","",INDIRECT("beschriftung!"&ADDRESS(beschriftung!$C$1*12+ROW(beschriftung!$A8)-1,COLUMN(beschriftung!K$1)))) -> General government | O7: =IF(INDIRECT("beschriftung!"&ADDRESS(beschriftung!$C$1*12+ROW(beschriftung!$A8)-1,COLUMN(beschriftung!O$1)))="","",INDIRECT("beschriftung!"&ADDRESS(beschriftung!$C$1*12+ROW(beschriftung!$A8)-1,COLUMN(beschriftung!O$1)))) -> Gross fixed capital formation | U7: =IF(INDIRECT("beschriftung!"&ADDRESS(beschriftung!$C$1*12+ROW(beschriftung!$A8)-1,COLUMN(beschriftung!U$1)))="","",INDIRECT("beschriftung!"&ADDRESS(beschriftung!$C$1*12+ROW(beschriftung!$A8)-1,COLUMN(beschriftung!U$1)))) -> Changes in inventories and statistical discrepancies | W7: =IF(INDIRECT("beschriftung!"&ADDRESS(beschriftung!$C$1*12+ROW(beschriftung!$A8)-1,COLUMN(beschriftung!W$1)))="","",INDIRECT("beschriftung!"&ADDRESS(beschriftung!$C$1*12+ROW(beschriftung!$A8)-1,COLUMN(beschriftung!W$1)))) -> Acquisitions less disposals of valuables (including non-monetary gold) | AC7: =IF(INDIRECT("beschriftung!"&ADDRESS(beschriftung!$C$1*12+ROW(beschriftung!$A8)-1,COLUMN(beschriftung!AC$1)))="","",INDIRECT("beschriftung!"&ADDRESS(beschriftung!$C$1*12+ROW(beschriftung!$A8)-1,COLUMN(beschriftung!AC$1)))) -> Exports (exp.) of goods | AI7: =IF(INDIRECT("beschriftung!"&ADDRESS(beschriftung!$C$1*12+ROW(beschriftung!$A8)-1,COLUMN(beschriftung!AI$1)))="","",INDIRECT("beschriftung!"&ADDRESS(beschriftung!$C$1*12+ROW(beschriftung!$A8)-1,COLUMN(beschriftung!AI$1)))) -> Exports of services | AM7: =IF(INDIRECT("beschriftung!"&ADDRESS(beschriftung!$C$1*12+ROW(beschriftung!$A8)-1,COLUMN(beschriftung!AM$1)))="","",INDIRECT("beschriftung!"&ADDRESS(beschriftung!$C$1*12+ROW(beschriftung!$A8)-1,COLUMN(beschriftung!AM$1)))) -> Imports (imp.) of goods | AS7: =IF(INDIRECT("beschriftung!"&ADDRESS(beschriftung!$C$1*12+ROW(beschriftung!$A8)-1,COLUMN(beschriftung!AS$1)))="","",INDIRECT("beschriftung!"&ADDRESS(beschriftung!$C$1*12+ROW(beschriftung!$A8)-1,COLUMN(beschriftung!AS$1)))) -> Imports of services | BA7: =IF(INDIRECT("beschriftung!"&ADDRESS(beschriftung!$C$1*12+ROW(beschriftung!$A8)-1,COLUMN(beschriftung!BA$1)))="","",INDIRECT("beschriftung!"&ADDRESS(beschriftung!$C$1*12+ROW(beschriftung!$A8)-1,COLUMN(beschriftung!BA$1)))) -> thereof exports of goods excluding valuables
Q8: =IF(INDIRECT("beschriftung!"&ADDRESS(beschriftung!$C$1*12+ROW(beschriftung!$A9)-1,COLUMN(beschriftung!Q$1)))="","",INDIRECT("beschriftung!"&ADDRESS(beschriftung!$C$1*12+ROW(beschriftung!$A9)-1,COLUMN(beschriftung!Q$1)))) -> Construction | S8: =IF(INDIRECT("beschriftung!"&ADDRESS(beschriftung!$C$1*12+ROW(beschriftung!$A9)-1,COLUMN(beschriftung!S$1)))="","",INDIRECT("beschriftung!"&ADDRESS(beschriftung!$C$1*12+ROW(beschriftung!$A9)-1,COLUMN(beschriftung!S$1)))) -> Fixed assets and software | AE8: =IF(INDIRECT("beschriftung!"&ADDRESS(beschriftung!$C$1*12+ROW(beschriftung!$A9)-1,COLUMN(beschriftung!AE$1)))="","",INDIRECT("beschriftung!"&ADDRESS(beschriftung!$C$1*12+ROW(beschriftung!$A9)-1,COLUMN(beschriftung!AE$1)))) -> thereof exp. of goods excluding non-monetary gold | AG8: =IF(INDIRECT("beschriftung!"&ADDRESS(beschriftung!$C$1*12+ROW(beschriftung!$A9)-1,COLUMN(beschriftung!AG$1)))="","",INDIRECT("beschriftung!"&ADDRESS(beschriftung!$C$1*12+ROW(beschriftung!$A9)-1,COLUMN(beschriftung!AG$1)))) -> thereof exp. of goods excluding valuables and merchanting | AO8: =IF(INDIRECT("beschriftung!"&ADDRESS(beschriftung!$C$1*12+ROW(beschriftung!$A9)-1,COLUMN(beschriftung!AO$1)))="","",INDIRECT("beschriftung!"&ADDRESS(beschriftung!$C$1*12+ROW(beschriftung!$A9)-1,COLUMN(beschriftung!AO$1)))) -> thereof imp. of goods excluding non-monetary gold | AQ8: =IF(INDIRECT("beschriftung!"&ADDRESS(beschriftung!$C$1*12+ROW(beschriftung!$A9)-1,COLUMN(beschriftung!AQ$1)))="","",INDIRECT("beschriftung!"&ADDRESS(beschriftung!$C$1*12+ROW(beschriftung!$A9)-1,COLUMN(beschriftung!AQ$1)))) -> thereof imp. of goods excluding valuables
C11: B1GQ | E11: P3_P5 | G11: P3 | I11: P31_S14_S15 | K11: P3_S13 | M11: P5 | O11: P51G | Q11: P5111_N111_112G | S11: P5111_N113T117G | U11: P52_YA0 | W11: P53 | Y11: B11 | AA11: P6 | AC11: P61 | AE11: P61XF11 | AI11: P62 | AK11: P7 | AM11: P71 | AO11: P71XF11 | AS11: P72 | AU11: P3_P51G_P6 | AW11: P3_P51G
A12: 1980 | B12: 1 | C12: 55.995715 | E12: 57.794928 | G12: 56.095607 | I12: 58.578582 | K12: 45.419502 | M12: 61.215324 | O12: 74.827304 | Q12: 61.701392 | S12: 82.213314 | AA12: 86.604421 | AC12: 97.928172 | AE12: 91.459312 | AG12: 86.835283 | AI12: 62.13098 | AK12: 98.238868 | AM12: 104.46978 | AO12: 112.64682 | AQ12: 109.06269 | AS12: 72.614214 | AU12: 65.509868 | AW12: 61.059562 | AY12: 75.701671 | BA12: 84.17903 | BC12: 95.976456
A13: 1980 | B13: 2 | C13: 56.314138 | E13: 58.36295 | G13: 56.588567 | I13: 59.092809 | K13: 45.821223 | M13: 61.963109 | O13: 75.57753 | Q13: 62.768484 | S13: 82.568223 | AA13: 85.543901 | AC13: 96.617277 | AE13: 93.496738 | AG13: 88.778692 | AI13: 61.622358 | AK13: 97.789715 | AM13: 103.32276 | AO13: 114.89643 | AQ13: 111.41319 | AS13: 74.532819 | AU13: 66.153791 | AW13: 61.62152 | AY13: 76.581082 | BA13: 86.038678 | BC13: 98.146667
A14: 1980 | B14: 3 | C14: 57.09698 | E14: 59.185646 | G14: 57.234194 | I14: 59.813306 | K14: 46.131869 | M14: 63.175063 | O14: 75.953011 | Q14: 62.791148 | S14: 83.298481 | AA14: 87.28319 | AC14: 99.428518 | AE14: 91.886424 | AG14: 87.152953 | AI14: 61.126317 | AK14: 99.844926 | AM14: 105.91593 | AO14: 113.27558 | AQ14: 110.1379 | AS14: 74.741921 | AU14: 66.357083 | AW14: 62.194055 | AY14: 75.482704 | BA14: 84.504288 | BC14: 97.387664
A15: 1980 | B15: 4 | C15: 57.313437 | E15: 59.535448 | G15: 57.697668 | I15: 60.234883 | K15: 46.797024 | M15: 63.26969 | O15: 77.188397 | Q15: 63.961544 | S15: 84.53734 | AA15: 89.041524 | AC15: 101.84707 | AE15: 94.367664 | AG15: 90.746431 | AI15: 61.200578 | AK15: 102.24821 | AM15: 108.43263 | AO15: 116.65878 | AQ15: 114.55765 | AS15: 76.648605 | AU15: 67.359143 | AW15: 62.852606 | AY15: 77.581884 | BA15: 87.945049 | BC15: 100.92278
A16: 1981 | B16: 1 | C16: 58.744227 | D16: 0.049084313 | E16: 61.420137 | F16: 0.062725394 | G16: 58.873974 | H16: 0.049529137 | I16: 61.452342 | J16: 0.049058191 | K16: 47.795725 | L16: 0.052317243 | M16: 66.861291 | N16: 0.092231261 | O16: 79.425271 | P16: 0.061447719 | Q16: 66.279331 | R16: 0.074195068 | S16: 86.506261 | T16: 0.052217175 | AA16: 87.0582 | AB16: 0.0052396757 | AC16: 98.417259 | AD16: 0.004994341 | AE16: 94.137077 | AF16: 0.029278204 | AG16: 91.233675 | AH16: 0.050652129 | AI16: 62.449927 | AJ16: 0.0051334543 | AK16: 101.33754 | AL16: 0.031542254 | AM16: 106.91809 | AN16: 0.023435602 | AO16: 119.3702 | AP16: 0.059685492 | AQ16: 117.80341 | AR16: 0.080144024 | AS16: 77.947915 | AT16: 0.073452575 | AU16: 68.692129 | AV16: 0.048576823 | AW16: 64.31221 | AX16: 0.053270092 | AY16: 78.34008 | AZ16: 0.03485272 | BA16: 88.428844 | BB16: 0.050485417 | BC16: 103.51911 | BD16: 0.078588581
A17: 1981 | B17: 2 | C17: 59.244675 | D17: 0.052039096 | E17: 62.309429 | F17: 0.067619591 | G17: 59.929441 | H17: 0.059037966 | I17: 62.543114 | J17: 0.058387889 | K17: 48.703028 | L17: 0.062892362 | M17: 67.266068 | N17: 0.085582512 | O17: 80.916434 | P17: 0.07064141 | Q17: 67.475914 | R17: 0.074996722 | S17: 88.10078 | T17: 0.067005887 | AA17: 86.379897 | AB17: 0.0097727114 | AC17: 96.996455 | AD17: 0.003924536 | AE17: 93.408003 | AF17: -0.00094906725 | AG17: 91.871687 | AH17: 0.034839388 | AI17: 63.341941 | AJ17: 0.027905165 | AK17: 101.70365 | AL17: 0.040023993 | AM17: 106.63161 | AN17: 0.032024361 | AO17: 119.91188 | AP17: 0.043651957 | AQ17: 120.15651 | AR17: 0.078476522 | AS17: 80.16572 | AT17: 0.075576117 | AU17: 69.800223 | AV17: 0.055120535 | AW17: 65.493364 | AX17: 0.062832668 | AY17: 79.090654 | AZ17: 0.03277013 | BA17: 89.063269 | BB17: 0.035153845 | BC17: 105.77588 | BD17: 0.077732755
A18: 1981 | B18: 3 | C18: 60.301482 | D18: 0.056123839 | E18: 63.069804 | F18: 0.065626677 | G18: 61.020107 | H18: 0.066147747 | I18: 63.701049 | J18: 0.064997957 | K18: 49.497922 | L18: 0.072965888 | M18: 67.241034 | N18: 0.064360372 | O18: 81.655625 | P18: 0.07508082 | Q18: 67.549511 | R18: 0.075780782 | S18: 89.505923 | T18: 0.074520468 | AA18: 83.923104 | AB18: -0.038496373 | AC18: 92.593845 | AD18: -0.068739564 | AE18: 90.941968 | AF18: -0.010278523 | AG18: 90.898506 | AH18: 0.042976772 | AI18: 64.846604 | AJ18: 0.060862271 | AK18: 97.605982 | AL18: -0.022424208 | AM18: 101.8363 | AN18: -0.038517691 | AO18: 118.14669 | AP18: 0.043002287 | AQ18: 119.6896 | AR18: 0.086724941 | AS18: 78.97817 | AT18: 0.056678358 | AU18: 70.604373 | AV18: 0.064006571 | AW18: 66.49003 | AX18: 0.069073716 | AY18: 79.241076 | AZ18: 0.049791163 | BA18: 88.167716 | BB18: 0.043351973 | BC18: 105.05489 | BD18: 0.07872896
A19: 1981 | B19: 4 | C19: 61.2259 | D19: 0.068264329 | E19: 62.871373 | F19: 0.056032589 | G19: 61.596838 | H19: 0.067579343 | I19: 64.17573 | J19: 0.065424655 | K19: 50.576436 | L19: 0.080761812 | M19: 65.425858 | N19: 0.034079008 | O19: 82.767244 | P19: 0.072275714 | Q19: 68.447967 | R19: 0.070142502 | S19: 90.742773 | T19: 0.073404637 | AA19: 81.428095 | AB19: -0.085504244 | AC19: 89.262937 | AD19: -0.12355915 | AE19: 93.209359 | AF19: -0.012274394 | AG19: 94.466988 | AH19: 0.040999487 | AI19: 65.620065 | AJ19: 0.07221315 | AK19: 91.566027 | AL19: -0.10447308 | AM19: 94.973885 | AN19: -0.12412083 | AO19: 113.78918 | AP19: -0.024598211 | AQ19: 115.70951 | AR19: 0.010054843 | AS19: 76.547791 | AT19: -0.001315279 | AU19: 71.683451 | AV19: 0.064197788 | AW19: 67.182316 | AX19: 0.068886724 | AY19: 81.54612 | AZ19: 0.051097447 | BA19: 91.601041 | BB19: 0.041571327 | BC19: 101.65578 | BD19: 0.007262996
A20: 1982 | B20: 1 | C20: 62.909002 | D20: 0.070896768 | E20: 63.950486 | F20: 0.041197379 | G20: 62.625561 | H20: 0.063722341 | I20: 65.135873 | J20: 0.059941276 | K20: 51.911602 | L20: 0.086113903 | M20: 66.464887 | N20: -0.005928748 | O20: 84.140087 | P20: 0.059361666 | Q20: 70.174541 | R20: 0.058769607 | S20: 91.672091 | T20: 0.059716249 | AA20: 80.41909 | AB20: -0.076260595 | AC20: 86.055386 | AD20: -0.12560676 | AE20: 91.834109 | AF20: -0.02446398 | AG20: 94.570355 | AH20: 0.036572897 | AI20: 68.159163 | AJ20: 0.091421024 | AK20: 88.195061 | AL20: -0.12969017 | AM20: 90.982394 | AN20: -0.14904585 | AO20: 110.90878 | AP20: -0.070883799 | AQ20: 113.49774 | AR20: -0.03654959 | AS20: 75.203512 | AT20: -0.035208155 | AU20: 72.856334 | AV20: 0.060621279 | AW20: 68.320944 | AX20: 0.062332393 | AY20: 82.724243 | AZ20: 0.055963216 | BA20: 91.740137 | BB20: 0.037445847 | BC20: 99.746611 | BD20: -0.036442536
A21: 1982 | B21: 2 | C21: 64.113541 | D21: 0.082182344 | E21: 65.319157 | F21: 0.048302942 | G21: 63.716679 | H21: 0.063194942 | I21: 66.2565 | J21: 0.059373228 | K21: 52.884637 | L21: 0.08585932 | M21: 68.565389 | N21: 0.019316151 | O21: 85.085863 | P21: 0.051527599 | Q21: 70.918721 | R21: 0.051022755 | S21: 92.724684 | T21: 0.052484256 | AA21: 82.008995 | AB21: -0.050600914 | AC21: 87.237815 | AD21: -0.10060821 | AE21: 92.949445 | AF21: -0.0049091879 | AG21: 97.426969 | AH21: 0.060467835 | AI21: 70.448367 | AJ21: 0.11219149 | AK21: 90.587549 | AL21: -0.10929894 | AM21: 92.986055 | AN21: -0.1279691 | AO21: 114.20659 | AP21: -0.047579045 | AQ21: 117.88568 | AR21: -0.018898927 | AS21: 78.508873 | AT21: -0.020667773 | AU21: 74.267604 | AV21: 0.064002389 | AW21: 69.376404 | AX21: 0.059289056 | AY21: 85.302038 | AZ21: 0.078534989 | BA21: 94.491499 | BB21: 0.060948026 | BC21: 103.74053 | BD21: -0.019242096
A22: 1982 | B22: 3 | C22: 64.971203 | D22: 0.077439567 | E22: 66.48849 | F22: 0.054204812 | G22: 64.704328 | H22: 0.060377172 | I22: 67.333578 | J22: 0.057024636 | K22: 53.468781 | L22: 0.080222742 | M22: 70.024627 | N22: 0.041397236 | O22: 85.384447 | P22: 0.045665214 | Q22: 70.683042 | R22: 0.046388665 | S22: 93.579017 | T22: 0.045506425 | AA22: 86.188724 | AB22: 0.026996375 | AC22: 92.543529 | AD22: -0.00054341191 | AE22: 93.989945 | AF22: 0.033515625 | AG22: 97.513597 | AH22: 0.072774474 | AI22: 71.190616 | AJ22: 0.097831064 | AK22: 95.807618 | AL22: -0.018424732 | AM22: 99.485608 | AN22: -0.023083001 | AO22: 115.34263 | AP22: -0.023733711 | AQ22: 119.66437 | AR22: -0.00021081651 | AS22: 78.877395 | AT22: -0.0012759926 | AU22: 75.039754 | AV22: 0.062820202 | AW22: 70.191855 | AX22: 0.055674896 | AY22: 85.825683 | AZ22: 0.083095886 | BA22: 94.592448 | BB22: 0.072869434 | BC22: 105.00742 | BD22: -0.00045188264
A23: 1982 | B23: 4 | C23: 65.176478 | D23: 0.064524625 | E23: 66.955441 | F23: 0.064959104 | G23: 65.133111 | H23: 0.057409979 | I23: 67.767167 | J23: 0.055962539 | K23: 53.898955 | L23: 0.065693017 | M23: 70.580661 | N23: 0.078788458 | O23: 85.881763 | P23: 0.037629854 | Q23: 70.621049 | R23: 0.031747942 | S23: 94.405006 | T23: 0.040358405 | AA23: 87.609294 | AB23: 0.075909901 | AC23: 94.675003 | AD23: 0.060630612 | AE23: 92.650729 | AF23: -0.0059932769 | AG23: 98.095296 | AH23: 0.038408203 | AI23: 72.574163 | AJ23: 0.10597518 | AK23: 98.067062 | AL23: 0.070998339 | AM23: 102.17185 | AN23: 0.075788929 | AO23: 114.8829 | AP23: 0.0096118458 | AQ23: 120.04976 | AR23: 0.037509932 | AS23: 79.818229 | AT23: 0.04272414 | AU23: 75.585553 | AV23: 0.054435185 | AW23: 70.690425 | AX23: 0.052217743 | AY23: 86.488423 | AZ23: 0.060607461 | BA23: 95.152664 | BB23: 0.038772731 | BC23: 105.59763 | BD23: 0.038776439
A24: 1983 | B24: 1 | C24: 65.581997 | D24: 0.042489861 | E24: 67.25456 | F24: 0.051666135 | G24: 65.459079 | H24: 0.045245395 | I24: 68.098105 | J24: 0.045477736 | K24: 54.195122 | L24: 0.043988633 | M24: 70.853483 | N24: 0.06602879 | O24: 86.217835 | P24: 0.024693916 | Q24: 70.728773 | R24: 0.0078978999 | S24: 95.082813 | T24: 0.037205679 | AA24: 85.896416 | AB24: 0.068109779 | AC24: 92.555297 | AD24: 0.075531723 | AE24: 91.406471 | AF24: -0.0046566378 | AG24: 95.550208 | AH24: 0.010361101 | AI24: 71.276271 | AJ24: 0.045732772 | AK24: 95.9972 | AL24: 0.088464586 | AM24: 100.15747 | AN24: 0.10084452 | AO24: 112.67864 | AP24: 0.015957758 | AQ24: 116.30107 | AR24: 0.024699364 | AS24: 77.645878 | AT24: 0.032476751 | AU24: 75.405339 | AV24: 0.034986734 | AW24: 70.985774 | AX24: 0.039004583 | AY24: 84.663951 | AZ24: 0.02344788 | BA24: 92.721077 | BB24: 0.010692599 | BC24: 102.40835 | BD24: 0.026685001
A25: 1983 | B25: 2 | C25: 65.602407 | D25: 0.023222329 | E25: 66.860148 | F25: 0.023591713 | G25: 65.961473 | H25: 0.03523087 | I25: 68.638005 | J25: 0.035943719 | K25: 54.534103 | L25: 0.031189877 | M25: 68.535382 | N25: -0.00043765153 | O25: 86.54057 | P25: 0.017096925 | Q25: 70.786817 | R25: -0.0018599302 | S25: 95.755298 | T25: 0.032684 | AA25: 87.346486 | AB25: 0.065084213 | AC25: 95.019217 | AD25: 0.089197574 | AE25: 95.072578 | AF25: 0.022841799 | AG25: 99.539044 | AH25: 0.021678543 | AI25: 70.851696 | AJ25: 0.0057251726 | AK25: 96.172724 | AL25: 0.061654996 | AM25: 99.999131 | AN25: 0.07542073 | AO25: 113.53322 | AP25: -0.0058960932 | AQ25: 116.92614 | AR25: -0.0081396074 | AS25: 78.99485 | AT25: 0.0061900925 | AU25: 76.208281 | AV25: 0.026130867 | AW25: 71.427988 | AX25: 0.029571783 | AY25: 86.647898 | AZ25: 0.015777581 | BA25: 96.535152 | BB25: 0.021627908 | BC25: 103.27845 | BD25: -0.0044541517
A26: 1983 | B26: 3 | C26: 65.845568 | D26: 0.013457744 | E26: 67.326858 | F26: 0.012609209 | G26: 66.318618 | H26: 0.024948724 | I26: 68.985858 | J26: 0.02453873 | K26: 54.935937 | L26: 0.027439486 | M26: 69.157457 | N26: -0.012383781 | O26: 86.761982 | P26: 0.016133332 | Q26: 70.794667 | R26: 0.0015792213 | S26: 96.310996 | T26: 0.029194355 | AA26: 85.874404 | AB26: -0.0036468805 | AC26: 92.944018 | AD26: 0.0043275809 | AE26: 92.531322 | AF26: -0.015518917 | AG26: 96.50599 | AH26: -0.010332983 | AI26: 70.672735 | AJ26: -0.0072745691 | AK26: 95.342923 | AL26: -0.004850291 | AM26: 99.298099 | AN26: -0.001884792 | AO26: 112.43141 | AP26: -0.025239801 | AQ26: 115.68349 | AR26: -0.033267067 | AS26: 77.952704 | AT26: -0.011723148 | AU26: 76.07429 | AV26: 0.013786511 | AW26: 71.754466 | AX26: 0.022261995 | AY26: 84.936798 | AZ26: -0.010356861 | BA26: 93.641538 | BB26: -0.010052701 | BC26: 102.13955 | BD26: -0.027311171
A27: 1983 | B27: 4 | C27: 66.241149 | D27: 0.016335195 | E27: 67.260004 | F27: 0.00454874 | G27: 66.795989 | H27: 0.025530451 | I27: 69.461971 | J27: 0.025009228 | K27: 55.427688 | L27: 0.028362947 | M27: 68.110119 | N27: -0.035003094 | O27: 87.282501 | P27: 0.016310079 | Q27: 70.88362 | R27: 0.0037180251 | S27: 96.738446 | T27: 0.024717332 | AA27: 86.67617 | AB27: -0.010650969 | AC27: 93.687575 | AD27: -0.010429661 | AE27: 95.411241 | AF27: 0.029794821 | AG27: 99.659056 | AH27: 0.015941238 | AI27: 71.212234 | AJ27: -0.018766033 | AK27: 94.657475 | AL27: -0.034767912 | AM27: 98.150074 | AN27: -0.039362897 | AO27: 113.25113 | AP27: -0.014203812 | AQ27: 116.78147 | AR27: -0.027224529 | AS27: 78.605885 | AT27: -0.015188809 | AU27: 76.945322 | AV27: 0.017989797 | AW27: 72.281683 | AX27: 0.022510236 | AY27: 86.929939 | AZ27: 0.0051049081 | BA27: 96.659997 | BB27: 0.015841205 | BC27: 103.04661 | BD27: -0.024157934
... A195: 2025 | B195: 4 | C195: 106.66671 | D195: -0.002799079 | E195: 106.81148 | F195: 0.020877983 | G195: 106.81252 | H195: 0.005246278 | I195: 105.45543 | J195: 0.0028395277 | K195: 112.62594 | L195: 0.015309399 | M195: 106.27431 | N195: 0.050935709 | O195: 107.66564 | P195: 0.0039733745 | Q195: 116.10999 | R195: 0.0085422783 | S195: 104.20613 | T195: 0.0020404939 | AA195: 122.11663 | AB195: 0.068724424 | AC195: 125.94308 | AD195: 0.092292105 | AE195: 107.01702 | AF195: -0.017096658 | AG195: 99.127951 | AH195: -0.012986605 | AI195: 111.25242 | AJ195: -0.003302022 | AK195: 124.06526 | AL195: 0.10684635 | AM195: 128.43601 | AN195: 0.1467367 | AO195: 102.2732 | AP195: -0.010732255 | AQ195: 100.69314 | AR195: -0.024077902 | AS195: 114.19053 | AT195: 0.017129951 | AU195: 107.45864 | AV195: -0.002830882 | AW195: 107.07607 | AX195: 0.0048823275 | AY195: 107.89461 | AZ195: -0.014815402 | BA195: 106.13578 | BB195: -0.02024751 | BC195: 106.20815 | BD195: -0.0077549309

Sheet gc_q
A1: =IF(INDIRECT("beschriftung!"&ADDRESS(beschriftung!$C$1*12+ROW(beschriftung!$A1)-1,COLUMN(beschriftung!A$1)))="","",INDIRECT("beschriftung!"&ADDRESS(beschriftung!$C$1*12+ROW(beschriftung!$A1)-1,COLUMN(beschriftung!A$1)))) -> ESA 2010, Quarterly aggregates of Gross Domestic Product, expenditure approach, raw data
A2: =IF(INDIRECT("beschriftung!"&ADDRESS(beschriftung!$C$1*12+ROW(beschriftung!$A6)-1,COLUMN(beschriftung!A$1)))="","",INDIRECT("beschriftung!"&ADDRESS(beschriftung!$C$1*12+ROW(beschriftung!$A6)-1,COLUMN(beschriftung!A$1)))) -> Contributions to real GDP-growth
A3: =IF(INDIRECT("beschriftung!"&ADDRESS(beschriftung!$C$1*12+ROW(beschriftung!$A5)-1,COLUMN(beschriftung!A$1)))="","",INDIRECT("beschriftung!"&ADDRESS(beschriftung!$C$1*12+ROW(beschriftung!$A5)-1,COLUMN(beschriftung!A$1))))
C4: =IF(INDIRECT("beschriftung!"&ADDRESS(beschriftung!$C$1*12+ROW(beschriftung!$A5)-1,COLUMN(beschriftung!C$1)))="","",INDIRECT("beschriftung!"&ADDRESS(beschriftung!$C$1*12+ROW(beschriftung!$A5)-1,COLUMN(beschriftung!C$1)))) -> Gross domestic product
E5: =IF(INDIRECT("beschriftung!"&ADDRESS(beschriftung!$C$1*12+ROW(beschriftung!$A6)-1,COLUMN(beschriftung!E$1)))="","",INDIRECT("beschriftung!"&ADDRESS(beschriftung!$C$1*12+ROW(beschriftung!$A6)-1,COLUMN(beschriftung!E$1)))) -> Internal demand | Y5: =IF(INDIRECT("beschriftung!"&ADDRESS(beschriftung!$C$1*12+ROW(beschriftung!$A6)-1,COLUMN(beschriftung!Y$1)))="","",INDIRECT("beschriftung!"&ADDRESS(beschriftung!$C$1*12+ROW(beschriftung!$A6)-1,COLUMN(beschriftung!Y$1)))) -> Trade balance (goods and services) | AU5: =IF(INDIRECT("beschriftung!"&ADDRESS(beschriftung!$C$1*12+ROW(beschriftung!$A6)-1,COLUMN(beschriftung!AU$1)))="","",INDIRECT("beschriftung!"&ADDRESS(beschriftung!$C$1*12+ROW(beschriftung!$A6)-1,COLUMN(beschriftung!AU$1)))) -> Global demand excluding inventories change, stat. discrepancies and valuables
G6: =IF(INDIRECT("beschriftung!"&ADDRESS(beschriftung!$C$1*12+ROW(beschriftung!$A7)-1,COLUMN(beschriftung!G$1)))="","",INDIRECT("beschriftung!"&ADDRESS(beschriftung!$C$1*12+ROW(beschriftung!$A7)-1,COLUMN(beschriftung!G$1)))) -> Final consumption expenditure | M6: =IF(INDIRECT("beschriftung!"&ADDRESS(beschriftung!$C$1*12+ROW(beschriftung!$A7)-1,COLUMN(beschriftung!M$1)))="","",INDIRECT("beschriftung!"&ADDRESS(beschriftung!$C$1*12+ROW(beschriftung!$A7)-1,COLUMN(beschriftung!M$1)))) -> Gross capital formation | AA6: =IF(INDIRECT("beschriftung!"&ADDRESS(beschriftung!$C$1*12+ROW(beschriftung!$A7)-1,COLUMN(beschriftung!AA$1)))="","",INDIRECT("beschriftung!"&ADDRESS(beschriftung!$C$1*12+ROW(beschriftung!$A7)-1,COLUMN(beschriftung!AA$1)))) -> Exports of goods and services | AK6: =IF(INDIRECT("beschriftung!"&ADDRESS(beschriftung!$C$1*12+ROW(beschriftung!$A7)-1,COLUMN(beschriftung!AK$1)))="","",INDIRECT("beschriftung!"&ADDRESS(beschriftung!$C$1*12+ROW(beschriftung!$A7)-1,COLUMN(beschriftung!AK$1)))) -> Imports of goods and services | AW6: =IF(INDIRECT("beschriftung!"&ADDRESS(beschriftung!$C$1*12+ROW(beschriftung!$A7)-1,COLUMN(beschriftung!AW$1)))="","",INDIRECT("beschriftung!"&ADDRESS(beschriftung!$C$1*12+ROW(beschriftung!$A7)-1,COLUMN(beschriftung!AW$1)))) -> Final domestic demand | AY6: =IF(INDIRECT("beschriftung!"&ADDRESS(beschriftung!$C$1*12+ROW(beschriftung!$A7)-1,COLUMN(beschriftung!AY$1)))="","",INDIRECT("beschriftung!"&ADDRESS(beschriftung!$C$1*12+ROW(beschriftung!$A7)-1,COLUMN(beschriftung!AY$1)))) -> Exports of goods and services (excluding valuables) | BC6: =IF(INDIRECT("beschriftung!"&ADDRESS(beschriftung!$C$1*12+ROW(beschriftung!$A7)-1,COLUMN(beschriftung!BC$1)))="","",INDIRECT("beschriftung!"&ADDRESS(beschriftung!$C$1*12+ROW(beschriftung!$A7)-1,COLUMN(beschriftung!BC$1)))) -> Imports of goods and services (excluding valuables)
I7: =IF(INDIRECT("beschriftung!"&ADDRESS(beschriftung!$C$1*12+ROW(beschriftung!$A8)-1,COLUMN(beschriftung!I$1)))="","",INDIRECT("beschriftung!"&ADDRESS(beschriftung!$C$1*12+ROW(beschriftung!$A8)-1,COLUMN(beschriftung!I$1)))) -> Households and NPISH | K7: =IF(INDIRECT("beschriftung!"&ADDRESS(beschriftung!$C$1*12+ROW(beschriftung!$A8)-1,COLUMN(beschriftung!K$1)))="","",INDIRECT("beschriftung!"&ADDRESS(beschriftung!$C$1*12+ROW(beschriftung!$A8)-1,COLUMN(beschriftung!K$1)))) -> General government | O7: =IF(INDIRECT("beschriftung!"&ADDRESS(beschriftung!$C$1*12+ROW(beschriftung!$A8)-1,COLUMN(beschriftung!O$1)))="","",INDIRECT("beschriftung!"&ADDRESS(beschriftung!$C$1*12+ROW(beschriftung!$A8)-1,COLUMN(beschriftung!O$1)))) -> Gross fixed capital formation | U7: =IF(INDIRECT("beschriftung!"&ADDRESS(beschriftung!$C$1*12+ROW(beschriftung!$A8)-1,COLUMN(beschriftung!U$1)))="","",INDIRECT("beschriftung!"&ADDRESS(beschriftung!$C$1*12+ROW(beschriftung!$A8)-1,COLUMN(beschriftung!U$1)))) -> Changes in inventories and statistical discrepancies | W7: =IF(INDIRECT("beschriftung!"&ADDRESS(beschriftung!$C$1*12+ROW(beschriftung!$A8)-1,COLUMN(beschriftung!W$1)))="","",INDIRECT("beschriftung!"&ADDRESS(beschriftung!$C$1*12+ROW(beschriftung!$A8)-1,COLUMN(beschriftung!W$1)))) -> Acquisitions less disposals of valuables (including non-monetary gold) | AC7: =IF(INDIRECT("beschriftung!"&ADDRESS(beschriftung!$C$1*12+ROW(beschriftung!$A8)-1,COLUMN(beschriftung!AC$1)))="","",INDIRECT("beschriftung!"&ADDRESS(beschriftung!$C$1*12+ROW(beschriftung!$A8)-1,COLUMN(beschriftung!AC$1)))) -> Exports (exp.) of goods | AI7: =IF(INDIRECT("beschriftung!"&ADDRESS(beschriftung!$C$1*12+ROW(beschriftung!$A8)-1,COLUMN(beschriftung!AI$1)))="","",INDIRECT("beschriftung!"&ADDRESS(beschriftung!$C$1*12+ROW(beschriftung!$A8)-1,COLUMN(beschriftung!AI$1)))) -> Exports of services | AM7: =IF(INDIRECT("beschriftung!"&ADDRESS(beschriftung!$C$1*12+ROW(beschriftung!$A8)-1,COLUMN(beschriftung!AM$1)))="","",INDIRECT("beschriftung!"&ADDRESS(beschriftung!$C$1*12+ROW(beschriftung!$A8)-1,COLUMN(beschriftung!AM$1)))) -> Imports (imp.) of goods | AS7: =IF(INDIRECT("beschriftung!"&ADDRESS(beschriftung!$C$1*12+ROW(beschriftung!$A8)-1,COLUMN(beschriftung!AS$1)))="","",INDIRECT("beschriftung!"&ADDRESS(beschriftung!$C$1*12+ROW(beschriftung!$A8)-1,COLUMN(beschriftung!AS$1)))) -> Imports of services | BA7: =IF(INDIRECT("beschriftung!"&ADDRESS(beschriftung!$C$1*12+ROW(beschriftung!$A8)-1,COLUMN(beschriftung!BA$1)))="","",INDIRECT("beschriftung!"&ADDRESS(beschriftung!$C$1*12+ROW(beschriftung!$A8)-1,COLUMN(beschriftung!BA$1)))) -> thereof exports of goods excluding valuables
Q8: =IF(INDIRECT("beschriftung!"&ADDRESS(beschriftung!$C$1*12+ROW(beschriftung!$A9)-1,COLUMN(beschriftung!Q$1)))="","",INDIRECT("beschriftung!"&ADDRESS(beschriftung!$C$1*12+ROW(beschriftung!$A9)-1,COLUMN(beschriftung!Q$1)))) -> Construction | S8: =IF(INDIRECT("beschriftung!"&ADDRESS(beschriftung!$C$1*12+ROW(beschriftung!$A9)-1,COLUMN(beschriftung!S$1)))="","",INDIRECT("beschriftung!"&ADDRESS(beschriftung!$C$1*12+ROW(beschriftung!$A9)-1,COLUMN(beschriftung!S$1)))) -> Fixed assets and software | AE8: =IF(INDIRECT("beschriftung!"&ADDRESS(beschriftung!$C$1*12+ROW(beschriftung!$A9)-1,COLUMN(beschriftung!AE$1)))="","",INDIRECT("beschriftung!"&ADDRESS(beschriftung!$C$1*12+ROW(beschriftung!$A9)-1,COLUMN(beschriftung!AE$1)))) -> thereof exp. of goods excluding non-monetary gold | AG8: =IF(INDIRECT("beschriftung!"&ADDRESS(beschriftung!$C$1*12+ROW(beschriftung!$A9)-1,COLUMN(beschriftung!AG$1)))="","",INDIRECT("beschriftung!"&ADDRESS(beschriftung!$C$1*12+ROW(beschriftung!$A9)-1,COLUMN(beschriftung!AG$1)))) -> thereof exp. of goods excluding valuables and merchanting | AO8: =IF(INDIRECT("beschriftung!"&ADDRESS(beschriftung!$C$1*12+ROW(beschriftung!$A9)-1,COLUMN(beschriftung!AO$1)))="","",INDIRECT("beschriftung!"&ADDRESS(beschriftung!$C$1*12+ROW(beschriftung!$A9)-1,COLUMN(beschriftung!AO$1)))) -> thereof imp. of goods excluding non-monetary gold | AQ8: =IF(INDIRECT("beschriftung!"&ADDRESS(beschriftung!$C$1*12+ROW(beschriftung!$A9)-1,COLUMN(beschriftung!AQ$1)))="","",INDIRECT("beschriftung!"&ADDRESS(beschriftung!$C$1*12+ROW(beschriftung!$A9)-1,COLUMN(beschriftung!AQ$1)))) -> thereof imp. of goods excluding valuables
C11: B1GQ | E11: P3_P5 | G11: P3 | I11: P31_S14_S15 | K11: P3_S13 | M11: P5 | O11: P51G | Q11: P5111_N111_112G | S11: P5111_N113T117G | U11: P52_YA0 | W11: P53 | Y11: B11 | AA11: P6 | AC11: P61 | AE11: P61XF11 | AI11: P62 | AK11: P7 | AM11: P71 | AO11: P71XF11 | AS11: P72 | AU11: P3_P51G_P6 | AW11: P3_P51G
A12: 1980 | B12: 1
A13: 1980 | B13: 2
A14: 1980 | B14: 3
A15: 1980 | B15: 4
A16: 1981 | B16: 1 | E16: -0.072914901 | G16: 0.0068194993 | I16: 0.0031150946 | K16: 0.0037044047 | M16: -0.079734401 | O16: 0.0095995053 | Q16: 0.012994674 | S16: -0.0033951688 | U16: -0.026422211 | W16: -0.062911695 | Y16: 0.083914624 | AA16: 0.045160164 | AC16: 0.034316907 | AE16: 0.0079474241 | AG16: 0.0026915583 | AI16: 0.010843257 | AK16: 0.038754461 | AM16: 0.041856724 | AO16: 0.022506576 | AQ16: 0.0098493079 | AS16: -0.0031022634 | AU16: 0.030674889 | AW16: 0.016419005 | AY16: 0.014255885 | BA16: 0.0034126279 | BC16: 0.0067470446
A17: 1981 | B17: 2 | E17: -0.029025375 | G17: 0.010989457 | I17: 0.0084430223 | K17: 0.0025464346 | M17: -0.040014832 | O17: 0.004081885 | Q17: 0.0049348312 | S17: -0.00085294623 | U17: -0.015289612 | W17: -0.028807105 | Y17: 0.049460585 | AA17: 0.053547969 | AC17: 0.044348559 | AE17: 0.023937302 | AG17: 0.0096664868 | AI17: 0.0091994093 | AK17: -0.0040873835 | AM17: -0.0010250505 | AO17: 0.0006690117 | AQ17: 0.0040648945 | AS17: -0.003062333 | AU17: 0.034722261 | AW17: 0.015071342 | AY17: 0.019650919 | BA17: 0.010451509 | BC17: 0.0010025615
A18: 1981 | B18: 3 | E18: 0.017038247 | G18: 0.0079321407 | I18: 0.0064314632 | K18: 0.0015006775 | M18: 0.0091061062 | O18: 0.0058302522 | Q18: 0.0020747795 | S18: 0.0037554726 | U18: -0.011934735 | W18: 0.015210589 | Y18: 0.0035349818 | AA18: 0.094401383 | AC18: 0.087591639 | AE18: 0.036231317 | AG18: 0.014326105 | AI18: 0.0068097443 | AK18: -0.090866401 | AM18: -0.086642004 | AO18: -0.0073858064 | AQ18: 0.0012308239 | AS18: -0.0042243967 | AU18: 0.035501537 | AW18: 0.013762393 | AY18: 0.021739144 | BA18: 0.0149294 | BC18: -0.0029935727
A19: 1981 | B19: 4 | E19: 0.013452646 | G19: 0.0052034271 | I19: 0.0042063628 | K19: 0.00099706427 | M19: 0.008249219 | O19: -0.0030836083 | Q19: 0.0011878007 | S19: -0.0042714091 | U19: 0.011495465 | W19: -0.00016263761 | Y19: -0.0013531135 | AA19: 0.082107806 | AC19: 0.075283232 | AE19: 0.020366648 | AG19: 0.0084490943 | AI19: 0.0068245742 | AK19: -0.083460919 | AM19: -0.075013861 | AO19: -0.0097381097 | AQ19: -0.0084961842 | AS19: -0.0084470581 | AU19: 0.01754731 | AW19: 0.0021198187 | AY19: 0.015427491 | BA19: 0.0086029171 | BC19: -0.016943242
A20: 1982 | B20: 1 | E20: 0.031492131 | G20: 0.0035914969 | I20: 0.0029891287 | K20: 0.00060236819 | M20: 0.027900634 | O20: -0.012392593 | Q20: -0.0036153337 | S20: -0.0087772591 | U20: 0.021146775 | W20: 0.019146452 | Y20: -0.02582661 | AA20: 0.040016795 | AC20: 0.035170404 | AE20: 0.014236296 | AG20: 6.2586637e-05 | AI20: 0.0048463902 | AK20: -0.065843404 | AM20: -0.056345956 | AO20: -0.013440245 | AQ20: -0.0016014713 | AS20: -0.0094974481 | AU20: -0.0043823338 | AW20: -0.0088010959 | AY20: 0.0044187621 | BA20: -0.00042762808 | BC20: -0.011098919
A21: 1982 | B21: 2 | E21: 0.039040506 | G21: 0.00089321991 | I21: 0.00086226705 | K21: 3.0952854e-05 | M21: 0.038147286 | O21: -0.014989577 | Q21: -0.0095607866 | S21: -0.0054287904 | U21: 0.014561561 | W21: 0.038575302 | Y21: -0.051697852 | AA21: 0.0067104399 | AC21: 0.0059925675 | AE21: 0.003840837 | AG21: -0.0063878046 | AI21: 0.00071787245 | AK21: -0.058408292 | AM21: -0.05242113 | AO21: -0.0046090039 | AQ21: -0.00060344882 | AS21: -0.0059871617 | AU21: -0.020628296 | AW21: -0.014096357 | AY21: -0.0065319394 | BA21: -0.0072498118 | BC21: -0.0065906106
A22: 1982 | B22: 3 | E22: -0.0084274694 | G22: 0.0017041289 | I22: 0.0015387144 | K22: 0.00016541442 | M22: -0.010131598 | O22: -0.021766437 | Q22: -0.0092270029 | S22: -0.012539434 | U22: -0.00079604326 | W22: 0.012430882 | Y22: -0.013384142 | AA22: -0.047267716 | AC22: -0.047161603 | AE22: -0.023242567 | AG22: -0.016996024 | AI22: -0.00010611243 | AK22: 0.033883574 | AM22: 0.038289718 | AO22: 0.020713867 | AQ22: 0.02147359 | AS22: -0.0044061446 | AU22: -0.038083013 | AW22: -0.020062308 | AY22: -0.018020705 | BA22: -0.017914593 | BC22: 0.017067445
A23: 1982 | B23: 4 | E23: -0.028511304 | G23: 0.0021105413 | I23: 0.00048564709 | K23: 0.0016248942 | M23: -0.030621845 | O23: -0.0023588846 | Q23: 0.0047589257 | S23: -0.0071178102 | U23: -0.029737424 | W23: 0.001474463 | Y23: 0.0058837543 | AA23: -0.028917812 | AC23: -0.03053218 | AE23: 0.0018947324 | AG23: -0.0061581396 | AI23: 0.0016143677 | AK23: 0.034801567 | AM23: 0.036392356 | AO23: 0.0058321298 | AQ23: 0.014225674 | AS23: -0.0015907892 | AU23: -0.0055250105 | AW23: -0.00024834325 | AY23: -0.0052766673 | BA23: -0.006891035 | BC23: 0.012634885
A24: 1983 | B24: 1 | E24: 0.010648429 | G24: 0.014784944 | I24: 0.01228426 | K24: 0.0025006834 | M24: -0.0041365145 | O24: 0.0014492693 | Q24: -0.0011291961 | S24: 0.0025784654 | U24: -0.020541583 | W24: 0.0149558 | Y24: -0.014048975 | AA24: -0.022217831 | AC24: -0.028094895 | AE24: 0.0029905666 | AG24: 0.0049182722 | AI24: 0.0058770637 | AK24: 0.0081688559 | AM24: 0.012189741 | AO24: -0.0090211119 | AQ24: -0.0053499174 | AS24: -0.0040208854 | AU24: 0.02651184 | AW24: 0.016234213 | AY24: 0.010277627 | BA24: 0.0044005637 | BC24: -0.0093708028
A25: 1983 | B25: 2 | E25: 0.0046359149 | G25: 0.0057647506 | I25: 0.00244536 | K25: 0.0033193906 | M25: -0.0011288357 | O25: 0.011109999 | Q25: 0.0059475919 | S25: 0.0051624071 | U25: -0.011429059 | W25: -0.00080977575 | Y25: -0.0052156127 | AA25: -0.016043971 | AC25: -0.023305629 | AE25: -0.0037556793 | AG25: -0.0028398934 | AI25: 0.007261658 | AK25: 0.010828358 | AM25: 0.01191754 | AO25: -0.01368091 | AQ25: -0.0091065539 | AS25: -0.001089182 | AU25: 0.021045097 | AW25: 0.01687475 | AY25: 0.0041703475 | BA25: -0.0030913105 | BC25: -0.010195736
A26: 1983 | B26: 3 | E26: 0.025696197 | G26: 0.0096100016 | I26: 0.0064333461 | K26: 0.0031766554 | M26: 0.016086195 | O26: 0.010706921 | Q26: 0.0091901479 | S26: 0.0015167734 | U26: -0.00194846 | W26: 0.0073277341 | Y26: -0.013691631 | AA26: -0.0088217989 | AC26: -0.013090536 | AE26: 0.010114314 | AG26: 0.0061580344 | AI26: 0.0042687372 | AK26: -0.0048698321 | AM26: -0.0041368131 | AO26: -0.020073537 | AQ26: -0.016007812 | AS26: -0.00073301895 | AU26: 0.030693856 | AW26: 0.020316923 | AY26: 0.010376934 | BA26: 0.0061081965 | BC26: -0.016740831
A27: 1983 | B27: 4 | E27: 0.051630207 | G27: 0.0092343881 | I27: 0.0078615251 | K27: 0.0013728631 | M27: 0.042395819 | O27: 0.016937692 | Q27: 0.011939973 | S27: 0.0049977191 | U27: 0.0033750171 | W27: 0.022083109 | Y27: -0.034426651 | AA27: -0.00091806805 | AC27: -0.0072180231 | AE27: 0.0004312326 | AG27: 0.0031274448 | AI27: 0.0062999551 | AK27: -0.033508583 | AM27: -0.028959421 | AO27: -0.016985413 | AQ27: -0.017348065 | AS27: -0.0045491621 | AU27: 0.035725766 | AW27: 0.026172081 | AY27: 0.0095536853 | BA27: 0.0032537302 | BC27: -0.021897227
... A195: 2025 | B195: 4 | E195: 0.061135967 | G195: 0.0075883799 | I195: 0.0073424186 | K195: 0.00024596136 | M195: 0.053547587 | O195: 0.001647547 | Q195: 0.001426009 | S195: 0.00022153807 | U195: 0.03489942 | W195: 0.01700062 | Y195: -0.054072002 | AA195: 0.0050259139 | AC195: 0.015950325 | AE195: 0.0067372797 | AG195: -0.017574812 | AI195: -0.010924411 | AK195: -0.059097916 | AM195: -0.065802916 | AO195: -0.025693875 | AQ195: -0.026515838 | AS195: 0.0067050004 | AU195: -0.0080246167 | AW195: 0.009235927 | AY195: -0.017260544 | BA195: -0.0063361324 | BC195: -0.019810838

Sheet nom_y
A1: =IF(INDIRECT("beschriftung!"&ADDRESS(beschriftung!$C$1*12+ROW(beschriftung!$A1)-1,COLUMN(beschriftung!B$1)))="","",INDIRECT("beschriftung!"&ADDRESS(beschriftung!$C$1*12+ROW(beschriftung!$A1)-1,COLUMN(beschriftung!B$1)))) -> ESA 2010, Annual aggregates of Gross Domestic Product, expenditure approach (SFSO, SECO), raw data
A2: =IF(INDIRECT("beschriftung!"&ADDRESS(beschriftung!$C$1*12+ROW(beschriftung!$A2)-1,COLUMN(beschriftung!B$1)))="","",INDIRECT("beschriftung!"&ADDRESS(beschriftung!$C$1*12+ROW(beschriftung!$A2)-1,COLUMN(beschriftung!B$1)))) -> In Mio. Swiss Francs, at current prices, percentage change to previous year
A3: =IF(INDIRECT("beschriftung!"&ADDRESS(beschriftung!$C$1*12+ROW(beschriftung!$A5)-1,COLUMN(beschriftung!B$1)))="","",INDIRECT("beschriftung!"&ADDRESS(beschriftung!$C$1*12+ROW(beschriftung!$A5)-1,COLUMN(beschriftung!B$1))))
C4: =IF(INDIRECT("beschriftung!"&ADDRESS(beschriftung!$C$1*12+ROW(beschriftung!$A5)-1,COLUMN(beschriftung!C$1)))="","",INDIRECT("beschriftung!"&ADDRESS(beschriftung!$C$1*12+ROW(beschriftung!$A5)-1,COLUMN(beschriftung!C$1)))) -> Gross domestic product
E5: =IF(INDIRECT("beschriftung!"&ADDRESS(beschriftung!$C$1*12+ROW(beschriftung!$A6)-1,COLUMN(beschriftung!E$1)))="","",INDIRECT("beschriftung!"&ADDRESS(beschriftung!$C$1*12+ROW(beschriftung!$A6)-1,COLUMN(beschriftung!E$1)))) -> Internal demand | Y5: =IF(INDIRECT("beschriftung!"&ADDRESS(beschriftung!$C$1*12+ROW(beschriftung!$A6)-1,COLUMN(beschriftung!Y$1)))="","",INDIRECT("beschriftung!"&ADDRESS(beschriftung!$C$1*12+ROW(beschriftung!$A6)-1,COLUMN(beschriftung!Y$1)))) -> Trade balance (goods and services) | AU5: =IF(INDIRECT("beschriftung!"&ADDRESS(beschriftung!$C$1*12+ROW(beschriftung!$A6)-1,COLUMN(beschriftung!AU$1)))="","",INDIRECT("beschriftung!"&ADDRESS(beschriftung!$C$1*12+ROW(beschriftung!$A6)-1,COLUMN(beschriftung!AU$1)))) -> Global demand excluding inventories change, stat. discrepancies and valuables
G6: =IF(INDIRECT("beschriftung!"&ADDRESS(beschriftung!$C$1*12+ROW(beschriftung!$A7)-1,COLUMN(beschriftung!G$1)))="","",INDIRECT("beschriftung!"&ADDRESS(beschriftung!$C$1*12+ROW(beschriftung!$A7)-1,COLUMN(beschriftung!G$1)))) -> Final consumption expenditure | M6: =IF(INDIRECT("beschriftung!"&ADDRESS(beschriftung!$C$1*12+ROW(beschriftung!$A7)-1,COLUMN(beschriftung!M$1)))="","",INDIRECT("beschriftung!"&ADDRESS(beschriftung!$C$1*12+ROW(beschriftung!$A7)-1,COLUMN(beschriftung!M$1)))) -> Gross capital formation | AA6: =IF(INDIRECT("beschriftung!"&ADDRESS(beschriftung!$C$1*12+ROW(beschriftung!$A7)-1,COLUMN(beschriftung!AA$1)))="","",INDIRECT("beschriftung!"&ADDRESS(beschriftung!$C$1*12+ROW(beschriftung!$A7)-1,COLUMN(beschriftung!AA$1)))) -> Exports of goods and services | AK6: =IF(INDIRECT("beschriftung!"&ADDRESS(beschriftung!$C$1*12+ROW(beschriftung!$A7)-1,COLUMN(beschriftung!AK$1)))="","",INDIRECT("beschriftung!"&ADDRESS(beschriftung!$C$1*12+ROW(beschriftung!$A7)-1,COLUMN(beschriftung!AK$1)))) -> Imports of goods and services | AW6: =IF(INDIRECT("beschriftung!"&ADDRESS(beschriftung!$C$1*12+ROW(beschriftung!$A7)-1,COLUMN(beschriftung!AW$1)))="","",INDIRECT("beschriftung!"&ADDRESS(beschriftung!$C$1*12+ROW(beschriftung!$A7)-1,COLUMN(beschriftung!AW$1)))) -> Final domestic demand | AY6: =IF(INDIRECT("beschriftung!"&ADDRESS(beschriftung!$C$1*12+ROW(beschriftung!$A7)-1,COLUMN(beschriftung!AY$1)))="","",INDIRECT("beschriftung!"&ADDRESS(beschriftung!$C$1*12+ROW(beschriftung!$A7)-1,COLUMN(beschriftung!AY$1)))) -> Exports of goods and services (excluding valuables) | BC6: =IF(INDIRECT("beschriftung!"&ADDRESS(beschriftung!$C$1*12+ROW(beschriftung!$A7)-1,COLUMN(beschriftung!BC$1)))="","",INDIRECT("beschriftung!"&ADDRESS(beschriftung!$C$1*12+ROW(beschriftung!$A7)-1,COLUMN(beschriftung!BC$1)))) -> Imports of goods and services (excluding valuables)
I7: =IF(INDIRECT("beschriftung!"&ADDRESS(beschriftung!$C$1*12+ROW(beschriftung!$A8)-1,COLUMN(beschriftung!I$1)))="","",INDIRECT("beschriftung!"&ADDRESS(beschriftung!$C$1*12+ROW(beschriftung!$A8)-1,COLUMN(beschriftung!I$1)))) -> Households and NPISH | K7: =IF(INDIRECT("beschriftung!"&ADDRESS(beschriftung!$C$1*12+ROW(beschriftung!$A8)-1,COLUMN(beschriftung!K$1)))="","",INDIRECT("beschriftung!"&ADDRESS(beschriftung!$C$1*12+ROW(beschriftung!$A8)-1,COLUMN(beschriftung!K$1)))) -> General government | O7: =IF(INDIRECT("beschriftung!"&ADDRESS(beschriftung!$C$1*12+ROW(beschriftung!$A8)-1,COLUMN(beschriftung!O$1)))="","",INDIRECT("beschriftung!"&ADDRESS(beschriftung!$C$1*12+ROW(beschriftung!$A8)-1,COLUMN(beschriftung!O$1)))) -> Gross fixed capital formation | U7: =IF(INDIRECT("beschriftung!"&ADDRESS(beschriftung!$C$1*12+ROW(beschriftung!$A8)-1,COLUMN(beschriftung!U$1)))="","",INDIRECT("beschriftung!"&ADDRESS(beschriftung!$C$1*12+ROW(beschriftung!$A8)-1,COLUMN(beschriftung!U$1)))) -> Changes in inventories and statistical discrepancies | W7: =IF(INDIRECT("beschriftung!"&ADDRESS(beschriftung!$C$1*12+ROW(beschriftung!$A8)-1,COLUMN(beschriftung!W$1)))="","",INDIRECT("beschriftung!"&ADDRESS(beschriftung!$C$1*12+ROW(beschriftung!$A8)-1,COLUMN(beschriftung!W$1)))) -> Acquisitions less disposals of valuables (including non-monetary gold) | AC7: =IF(INDIRECT("beschriftung!"&ADDRESS(beschriftung!$C$1*12+ROW(beschriftung!$A8)-1,COLUMN(beschriftung!AC$1)))="","",INDIRECT("beschriftung!"&ADDRESS(beschriftung!$C$1*12+ROW(beschriftung!$A8)-1,COLUMN(beschriftung!AC$1)))) -> Exports (exp.) of goods | AI7: =IF(INDIRECT("beschriftung!"&ADDRESS(beschriftung!$C$1*12+ROW(beschriftung!$A8)-1,COLUMN(beschriftung!AI$1)))="","",INDIRECT("beschriftung!"&ADDRESS(beschriftung!$C$1*12+ROW(beschriftung!$A8)-1,COLUMN(beschriftung!AI$1)))) -> Exports of services | AM7: =IF(INDIRECT("beschriftung!"&ADDRESS(beschriftung!$C$1*12+ROW(beschriftung!$A8)-1,COLUMN(beschriftung!AM$1)))="","",INDIRECT("beschriftung!"&ADDRESS(beschriftung!$C$1*12+ROW(beschriftung!$A8)-1,COLUMN(beschriftung!AM$1)))) -> Imports (imp.) of goods | AS7: =IF(INDIRECT("beschriftung!"&ADDRESS(beschriftung!$C$1*12+ROW(beschriftung!$A8)-1,COLUMN(beschriftung!AS$1)))="","",INDIRECT("beschriftung!"&ADDRESS(beschriftung!$C$1*12+ROW(beschriftung!$A8)-1,COLUMN(beschriftung!AS$1)))) -> Imports of services | BA7: =IF(INDIRECT("beschriftung!"&ADDRESS(beschriftung!$C$1*12+ROW(beschriftung!$A8)-1,COLUMN(beschriftung!BA$1)))="","",INDIRECT("beschriftung!"&ADDRESS(beschriftung!$C$1*12+ROW(beschriftung!$A8)-1,COLUMN(beschriftung!BA$1)))) -> thereof exports of goods excluding valuables
Q8: =IF(INDIRECT("beschriftung!"&ADDRESS(beschriftung!$C$1*12+ROW(beschriftung!$A9)-1,COLUMN(beschriftung!Q$1)))="","",INDIRECT("beschriftung!"&ADDRESS(beschriftung!$C$1*12+ROW(beschriftung!$A9)-1,COLUMN(beschriftung!Q$1)))) -> Construction | S8: =IF(INDIRECT("beschriftung!"&ADDRESS(beschriftung!$C$1*12+ROW(beschriftung!$A9)-1,COLUMN(beschriftung!S$1)))="","",INDIRECT("beschriftung!"&ADDRESS(beschriftung!$C$1*12+ROW(beschriftung!$A9)-1,COLUMN(beschriftung!S$1)))) -> Fixed assets and software | AE8: =IF(INDIRECT("beschriftung!"&ADDRESS(beschriftung!$C$1*12+ROW(beschriftung!$A9)-1,COLUMN(beschriftung!AE$1)))="","",INDIRECT("beschriftung!"&ADDRESS(beschriftung!$C$1*12+ROW(beschriftung!$A9)-1,COLUMN(beschriftung!AE$1)))) -> thereof exp. of goods excluding non-monetary gold | AG8: =IF(INDIRECT("beschriftung!"&ADDRESS(beschriftung!$C$1*12+ROW(beschriftung!$A9)-1,COLUMN(beschriftung!AG$1)))="","",INDIRECT("beschriftung!"&ADDRESS(beschriftung!$C$1*12+ROW(beschriftung!$A9)-1,COLUMN(beschriftung!AG$1)))) -> thereof exp. of goods excluding valuables and merchanting | AO8: =IF(INDIRECT("beschriftung!"&ADDRESS(beschriftung!$C$1*12+ROW(beschriftung!$A9)-1,COLUMN(beschriftung!AO$1)))="","",INDIRECT("beschriftung!"&ADDRESS(beschriftung!$C$1*12+ROW(beschriftung!$A9)-1,COLUMN(beschriftung!AO$1)))) -> thereof imp. of goods excluding non-monetary gold | AQ8: =IF(INDIRECT("beschriftung!"&ADDRESS(beschriftung!$C$1*12+ROW(beschriftung!$A9)-1,COLUMN(beschriftung!AQ$1)))="","",INDIRECT("beschriftung!"&ADDRESS(beschriftung!$C$1*12+ROW(beschriftung!$A9)-1,COLUMN(beschriftung!AQ$1)))) -> thereof imp. of goods excluding valuables
C11: B1GQ | E11: P3_P5 | G11: P3 | I11: P31_S14_S15 | K11: P3_S13 | M11: P5 | O11: P51G | Q11: P5111_N111_112G | S11: P5111_N113T117G | U11: P52_YA0 | W11: P53 | Y11: B11 | AA11: P6 | AC11: P61 | AE11: P61XF11 | AI11: P62 | AK11: P7 | AM11: P71 | AO11: P71XF11 | AS11: P72 | AU11: P3_P51G_P6 | AW11: P3_P51G
A12: 1980 | C12: 208464.8 | E12: 213953.82 | G12: 139955.75 | I12: 120131.23 | K12: 19824.525 | M12: 73998.068 | O12: 63526.074 | Q12: 26091.579 | S12: 37434.495 | U12: 9366.0315 | W12: 1105.9621 | Y12: -5489.0144 | AA12: 94700.661 | AC12: 72036.142 | AE12: 50108.542 | AG12: 44744.489 | AI12: 22664.519 | AK12: 100189.68 | AM12: 82978.504 | AO12: 60751.506 | AQ12: 55436.063 | AS12: 17211.171 | AU12: 271746.01 | AW12: 203481.83 | AY12: 68264.182 | BA12: 45599.663 | BC12: 72647.234
A13: 1981 | C13: 223793.42 | D13: 0.073530966 | E13: 223651.78 | F13: 0.045327345 | G13: 150157.03 | H13: 0.072889306 | I13: 128517.07 | J13: 0.069805713 | K13: 21639.957 | L13: 0.091575046 | M13: 73494.749 | N13: -0.0068017851 | O13: 68852.265 | P13: 0.083842593 | Q13: 29183.609 | R13: 0.11850681 | S13: 39668.656 | T13: 0.059681881 | U13: 7468.9214 | W13: -2826.4376 | Y13: 141.64532 | AA13: 105879.32 | AB13: 0.11804209 | AC13: 80450.081 | AD13: 0.11680162 | AE13: 54778.581 | AF13: 0.09319845 | AG13: 48553.941 | AH13: 0.085137905 | AI13: 25429.244 | AJ13: 0.12198473 | AK13: 105737.68 | AL13: 0.055375007 | AM13: 86624.948 | AN13: 0.043944447 | AO13: 62259.035 | AP13: 0.024814686 | AQ13: 58581.455 | AR13: 0.056739105 | AS13: 19112.731 | AT13: 0.11048403 | AU13: 294018.69 | AV13: 0.081961391 | AW13: 219009.29 | AX13: 0.076308871 | AY13: 75009.394 | AZ13: 0.098810416 | BA13: 49580.15 | BB13: 0.087292024 | BC13: 77694.186 | BD13: 0.069472048
A14: 1982 | C14: 237092.14 | D14: 0.05942407 | E14: 236891.16 | F14: 0.059196406 | G14: 159819.97 | H14: 0.06435226 | I14: 136314.87 | J14: 0.060675171 | K14: 23505.106 | L14: 0.086190049 | M14: 77071.186 | N14: 0.048662485 | O14: 69221.447 | P14: 0.0053619383 | Q14: 29577.215 | R14: 0.01348722 | S14: 39644.232 | T14: -0.00061570433 | U14: 5977.8063 | W14: 1871.9331 | Y14: 200.98007 | AA14: 103100.9 | AB14: -0.026241405 | AC14: 74659.732 | AD14: -0.071974433 | AE14: 54484.632 | AF14: -0.0053661296 | AG14: 49306.66 | AH14: 0.015502732 | AI14: 28441.171 | AJ14: 0.11844342 | AK14: 102899.92 | AL14: -0.026837708 | AM14: 82683.184 | AN14: -0.045503804 | AO14: 59654.33 | AP14: -0.041836584 | AQ14: 56381.767 | AR14: -0.03754923 | AS14: 20216.739 | AT14: 0.057762947 | AU14: 307712.84 | AV14: 0.046575782 | AW14: 229041.42 | AX14: 0.04580685 | AY14: 78671.419 | AZ14: 0.048820879 | BA14: 50230.248 | BB14: 0.013112058 | BC14: 76598.506 | BD14: -0.014102482
A15: 1983 | C15: 244254.91 | D15: 0.030210899 | E15: 247846.61 | F15: 0.046246783 | G15: 167423.99 | H15: 0.047578618 | I15: 142520.02 | J15: 0.045520727 | K15: 24903.967 | L15: 0.05951309 | M15: 80422.627 | N15: 0.043485002 | O15: 72970.209 | P15: 0.054156084 | Q15: 31223.834 | R15: 0.055671883 | S15: 41746.375 | T15: 0.053025198 | U15: 1924.6149 | W15: 5527.8027 | Y15: -3591.7074 | AA15: 103107.79 | AB15: 6.6837163e-05 | AC15: 73085.743 | AD15: -0.021082167 | AE15: 55521.343 | AF15: 0.019027587 | AG15: 50449.665 | AH15: 0.02318155 | AI15: 30022.051 | AJ15: 0.055584207 | AK15: 106699.5 | AL15: 0.036924989 | AM15: 85823.163 | AN15: 0.037976033 | AO15: 62732.52 | AP15: 0.051600453 | AQ15: 58557.215 | AR15: 0.038584249 | AS15: 20876.338 | AT15: 0.032626389 | AU15: 321763.84 | AV15: 0.045662721 | AW15: 240394.2 | AX15: 0.049566475 | AY15: 81369.648 | AZ15: 0.034297455 | BA15: 51347.598 | BB15: 0.022244556 | BC15: 79433.553 | BD15: 0.037011784
A16: 1984 | C16: 261062.58 | D16: 0.068812014 | E16: 255111.07 | F16: 0.029310295 | G16: 175405.49 | H16: 0.047672428 | I16: 149315.63 | J16: 0.047681787 | K16: 26089.866 | L16: 0.047618865 | M16: 79705.576 | N16: -0.0089160307 | O16: 77356.349 | P16: 0.060108635 | Q16: 32993.142 | R16: 0.05666529 | S16: 44363.207 | T16: 0.062684055 | U16: 6716.4142 | W16: -4367.1869 | Y16: 5951.5073 | AA16: 120982.92 | AB16: 0.17336351 | AC16: 88066.905 | AD16: 0.20498064 | AE16: 62689.905 | AF16: 0.12911363 | AG16: 55876.338 | AH16: 0.1075661 | AI16: 32916.017 | AJ16: 0.096394699 | AK16: 115031.42 | AL16: 0.078087657 | AM16: 92271.375 | AN16: 0.0751337 | AO16: 71093.788 | AP16: 0.13328442 | AQ16: 65559.722 | AR16: 0.11958401 | AS16: 22760.04 | AT16: 0.090231451 | AU16: 342665.92 | AV16: 0.064960939 | AW16: 252761.84 | AX16: 0.051447363 | AY16: 89904.082 | AZ16: 0.10488474 | BA16: 56988.065 | BB16: 0.10984871 | BC16: 88319.762 | BD16: 0.11186971
A17: 1985 | C17: 276798.76 | D17: 0.06027744 | E17: 271258.52 | F17: 0.063295782 | G17: 184530.81 | H17: 0.052024113 | I17: 156568.32 | J17: 0.048572867 | K17: 27962.493 | L17: 0.071776032 | M17: 86727.716 | N17: 0.088100981 | O17: 83070.429 | P17: 0.073866986 | Q17: 34041.899 | R17: 0.031787122 | S17: 49028.531 | T17: 0.10516199 | U17: 6723.1328 | W17: -3065.8464 | Y17: 5540.2365 | AA17: 129531.83 | AB17: 0.070662106 | AC17: 93153.28 | AD17: 0.0577558 | AE17: 68859.18 | AF17: 0.098409377 | AG17: 62051.875 | AH17: 0.1105215 | AI17: 36378.551 | AJ17: 0.10519297 | AK17: 123991.59 | AL17: 0.077893321 | AM17: 98660.549 | AN17: 0.0692433 | AO17: 76835.779 | AP17: 0.080766424 | AQ17: 72014.649 | AR17: 0.098458741 | AS17: 25331.045 | AT17: 0.11296133 | AU17: 367421.32 | AV17: 0.072243534 | AW17: 267601.24 | AX17: 0.058709002 | AY17: 99820.084 | AZ17: 0.11029535 | BA17: 63441.533 | BB17: 0.11324245 | BC17: 97345.694 | BD17: 0.10219607
A18: 1986 | C18: 290499.27 | D18: 0.049496287 | E18: 289519.75 | F18: 0.067320359 | G18: 192752.22 | H18: 0.044553061 | I18: 162995.21 | J18: 0.041048505 | K18: 29757.01 | L18: 0.06417586 | M18: 96767.524 | N18: 0.1157624 | O18: 89403.501 | P18: 0.076237377 | Q18: 35581.567 | R18: 0.045228617 | S18: 53821.934 | T18: 0.097767638 | U18: 3487.9579 | W18: 3876.0658 | Y18: 979.5262 | AA18: 125070.49 | AB18: -0.034442044 | AC18: 89162.902 | AD18: -0.042836681 | AE18: 68886.402 | AF18: 0.0003953388 | AG18: 62851.894 | AH18: 0.012892751 | AI18: 35907.587 | AJ18: -0.012946194 | AK18: 124090.96 | AL18: 0.00080141907 | AM18: 99467.907 | AN18: 0.0081831837 | AO18: 75357.547 | AP18: -0.019238838 | AQ18: 70435.318 | AR18: -0.021930691 | AS18: 24623.056 | AT18: -0.027949426 | AU18: 382069.69 | AV18: 0.039868036 | AW18: 282155.72 | AX18: 0.054388702 | AY18: 99913.967 | AZ18: 0.00094051916 | BA18: 64006.38 | BB18: 0.0089034177 | BC18: 95058.375 | BD18: -0.023496871
A19: 1987 | C19: 301578.15 | D19: 0.038137378 | E19: 299155.79 | F19: 0.033282859 | G19: 199884.52 | H19: 0.037002443 | I19: 169147.6 | J19: 0.037745829 | K19: 30736.923 | L19: 0.032930513 | M19: 99271.266 | N19: 0.025873782 | O19: 93760.018 | P19: 0.048728705 | Q19: 37679.984 | R19: 0.058974844 | S19: 56080.034 | T19: 0.041955005 | U19: 3581.8664 | W19: 1929.3822 | Y19: 2422.3618 | AA19: 121666.98 | AB19: -0.027212729 | AC19: 84526.543 | AD19: -0.051998747 | AE19: 69509.143 | AF19: 0.0090401122 | AG19: 62771.774 | AH19: -0.0012747545 | AI19: 37140.437 | AJ19: 0.034333967 | AK19: 119244.62 | AL19: -0.039054777 | AM19: 93595.122 | AN19: -0.059042003 | AO19: 76799.346 | AP19: 0.019132771 | AQ19: 71525.112 | AR19: 0.015472262 | AS19: 25649.496 | AT19: 0.041686116 | AU19: 395170.89 | AV19: 0.034290093 | AW19: 293644.54 | AX19: 0.040718011 | AY19: 101526.35 | AZ19: 0.016137737 | BA19: 64385.915 | BB19: 0.0059296503 | BC19: 97174.608 | BD19: 0.02226246
A20: 1988 | C20: 320153.22 | D20: 0.061592874 | E20: 317698.69 | F20: 0.061984082 | G20: 209030.47 | H20: 0.045756129 | I20: 175790.68 | J20: 0.039273838 | K20: 33239.79 | L20: 0.081428667 | M20: 108668.22 | N20: 0.094659364 | O20: 105130.39 | P20: 0.12127106 | Q20: 42097.188 | R20: 0.11722945 | S20: 63033.207 | T20: 0.1239866 | U20: 4110.7539 | W20: -572.92689 | Y20: 2454.53 | AA20: 132892.23 | AB20: 0.092262058 | AC20: 94095.066 | AD20: 0.1132014 | AE20: 76305.666 | AF20: 0.097778835 | AG20: 68231.762 | AH20: 0.086981591 | AI20: 38797.16 | AJ20: 0.044606986 | AK20: 130437.7 | AL20: 0.093866524 | AM20: 101990.07 | AN20: 0.089694263 | AO20: 83902.824 | AP20: 0.092493991 | AQ20: 78335.212 | AR20: 0.09521271 | AS20: 28447.628 | AT20: 0.10909112 | AU20: 422825.3 | AV20: 0.069980888 | AW20: 314160.86 | AX20: 0.06986787 | AY20: 108664.44 | AZ20: 0.070307767 | BA20: 69867.283 | BB20: 0.085133031 | BC20: 106782.84 | BD20: 0.098875954
A21: 1989 | C21: 345570.29 | D21: 0.079390333 | E21: 343121.51 | F21: 0.080021818 | G21: 223253.16 | H21: 0.068041253 | I21: 185896.86 | J21: 0.057489867 | K21: 37356.302 | L21: 0.12384291 | M21: 119868.35 | N21: 0.10306722 | O21: 115292.58 | P21: 0.096662683 | Q21: 47227.895 | R21: 0.12187767 | S21: 68064.685 | T21: 0.07982267 | U21: 7520.421 | W21: -2944.6483 | Y21: 2448.7738 | AA21: 151750.48 | AB21: 0.14190635 | AC21: 109702.56 | AD21: 0.16586939 | AE21: 86889.457 | AF21: 0.13870256 | AG21: 76125.357 | AH21: 0.11568798 | AI21: 42047.92 | AJ21: 0.083788602 | AK21: 149301.7 | AL21: 0.14462082 | AM21: 117988.78 | AN21: 0.15686537 | AO21: 96912.571 | AP21: 0.15505732 | AQ21: 89408.644 | AR21: 0.14135957 | AS21: 31312.926 | AT21: 0.10072185 | AU21: 458771.44 | AV21: 0.085014148 | AW21: 338545.74 | AX21: 0.077619092 | AY21: 120225.7 | AZ21: 0.10639407 | BA21: 78177.776 | BB21: 0.11894684 | BC21: 120721.57 | BD21: 0.13053342
A22: 1990 | C22: 374762.04 | D22: 0.084474128 | E22: 375632.17 | F22: 0.094749678 | G22: 239889.48 | H22: 0.074517726 | I22: 198814.69 | J22: 0.069489238 | K22: 41074.789 | L22: 0.099541087 | M22: 135742.69 | N22: 0.13243141 | O22: 122965.34 | P22: 0.066550363 | Q22: 50419.832 | R22: 0.067585849 | S22: 72545.511 | T22: 0.065831872 | U22: 11655.447 | W22: 1121.8979 | Y22: -870.13072 | AA22: 151906.08 | AB22: 0.0010253919 | AC22: 110474.25 | AD22: 0.0070344026 | AE22: 91003.149 | AF22: 0.047343971 | AG22: 80399.631 | AH22: 0.056147836 | AI22: 41431.831 | AJ22: -0.014652051 | AK22: 152776.21 | AL22: 0.023271725 | AM22: 120710.04 | AN22: 0.023063715 | AO22: 98872.868 | AP22: 0.020227475 | AQ22: 91664.07 | AR22: 0.025226048 | AS22: 32066.175 | AT22: 0.024055517 | AU22: 486836.83 | AV22: 0.061175121 | AW22: 362854.82 | AX22: 0.071804421 | AY22: 123982.01 | AZ22: 0.031243879 | BA22: 82550.181 | BB22: 0.055929006 | BC22: 123730.25 | BD22: 0.024922434
A23: 1991 | C23: 391415.53 | D23: 0.044437508 | E23: 387730.54 | F23: 0.032208042 | G23: 258212.98 | H23: 0.076383082 | I23: 213111.62 | J23: 0.07191082 | K23: 45101.36 | L23: 0.098030215 | M23: 129517.57 | N23: -0.045859717 | O23: 123102.11 | P23: 0.0011122152 | Q23: 49444.5 | R23: -0.019344208 | S23: 73657.607 | T23: 0.015329627 | U23: 6083.3018 | W23: 332.15782 | Y23: 3684.9836 | AA23: 152674.9 | AB23: 0.0050611338 | AC23: 108516.49 | AD23: -0.017721429 | AE23: 90769.188 | AF23: -0.0025709174 | AG23: 81834.161 | AH23: 0.017842486 | AI23: 44158.41 | AJ23: 0.065808787 | AK23: 148989.91 | AL23: -0.024783291 | AM23: 115378.79 | AN23: -0.04416572 | AO23: 97268.152 | AP23: -0.0162301 | AQ23: 90502.242 | AR23: -0.012674852 | AS23: 33611.123 | AT23: 0.048179999 | AU23: 509445.59 | AV23: 0.046440109 | AW23: 381315.08 | AX23: 0.050875062 | AY23: 128130.51 | AZ23: 0.033460451 | BA23: 83972.096 | BB23: 0.017224862 | BC23: 124113.36 | BD23: 0.0030964117
A24: 1992 | C24: 399556.86 | D24: 0.020799728 | E24: 391226.59 | F24: 0.0090166899 | G24: 269873.21 | H24: 0.045157426 | I24: 222281.42 | J24: 0.043028169 | K24: 47591.79 | L24: 0.055218529 | M24: 121353.38 | N24: -0.063035367 | O24: 112723.54 | P24: -0.084308599 | Q24: 47727.925 | R24: -0.034717208 | S24: 64995.616 | T24: -0.11759805 | U24: 8227.8589 | W24: 401.97958 | Y24: 8330.2743 | AA24: 159453.54 | AB24: 0.044399222 | AC24: 114053.92 | AD24: 0.051028512 | AE24: 94961.823 | AF24: 0.046190068 | AG24: 86416.906 | AH24: 0.056000401 | AI24: 45399.622 | AJ24: 0.028108163 | AK24: 151123.27 | AL24: 0.014318795 | AM24: 115095.99 | AN24: -0.0024510834 | AO24: 94699.76 | AP24: -0.026405268 | AQ24: 88735.272 | AR24: -0.019524048 | AS24: 36027.282 | AT24: 0.071885701 | AU24: 516091.56 | AV24: 0.013045492 | AW24: 382596.75 | AX24: 0.0033611763 | AY24: 133494.81 | AZ24: 0.041865919 | BA24: 88095.186 | BB24: 0.049100711 | BC24: 124762.55 | BD24: 0.0052306131
... A57: 2025 | C57: 867544.67 | D57: 0.015911439 | E57: 789956.37 | F57: 0.051796153 | G57: 534138.83 | H57: 0.021626666 | I57: 429665.13 | J57: 0.020372586 | K57: 104473.71 | L57: 0.026816848 | M57: 255817.54 | N57: 0.12091088 | O57: 225532.29 | P57: -0.0015089663 | Q57: 66454.017 | R57: 0.003619322 | S57: 159078.28 | T57: -0.003635792 | U57: 21734.636 | W57: 8550.6112 | Y57: 77588.3 | AA57: 677142.42 | AB57: 0.11365344 | AC57: 514410.47 | AD57: 0.1636785 | AE57: 362405.05 | AF57: 0.04649025 | AG57: 281040.6 | AH57: 0.025656503 | AI57: 162731.94 | AJ57: -0.019577423 | AK57: 599554.12 | AL57: 0.18691959 | AM57: 424138.87 | AN57: 0.2981039 | AO57: 255934.01 | AP57: 0.079041469 | AQ57: 241531.61 | AR57: 0.06153951 | AS57: 175415.24 | AT57: -0.016716037 | AU57: 1262756.9 | AV57: 0.012332518 | AW57: 759671.12 | AX57: 0.01464699 | AY57: 503085.76 | AZ57: 0.0088575537 | BA57: 340353.82 | BB57: 0.023044081 | BC57: 416946.85 | BD57: 0.027147649

Sheet tableauR
A1: annees | B1: Y | C1: C | D1: I | E1: G | F1: X | G1: M
A2: 1980 | B2: 208464.8 | C2: 120131.23 | D2: 19824.525 | E2: 63526.074 | F2: 94700.661 | G2: 100189.68
A3: 1981 | B3: 223793.42 | C3: 128517.07 | D3: 21639.957 | E3: 68852.265 | F3: 105879.32 | G3: 105737.68
A4: 1982 | B4: 237092.14 | C4: 136314.87 | D4: 23505.106 | E4: 69221.447 | F4: 103100.9 | G4: 102899.92
A5: 1983 | B5: 244254.91 | C5: 142520.02 | D5: 24903.967 | E5: 72970.209 | F5: 103107.79 | G5: 106699.5
A6: 1984 | B6: 261062.58 | C6: 149315.63 | D6: 26089.866 | E6: 77356.349 | F6: 120982.92 | G6: 115031.42
A7: 1985 | B7: 276798.76 | C7: 156568.32 | D7: 27962.493 | E7: 83070.429 | F7: 129531.83 | G7: 123991.59
A8: 1986 | B8: 290499.27 | C8: 162995.21 | D8: 29757.01 | E8: 89403.501 | F8: 125070.49 | G8: 124090.96
A9: 1987 | B9: 301578.15 | C9: 169147.6 | D9: 30736.923 | E9: 93760.018 | F9: 121666.98 | G9: 119244.62
A10: 1988 | B10: 320153.22 | C10: 175790.68 | D10: 33239.79 | E10: 105130.39 | F10: 132892.23 | G10: 130437.7
A11: 1989 | B11: 345570.29 | C11: 185896.86 | D11: 37356.302 | E11: 115292.58 | F11: 151750.48 | G11: 149301.7
A12: 1990 | B12: 374762.04 | C12: 198814.69 | D12: 41074.789 | E12: 122965.34 | F12: 151906.08 | G12: 152776.21
A13: 1991 | B13: 391415.53 | C13: 213111.62 | D13: 45101.36 | E13: 123102.11 | F13: 152674.9 | G13: 148989.91
... A47: 2025 | B47: 867544.67 | C47: 429665.13 | D47: 104473.71 | E47: 225532.29 | F47: 677142.42 | G47: 599554.12

Sheet exercice
A1: Calcul des contribution à la croissance des principaux aggrégats de la demande
C4: PIB | D4: Households and NPISH expenditures | E4: General government expenditure | F4: Gross fixed capital formation | G4: Net Export | H4: Export of goods and services
C5: B1GQ | D5: P31_S14_S15 | E5: P3_S13 | F5: P51G | G5: B11 | H5: P6
C6: Y | D6: C | E6: G | F6: I | G6: NX | H6: X | I6: Contribution à la croissance | O6: Moyenne des contributions | V6: Contributions relatives à la croissance
A7: 1980 | C7: 208464.8 | D7: 120131.23 | E7: 19824.525 | F7: 63526.074 | G7: -5489.0144 | H7: 94700.661 | J7: C | K7: I | L7: G | M7: NX | N7: X | O7: Période | P7: C | Q7: I | R7: G | S7: NX | T7: X | V7: C | W7: I | X7: G | Y7: NX | Z7: X | AA7: Taux_croissance_pib
A8: 1981 | C8: 223793.42 | D8: 128517.07 | E8: 21639.957 | F8: 68852.265 | G8: 141.64532 | H8: 105879.32 | I8: 1981 | J8: =(D8-D7)/C7 -> 0.040226674 | K8: =(F8-F7)/C7 -> 0.025549593 | L8: =(E8-E7)/C7 -> 0.0087085769 | M8: =(G8-G7)/C7 -> 0.027010122 | N8: =(H8-H7)/C7 -> 0.053623746 | O8: 1980 à 2025 | P8: =AVERAGE(J8:J52) -> 0.015809846 | Q8: =AVERAGE(K8:K52) -> 0.0083559646 | R8: =AVERAGE(L8:L52) -> 0.0041418355 | S8: =AVERAGE(M8:M52) -> 0.0041279253 | T8: =AVERAGE(N8:N52) -> 0.024261218 | U8: 1981 | V8: =J8/AA8 -> 1.3054431 | W8: =K8/AA8 -> 0.82913984 | X8: =L8/AA8 -> 0.28261226 | Y8: =M8/AA8 -> 0.87653718 | Z8: =N8/AA8 -> 1.7402072 | AA8: =LOG(C8)-LOG(C7) -> 0.030814576
A9: 1982 | C9: 237092.14 | D9: 136314.87 | E9: 23505.106 | F9: 69221.447 | G9: 200.98007 | H9: 103100.9 | I9: 1982 | J9: =(D9-D8)/C8 -> 0.034843719 | K9: =(F9-F8)/C8 -> 0.0016496535 | L9: =(E9-E8)/C8 -> 0.0083342437 | M9: =(G9-G8)/C8 -> 0.00026513177 | N9: =(H9-H8)/C8 -> -0.01241512 | O9: 1980 à 2007 | P9: =AVERAGE(J8:J34) -> 0.020440946 | Q9: =AVERAGE(K8:K34) -> 0.010665805 | R9: =AVERAGE(L8:L34) -> 0.0047908449 | S9: =AVERAGE(M8:M34) -> 0.0054745917 | T9: =AVERAGE(N8:N34) -> 0.024327356 | U9: 1982 | V9: =J9/AA9 -> 1.3898663 | W9: =K9/AA9 -> 0.065802324 | X9: =L9/AA9 -> 0.3324411 | Y9: =M9/AA9 -> 0.010575728 | Z9: =N9/AA9 -> -0.49522143 | AA9: =LOG(C9)-LOG(C8) -> 0.025069836
A10: 1983 | C10: 244254.91 | D10: 142520.02 | E10: 24903.967 | F10: 72970.209 | G10: -3591.7074 | H10: 103107.79 | I10: 1983 | J10: =(D10-D9)/C9 -> 0.026171901 | K10: =(F10-F9)/C9 -> 0.015811416 | L10: =(E10-E9)/C9 -> 0.0059000752 | M10: =(G10-G9)/C9 -> -0.015996682 | N10: =(H10-H9)/C9 -> 2.9064531e-05 | O10: 2008 à 2025 | P10: =AVERAGE(J35:J52) -> 0.0088631954 | Q10: =AVERAGE(K35:K52) -> 0.0048912041 | R10: =AVERAGE(L35:L52) -> 0.0031683213 | S10: =AVERAGE(M35:M52) -> 0.0021079258 | T10: =AVERAGE(N35:N52) -> 0.024162011 | U10: 1983 | V10: =J10/AA10 -> 2.0247267 | W10: =K10/AA10 -> 1.2232125 | X10: =L10/AA10 -> 0.45644525 | Y10: =M10/AA10 -> -1.2375452 | Z10: =N10/AA10 -> 0.0022485082 | AA10: =LOG(C10)-LOG(C9) -> 0.01292614
A11: 1984 | C11: 261062.58 | D11: 149315.63 | E11: 26089.866 | F11: 77356.349 | G11: 5951.5073 | H11: 120982.92 | I11: 1984 | J11: =(D11-D10)/C10 -> 0.027821792 | K11: =(F11-F10)/C10 -> 0.017957222 | L11: =(E11-E10)/C10 -> 0.0048551682 | M11: =(G11-G10)/C10 -> 0.039070719 | N11: =(H11-H10)/C10 -> 0.073182272 | U11: 1984 | V11: =J11/AA11 -> 0.96264757 | W11: =K11/AA11 -> 0.62132865 | X11: =L11/AA11 -> 0.16799119 | Y11: =M11/AA11 -> 1.3518659 | Z11: =N11/AA11 -> 2.5321423 | AA11: =LOG(C11)-LOG(C10) -> 0.028901327
A12: 1985 | C12: 276798.76 | D12: 156568.32 | E12: 27962.493 | F12: 83070.429 | G12: 5540.2365 | H12: 129531.83 | I12: 1985 | J12: =(D12-D11)/C11 -> 0.027781416 | K12: =(F12-F11)/C11 -> 0.02188778 | L12: =(E12-E11)/C11 -> 0.0071730964 | M12: =(G12-G11)/C11 -> -0.0015753726 | N12: =(H12-H11)/C11 -> 0.032746586 | U12: 1985 | V12: =J12/AA12 -> 1.0929166 | W12: =K12/AA12 -> 0.86106188 | X12: =L12/AA12 -> 0.2821885 | Y12: =M12/AA12 -> -0.061974915 | Z12: =N12/AA12 -> 1.2882456 | AA12: =LOG(C12)-LOG(C11) -> 0.025419521
A13: 1986 | C13: 290499.27 | D13: 162995.21 | E13: 29757.01 | F13: 89403.501 | G13: 979.5262 | H13: 125070.49 | I13: 1986 | J13: =(D13-D12)/C12 -> 0.023218656 | K13: =(F13-F12)/C12 -> 0.022879696 | L13: =(E13-E12)/C12 -> 0.0064831107 | M13: =(G13-G12)/C12 -> -0.016476628 | N13: =(H13-H12)/C12 -> -0.016117634 | U13: 1986 | V13: =J13/AA13 -> 1.1066565 | W13: =K13/AA13 -> 1.0905009 | X13: =L13/AA13 -> 0.30900051 | Y13: =M13/AA13 -> -0.78531537 | Z13: =N13/AA13 -> -0.76820484 | AA13: =LOG(C13)-LOG(C12) -> 0.020980906
A14: 1987 | C14: 301578.15 | D14: 169147.6 | E14: 30736.923 | F14: 93760.018 | G14: 2422.3618 | H14: 121666.98 | I14: 1987 | J14: =(D14-D13)/C13 -> 0.021178674 | K14: =(F14-F13)/C13 -> 0.014996653 | L14: =(E14-E13)/C13 -> 0.003373205 | M14: =(G14-G13)/C13 -> 0.0049667442 | N14: =(H14-H13)/C13 -> -0.011716068 | U14: 1987 | V14: =J14/AA14 -> 1.3029159 | W14: =K14/AA14 -> 0.92259686 | X14: =L14/AA14 -> 0.20752019 | Y14: =M14/AA14 -> 0.30555502 | Z14: =N14/AA14 -> -0.72077467 | AA14: =LOG(C14)-LOG(C13) -> 0.016254828
A15: 1988 | C15: 320153.22 | D15: 175790.68 | E15: 33239.79 | F15: 105130.39 | G15: 2454.53 | H15: 132892.23 | I15: 1988 | J15: =(D15-D14)/C14 -> 0.022027708 | K15: =(F15-F14)/C14 -> 0.037702919 | L15: =(E15-E14)/C14 -> 0.0082992308 | M15: =(G15-G14)/C14 -> 0.00010666612 | N15: =(H15-H14)/C14 -> 0.037221682 | U15: 1988 | V15: =J15/AA15 -> 0.8485905 | W15: =K15/AA15 -> 1.4524588 | X15: =L15/AA15 -> 0.31971771 | Y15: =M15/AA15 -> 0.0041091818 | Z15: =N15/AA15 -> 1.4339198 | AA15: =LOG(C15)-LOG(C14) -> 0.025957995
A16: 1989 | C16: 345570.29 | D16: 185896.86 | E16: 37356.302 | F16: 115292.58 | G16: 2448.7738 | H16: 151750.48 | I16: 1989 | J16: =(D16-D15)/C15 -> 0.031566706 | K16: =(F16-F15)/C15 -> 0.031741633 | L16: =(E16-E15)/C15 -> 0.012857944 | M16: =(G16-G15)/C15 -> -1.7979454e-05 | N16: =(H16-H15)/C15 -> 0.058903831 | U16: 1989 | V16: =J16/AA16 -> 0.95141985 | W16: =K16/AA16 -> 0.95669214 | X16: =L16/AA16 -> 0.38753817 | Y16: =M16/AA16 -> -0.00054190036 | Z16: =N16/AA16 -> 1.7753602 | AA16: =LOG(C16)-LOG(C15) -> 0.033178524
A17: 1990 | C17: 374762.04 | D17: 198814.69 | E17: 41074.789 | F17: 122965.34 | G17: -870.13072 | H17: 151906.08 | I17: 1990 | J17: =(D17-D16)/C16 -> 0.037381197 | K17: =(F17-F16)/C16 -> 0.022203191 | L17: =(E17-E16)/C16 -> 0.010760436 | M17: =(G17-G16)/C16 -> -0.0096041373 | N17: =(H17-H16)/C16 -> 0.00045028092 | U17: 1990 | V17: =J17/AA17 -> 1.061387 | W17: =K17/AA17 -> 0.63042868 | X17: =L17/AA17 -> 0.30552759 | Y17: =M17/AA17 -> -0.2726961 | Z17: =N17/AA17 -> 0.0127851 | AA17: =LOG(C17)-LOG(C16) -> 0.035219195
A18: 1991 | C18: 391415.53 | D18: 213111.62 | E18: 45101.36 | F18: 123102.11 | G18: 3684.9836 | H18: 152674.9 | I18: 1991 | J18: =(D18-D17)/C17 -> 0.038149348 | K18: =(F18-F17)/C17 -> 0.00036493538 | L18: =(E18-E17)/C17 -> 0.010744339 | M18: =(G18-G17)/C17 -> 0.012154685 | N18: =(H18-H17)/C17 -> 0.0020514805 | U18: 1991 | V18: =J18/AA18 -> 2.020359 | W18: =K18/AA18 -> 0.019326686 | X18: =L18/AA18 -> 0.56901162 | Y18: =M18/AA18 -> 0.64370239 | Z18: =N18/AA18 -> 0.10864477 | AA18: =LOG(C18)-LOG(C17) -> 0.01888246
A19: 1992 | C19: 399556.86 | D19: 222281.42 | E19: 47591.79 | F19: 112723.54 | G19: 8330.2743 | H19: 159453.54 | I19: 1992 | J19: =(D19-D18)/C18 -> 0.023427284 | K19: =(F19-F18)/C18 -> -0.026515469 | L19: =(E19-E18)/C18 -> 0.0063626263 | M19: =(G19-G18)/C18 -> 0.011867926 | N19: =(H19-H18)/C18 -> 0.017318288 | U19: 1992 | V19: =J19/AA19 -> 2.6203416 | W19: =K19/AA19 -> -2.965755 | X19: =L19/AA19 -> 0.71165971 | Y19: =M19/AA19 -> 1.3274275 | Z19: =N19/AA19 -> 1.9370504 | AA19: =LOG(C19)-LOG(C18) -> 0.0089405459
A20: 1993 | C20: 408319.61 | D20: 227140.16 | E20: 48707.238 | F20: 107900.91 | G20: 13921.307 | H20: 163182.5 | I20: 1993 | J20: =(D20-D19)/C19 -> 0.012160325 | K20: =(F20-F19)/C19 -> -0.012069948 | L20: =(E20-E19)/C19 -> 0.0027917117 | M20: =(G20-G19)/C19 -> 0.013993084 | N20: =(H20-H19)/C19 -> 0.0093327276 | U20: 1993 | V20: =J20/AA20 -> 1.2906806 | W20: =K20/AA20 -> -1.2810881 | X20: =L20/AA20 -> 0.29630854 | Y20: =M20/AA20 -> 1.4852072 | Z20: =N20/AA20 -> 0.9905632 | AA20: =LOG(C20)-LOG(C19) -> 0.0094216378
A21: 1994 | C21: 418401.77 | D21: 229582.01 | E21: 49912.558 | F21: 111551.67 | G21: 14377.682 | H21: 164176.93 | I21: 1994 | J21: =(D21-D20)/C20 -> 0.0059802385 | K21: =(F21-F20)/C20 -> 0.0089409388 | L21: =(E21-E20)/C20 -> 0.0029519025 | M21: =(G21-G20)/C20 -> 0.0011176906 | N21: =(H21-H20)/C20 -> 0.0024354112 | U21: 1994 | V21: =J21/AA21 -> 0.56453153 | W21: =K21/AA21 -> 0.84402017 | X21: =L21/AA21 -> 0.27865812 | Y21: =M21/AA21 -> 0.10550943 | Z21: =N21/AA21 -> 0.2299016 | AA21: =LOG(C21)-LOG(C20) -> 0.010593276
A22: 1995 | C22: 423515.36 | D22: 234427.98 | E22: 50375.483 | F22: 112691.99 | G22: 13809.663 | H22: 166014.65 | I22: 1995 | J22: =(D22-D21)/C21 -> 0.011582096 | K22: =(F22-F21)/C21 -> 0.0027254258 | L22: =(E22-E21)/C21 -> 0.0011064142 | M22: =(G22-G21)/C21 -> -0.0013575923 | N22: =(H22-H21)/C21 -> 0.004392259 | U22: 1995 | V22: =J22/AA22 -> 2.1953869 | W22: =K22/AA22 -> 0.51660463 | X22: =L22/AA22 -> 0.20972088 | Y22: =M22/AA22 -> -0.2573317 | Z22: =N22/AA22 -> 0.83255296 | AA22: =LOG(C22)-LOG(C21) -> 0.0052756512
... A52: 2025 | C52: 867544.67 | D52: 429665.13 | E52: 104473.71 | F52: 225532.29 | G52: 77588.3 | H52: 677142.42 | I52: 2025 | J52: =(D52-D51)/C51 -> 0.01004573 | K52: =(F52-F51)/C51 -> -0.00039912424 | L52: =(E52-E51)/C51 -> 0.0031951096 | M52: =(G52-G51)/C51 -> -0.029643244 | N52: =(H52-H51)/C51 -> 0.080923853 | U52: 2025 | V52: =J52/AA52 -> 1.4652784 | W52: =K52/AA52 -> -0.05821659 | X52: =L52/AA52 -> 0.46604131 | Y52: =M52/AA52 -> -4.323788 | Z52: =N52/AA52 -> 11.80362 | AA52: =LOG(C52)-LOG(C51) -> 0.0068558505

Sheet real_y
A1: =IF(INDIRECT("beschriftung!"&ADDRESS(beschriftung!$C$1*12+ROW(beschriftung!$A1)-1,COLUMN(beschriftung!B$1)))="","",INDIRECT("beschriftung!"&ADDRESS(beschriftung!$C$1*12+ROW(beschriftung!$A1)-1,COLUMN(beschriftung!B$1)))) -> ESA 2010, Annual aggregates of Gross Domestic Product, expenditure approach (SFSO, SECO), raw data
A2: =IF(INDIRECT("beschriftung!"&ADDRESS(beschriftung!$C$1*12+ROW(beschriftung!$A3)-1,COLUMN(beschriftung!B$1)))="","",INDIRECT("beschriftung!"&ADDRESS(beschriftung!$C$1*12+ROW(beschriftung!$A3)-1,COLUMN(beschriftung!B$1)))) -> In Mio. Swiss Francs, at prices of preceding year, chained values, reference year 2020, percentage change to previous year
A3: =IF(INDIRECT("beschriftung!"&ADDRESS(beschriftung!$C$1*12+ROW(beschriftung!$A5)-1,COLUMN(beschriftung!B$1)))="","",INDIRECT("beschriftung!"&ADDRESS(beschriftung!$C$1*12+ROW(beschriftung!$A5)-1,COLUMN(beschriftung!B$1))))
C4: =IF(INDIRECT("beschriftung!"&ADDRESS(beschriftung!$C$1*12+ROW(beschriftung!$A5)-1,COLUMN(beschriftung!C$1)))="","",INDIRECT("beschriftung!"&ADDRESS(beschriftung!$C$1*12+ROW(beschriftung!$A5)-1,COLUMN(beschriftung!C$1)))) -> Gross domestic product
E5: =IF(INDIRECT("beschriftung!"&ADDRESS(beschriftung!$C$1*12+ROW(beschriftung!$A6)-1,COLUMN(beschriftung!E$1)))="","",INDIRECT("beschriftung!"&ADDRESS(beschriftung!$C$1*12+ROW(beschriftung!$A6)-1,COLUMN(beschriftung!E$1)))) -> Internal demand | Y5: =IF(INDIRECT("beschriftung!"&ADDRESS(beschriftung!$C$1*12+ROW(beschriftung!$A6)-1,COLUMN(beschriftung!Y$1)))="","",INDIRECT("beschriftung!"&ADDRESS(beschriftung!$C$1*12+ROW(beschriftung!$A6)-1,COLUMN(beschriftung!Y$1)))) -> Trade balance (goods and services) | AU5: =IF(INDIRECT("beschriftung!"&ADDRESS(beschriftung!$C$1*12+ROW(beschriftung!$A6)-1,COLUMN(beschriftung!AU$1)))="","",INDIRECT("beschriftung!"&ADDRESS(beschriftung!$C$1*12+ROW(beschriftung!$A6)-1,COLUMN(beschriftung!AU$1)))) -> Global demand excluding inventories change, stat. discrepancies and valuables
G6: =IF(INDIRECT("beschriftung!"&ADDRESS(beschriftung!$C$1*12+ROW(beschriftung!$A7)-1,COLUMN(beschriftung!G$1)))="","",INDIRECT("beschriftung!"&ADDRESS(beschriftung!$C$1*12+ROW(beschriftung!$A7)-1,COLUMN(beschriftung!G$1)))) -> Final consumption expenditure | M6: =IF(INDIRECT("beschriftung!"&ADDRESS(beschriftung!$C$1*12+ROW(beschriftung!$A7)-1,COLUMN(beschriftung!M$1)))="","",INDIRECT("beschriftung!"&ADDRESS(beschriftung!$C$1*12+ROW(beschriftung!$A7)-1,COLUMN(beschriftung!M$1)))) -> Gross capital formation | AA6: =IF(INDIRECT("beschriftung!"&ADDRESS(beschriftung!$C$1*12+ROW(beschriftung!$A7)-1,COLUMN(beschriftung!AA$1)))="","",INDIRECT("beschriftung!"&ADDRESS(beschriftung!$C$1*12+ROW(beschriftung!$A7)-1,COLUMN(beschriftung!AA$1)))) -> Exports of goods and services | AK6: =IF(INDIRECT("beschriftung!"&ADDRESS(beschriftung!$C$1*12+ROW(beschriftung!$A7)-1,COLUMN(beschriftung!AK$1)))="","",INDIRECT("beschriftung!"&ADDRESS(beschriftung!$C$1*12+ROW(beschriftung!$A7)-1,COLUMN(beschriftung!AK$1)))) -> Imports of goods and services | AW6: =IF(INDIRECT("beschriftung!"&ADDRESS(beschriftung!$C$1*12+ROW(beschriftung!$A7)-1,COLUMN(beschriftung!AW$1)))="","",INDIRECT("beschriftung!"&ADDRESS(beschriftung!$C$1*12+ROW(beschriftung!$A7)-1,COLUMN(beschriftung!AW$1)))) -> Final domestic demand | AY6: =IF(INDIRECT("beschriftung!"&ADDRESS(beschriftung!$C$1*12+ROW(beschriftung!$A7)-1,COLUMN(beschriftung!AY$1)))="","",INDIRECT("beschriftung!"&ADDRESS(beschriftung!$C$1*12+ROW(beschriftung!$A7)-1,COLUMN(beschriftung!AY$1)))) -> Exports of goods and services (excluding valuables) | BC6: =IF(INDIRECT("beschriftung!"&ADDRESS(beschriftung!$C$1*12+ROW(beschriftung!$A7)-1,COLUMN(beschriftung!BC$1)))="","",INDIRECT("beschriftung!"&ADDRESS(beschriftung!$C$1*12+ROW(beschriftung!$A7)-1,COLUMN(beschriftung!BC$1)))) -> Imports of goods and services (excluding valuables)
I7: =IF(INDIRECT("beschriftung!"&ADDRESS(beschriftung!$C$1*12+ROW(beschriftung!$A8)-1,COLUMN(beschriftung!I$1)))="","",INDIRECT("beschriftung!"&ADDRESS(beschriftung!$C$1*12+ROW(beschriftung!$A8)-1,COLUMN(beschriftung!I$1)))) -> Households and NPISH | K7: =IF(INDIRECT("beschriftung!"&ADDRESS(beschriftung!$C$1*12+ROW(beschriftung!$A8)-1,COLUMN(beschriftung!K$1)))="","",INDIRECT("beschriftung!"&ADDRESS(beschriftung!$C$1*12+ROW(beschriftung!$A8)-1,COLUMN(beschriftung!K$1)))) -> General government | O7: =IF(INDIRECT("beschriftung!"&ADDRESS(beschriftung!$C$1*12+ROW(beschriftung!$A8)-1,COLUMN(beschriftung!O$1)))="","",INDIRECT("beschriftung!"&ADDRESS(beschriftung!$C$1*12+ROW(beschriftung!$A8)-1,COLUMN(beschriftung!O$1)))) -> Gross fixed capital formation | U7: =IF(INDIRECT("beschriftung!"&ADDRESS(beschriftung!$C$1*12+ROW(beschriftung!$A8)-1,COLUMN(beschriftung!U$1)))="","",INDIRECT("beschriftung!"&ADDRESS(beschriftung!$C$1*12+ROW(beschriftung!$A8)-1,COLUMN(beschriftung!U$1)))) -> Changes in inventories and statistical discrepancies | W7: =IF(INDIRECT("beschriftung!"&ADDRESS(beschriftung!$C$1*12+ROW(beschriftung!$A8)-1,COLUMN(beschriftung!W$1)))="","",INDIRECT("beschriftung!"&ADDRESS(beschriftung!$C$1*12+ROW(beschriftung!$A8)-1,COLUMN(beschriftung!W$1)))) -> Acquisitions less disposals of valuables (including non-monetary gold) | AC7: =IF(INDIRECT("beschriftung!"&ADDRESS(beschriftung!$C$1*12+ROW(beschriftung!$A8)-1,COLUMN(beschriftung!AC$1)))="","",INDIRECT("beschriftung!"&ADDRESS(beschriftung!$C$1*12+ROW(beschriftung!$A8)-1,COLUMN(beschriftung!AC$1)))) -> Exports (exp.) of goods | AI7: =IF(INDIRECT("beschriftung!"&ADDRESS(beschriftung!$C$1*12+ROW(beschriftung!$A8)-1,COLUMN(beschriftung!AI$1)))="","",INDIRECT("beschriftung!"&ADDRESS(beschriftung!$C$1*12+ROW(beschriftung!$A8)-1,COLUMN(beschriftung!AI$1)))) -> Exports of services | AM7: =IF(INDIRECT("beschriftung!"&ADDRESS(beschriftung!$C$1*12+ROW(beschriftung!$A8)-1,COLUMN(beschriftung!AM$1)))="","",INDIRECT("beschriftung!"&ADDRESS(beschriftung!$C$1*12+ROW(beschriftung!$A8)-1,COLUMN(beschriftung!AM$1)))) -> Imports (imp.) of goods | AS7: =IF(INDIRECT("beschriftung!"&ADDRESS(beschriftung!$C$1*12+ROW(beschriftung!$A8)-1,COLUMN(beschriftung!AS$1)))="","",INDIRECT("beschriftung!"&ADDRESS(beschriftung!$C$1*12+ROW(beschriftung!$A8)-1,COLUMN(beschriftung!AS$1)))) -> Imports of services | BA7: =IF(INDIRECT("beschriftung!"&ADDRESS(beschriftung!$C$1*12+ROW(beschriftung!$A8)-1,COLUMN(beschriftung!BA$1)))="","",INDIRECT("beschriftung!"&ADDRESS(beschriftung!$C$1*12+ROW(beschriftung!$A8)-1,COLUMN(beschriftung!BA$1)))) -> thereof exports of goods excluding valuables
Q8: =IF(INDIRECT("beschriftung!"&ADDRESS(beschriftung!$C$1*12+ROW(beschriftung!$A9)-1,COLUMN(beschriftung!Q$1)))="","",INDIRECT("beschriftung!"&ADDRESS(beschriftung!$C$1*12+ROW(beschriftung!$A9)-1,COLUMN(beschriftung!Q$1)))) -> Construction | S8: =IF(INDIRECT("beschriftung!"&ADDRESS(beschriftung!$C$1*12+ROW(beschriftung!$A9)-1,COLUMN(beschriftung!S$1)))="","",INDIRECT("beschriftung!"&ADDRESS(beschriftung!$C$1*12+ROW(beschriftung!$A9)-1,COLUMN(beschriftung!S$1)))) -> Fixed assets and software | AE8: =IF(INDIRECT("beschriftung!"&ADDRESS(beschriftung!$C$1*12+ROW(beschriftung!$A9)-1,COLUMN(beschriftung!AE$1)))="","",INDIRECT("beschriftung!"&ADDRESS(beschriftung!$C$1*12+ROW(beschriftung!$A9)-1,COLUMN(beschriftung!AE$1)))) -> thereof exp. of goods excluding non-monetary gold | AG8: =IF(INDIRECT("beschriftung!"&ADDRESS(beschriftung!$C$1*12+ROW(beschriftung!$A9)-1,COLUMN(beschriftung!AG$1)))="","",INDIRECT("beschriftung!"&ADDRESS(beschriftung!$C$1*12+ROW(beschriftung!$A9)-1,COLUMN(beschriftung!AG$1)))) -> thereof exp. of goods excluding valuables and merchanting | AO8: =IF(INDIRECT("beschriftung!"&ADDRESS(beschriftung!$C$1*12+ROW(beschriftung!$A9)-1,COLUMN(beschriftung!AO$1)))="","",INDIRECT("beschriftung!"&ADDRESS(beschriftung!$C$1*12+ROW(beschriftung!$A9)-1,COLUMN(beschriftung!AO$1)))) -> thereof imp. of goods excluding non-monetary gold | AQ8: =IF(INDIRECT("beschriftung!"&ADDRESS(beschriftung!$C$1*12+ROW(beschriftung!$A9)-1,COLUMN(beschriftung!AQ$1)))="","",INDIRECT("beschriftung!"&ADDRESS(beschriftung!$C$1*12+ROW(beschriftung!$A9)-1,COLUMN(beschriftung!AQ$1)))) -> thereof imp. of goods excluding valuables
C11: B1GQ | E11: P3_P5 | G11: P3 | I11: P31_S14_S15 | K11: P3_S13 | M11: P5 | O11: P51G | Q11: P5111_N111_112G | S11: P5111_N113T117G | U11: P52_YA0 | W11: P53 | Y11: B11 | AA11: P6 | AC11: P61 | AE11: P61XF11 | AI11: P62 | AK11: P7 | AM11: P71 | AO11: P71XF11 | AS11: P72 | AU11: P3_P51G_P6 | AW11: P3_P51G
A12: 1980 | C12: 367723.79 | E12: 364379.07 | G12: 245917.07 | I12: 202112.88 | K12: 43051.206 | M12: 118638.49 | O12: 83748.031 | Q12: 41585.737 | S12: 45017.419 | AA12: 108682.07 | AC12: 72765.381 | AE12: 53979.552 | AG12: 50611.356 | AI12: 36851.652 | AK12: 100689.49 | AM12: 78649.041 | AO12: 53117.656 | AQ12: 49809.555 | AS12: 23048.086 | AU12: 409589.52 | AW12: 328558.37 | AY12: 89429.487 | BA12: 53211.171 | BC12: 74042.749
A13: 1981 | C13: 373612.28 | D13: 0.016013359 | E13: 358223.83 | F13: -0.016892389 | G13: 248743.34 | H13: 0.011492795 | I13: 204059.25 | J13: 0.0096301023 | K13: 44031.922 | L13: 0.022780206 | M13: 110265.16 | N13: -0.070578517 | O13: 84849.581 | P13: 0.013153146 | Q13: 43317.899 | R13: 0.041652791 | S13: 44715.312 | T13: -0.0067109055 | AA13: 125174.78 | AB13: 0.15175187 | AC13: 85521.144 | AD13: 0.17529989 | AE13: 58970.778 | AF13: 0.092465138 | AG13: 52694.291 | AH13: 0.041155486 | AI13: 39685.824 | AJ13: 0.07690762 | AK13: 108145.09 | AL13: 0.074045445 | AM13: 84743.683 | AN13: 0.077491632 | AO13: 52886.023 | AP13: -0.0043607621 | AQ13: 49518.037 | AR13: -0.0058526544 | AS13: 24371.754 | AT13: 0.057430688 | AU13: 418852.6 | AV13: 0.022615544 | AW13: 332504.74 | AX13: 0.012011149 | AY13: 94278.811 | AZ13: 0.054225116 | BA13: 55496.653 | BB13: 0.042951173 | BC13: 74719.506 | BD13: 0.0091400768
A14: 1982 | C14: 368720.14 | D14: -0.013094174 | E14: 360640.81 | F14: 0.0067471219 | G14: 249507.52 | H14: 0.0030721425 | I14: 204573.71 | J14: 0.002521142 | K14: 44311.281 | L14: 0.0063444673 | M14: 111837.04 | N14: 0.014255468 | O14: 81334.602 | P14: -0.041426006 | Q14: 41888.473 | R14: -0.03299851 | S14: 42585.701 | T14: -0.047625983 | AA14: 122695.69 | AB14: -0.019804984 | AC14: 82876.096 | AD14: -0.030928593 | AE14: 58688.149 | AF14: -0.0047926924 | AG14: 50877.657 | AH14: -0.034474984 | AI14: 40296.454 | AJ14: 0.015386593 | AK14: 110540.88 | AL14: 0.02215348 | AM14: 85887.57 | AN14: 0.0134982 | AO14: 52409.572 | AP14: -0.0090090023 | AQ14: 47883.977 | AR14: -0.032999283 | AS14: 25867.739 | AT14: 0.061381948 | AU14: 413379.38 | AV14: -0.013067179 | AW14: 328874.71 | AX14: -0.01091721 | AY14: 92455.028 | AZ14: -0.019344566 | BA14: 53434.515 | BB14: -0.037157887 | BC14: 73988.633 | BD14: -0.0097815473
A15: 1983 | C15: 371076.55 | D15: 0.0063907946 | E15: 368955.06 | F15: 0.023054089 | G15: 253142.28 | H15: 0.014567751 | I15: 207148.16 | J15: 0.012584473 | K15: 45466.454 | L15: 0.026069519 | M15: 116383.44 | N15: 0.040651927 | O15: 84171.526 | P15: 0.034879664 | Q15: 44104.392 | R15: 0.052900459 | S15: 43498.524 | T15: 0.021434962 | AA15: 119273.8 | AB15: -0.027889257 | AC15: 78122.984 | AD15: -0.057352024 | AE15: 59298.638 | AF15: 0.01040225 | AG15: 51571.027 | AH15: 0.013628193 | AI15: 42289.203 | AJ15: 0.049452224 | AK15: 111691.08 | AL15: 0.010405208 | AM15: 86355.526 | AN15: 0.0054484689 | AO15: 55523.716 | AP15: 0.059419373 | AQ15: 50292.163 | AR15: 0.050292101 | AS15: 26661.296 | AT15: 0.030677467 | AU15: 422488.49 | AV15: 0.022035695 | AW15: 335684.54 | AX15: 0.020706466 | AY15: 94850.129 | AZ15: 0.025905571 | BA15: 54106.351 | BB15: 0.012573078 | BC15: 77326.644 | BD15: 0.045115186
A16: 1984 | C16: 382240.23 | D16: 0.030084564 | E16: 365078.58 | F16: -0.010506638 | G16: 257222.7 | H16: 0.016119077 | I16: 210503.21 | J16: 0.016196347 | K16: 46179.226 | L16: 0.015676874 | M16: 108709.57 | N16: -0.065936103 | O16: 87756.063 | P16: 0.0425861 | Q16: 46515.681 | R16: 0.05467231 | S16: 44957.74 | T16: 0.033546326 | AA16: 138052.5 | AB16: 0.15744192 | AC16: 93057.597 | AD16: 0.19116798 | AE16: 64333.809 | AF16: 0.084912074 | AG16: 54745.051 | AH16: 0.061546643 | AI16: 45475.236 | AJ16: 0.075339145 | AK16: 118266.07 | AL16: 0.058867682 | AM16: 91751.969 | AN16: 0.062490999 | AO16: 61170.615 | AP16: 0.10170247 | AQ16: 54066.548 | AR16: 0.075049183 | AS16: 27833.65 | AT16: 0.043972135 | AU16: 437399.89 | AV16: 0.035294223 | AW16: 343792.33 | AX16: 0.024152982 | AY16: 101319.79 | AZ16: 0.068209317 | BA16: 57571.356 | BB16: 0.064040629 | BC16: 82498.379 | BD16: 0.066881665
A17: 1985 | C17: 396282.19 | D17: 0.036735959 | E17: 374976.9 | F17: 0.027112858 | G17: 263857.88 | H17: 0.025795452 | I17: 214998.97 | J17: 0.021357218 | K17: 48543.419 | L17: 0.05119603 | M17: 111972.16 | N17: 0.030012032 | O17: 90912.258 | P17: 0.035965552 | Q17: 47016.815 | R17: 0.010773434 | S17: 47416.975 | T17: 0.054701058 | AA17: 149075.03 | AB17: 0.079843027 | AC17: 100222.96 | AD17: 0.076999248 | AE17: 69364.252 | AF17: 0.078192843 | AG17: 59202.614 | AH17: 0.081424052 | AI17: 49452.116 | AJ17: 0.087451566 | AK17: 125448.57 | AL17: 0.06073166 | AM17: 97232.419 | AN17: 0.059731144 | AO17: 63347.577 | AP17: 0.035588354 | AQ17: 56578.398 | AR17: 0.046458474 | AS17: 29636.932 | AT17: 0.064787847 | AU17: 456492.02 | AV17: 0.043649138 | AW17: 353730.66 | AX17: 0.028907954 | AY17: 109941.44 | AZ17: 0.085093404 | BA17: 62391.883 | BB17: 0.083731341 | BC17: 86720.808 | BD17: 0.051181961
A18: 1986 | C18: 403647.62 | D18: 0.018586328 | E18: 398786.87 | F18: 0.063497156 | G18: 271413.26 | H18: 0.0286343 | I18: 221022.19 | J18: 0.028015091 | K18: 50101.731 | L18: 0.03210139 | M18: 127387.92 | N18: 0.13767496 | O18: 97236.633 | P18: 0.069565703 | Q18: 47735.93 | R18: 0.015294854 | S18: 52502.327 | T18: 0.10724749 | AA18: 151389.7 | AB18: 0.015526908 | AC18: 103070.91 | AD18: 0.028416144 | AE18: 71180.766 | AF18: 0.026188036 | AG18: 60511.865 | AH18: 0.022114742 | AI18: 48587.787 | AJ18: -0.017478107 | AK18: 139704.84 | AL18: 0.11364239 | AM18: 110685.49 | AN18: 0.13835996 | AO18: 69232.15 | AP18: 0.092893425 | AQ18: 61264.504 | AR18: 0.082825003 | AS18: 30151.762 | AT18: 0.017371235 | AU18: 470812.06 | AV18: 0.031369758 | AW18: 368354.06 | AX18: 0.041340479 | AY18: 110451.55 | AZ18: 0.0046398927 | BA18: 63472.683 | BB18: 0.017322764 | BC18: 92426.412 | BD18: 0.065792793
A19: 1987 | C19: 410047.36 | D19: 0.015854782 | E19: 406985.87 | F19: 0.020559852 | G19: 279250.44 | H19: 0.028875439 | I19: 227638.5 | J19: 0.029935049 | K19: 51257.647 | L19: 0.02307138 | M19: 127896.96 | N19: 0.0039959484 | O19: 101220.8 | P19: 0.040973975 | Q19: 49442.797 | R19: 0.03575643 | S19: 54834.653 | T19: 0.044423282 | AA19: 147768.4 | AB19: -0.023920417 | AC19: 98508.576 | AD19: -0.04426405 | AE19: 72018.073 | AF19: 0.011763119 | AG19: 60418.877 | AH19: -0.0015366858 | AI19: 49879.993 | AJ19: 0.026595295 | AK19: 137852.79 | AL19: -0.01325687 | AM19: 107338.97 | AN19: -0.030234549 | AO19: 73413.295 | AP19: 0.060393118 | AQ19: 64792.269 | AR19: 0.057582541 | AS19: 31819.956 | AT19: 0.055326582 | AU19: 483762.14 | AV19: 0.027505842 | AW19: 380402.54 | AX19: 0.032708965 | AY19: 111866.69 | AZ19: 0.012812292 | BA19: 63795.126 | BB19: 0.0050800251 | BC19: 97694.549 | BD19: 0.056998178
A20: 1988 | C20: 423487.06 | D20: 0.032775963 | E20: 416968.16 | F20: 0.024527357 | G20: 286255.31 | H20: 0.025084539 | I20: 232497.34 | J20: 0.021344565 | K20: 53598.373 | L20: 0.045665895 | M20: 130890.45 | N20: 0.02340546 | O20: 109633.98 | P20: 0.083117069 | Q20: 53087.305 | R20: 0.073711617 | S20: 59738.876 | T20: 0.08943656 | AA20: 159072.86 | AB20: 0.076501185 | AC20: 109008.67 | AD20: 0.10659071 | AE20: 77263.43 | AF20: 0.072833898 | AG20: 64733.518 | AH20: 0.071412135 | AI20: 50280.109 | AJ20: 0.0080215603 | AK20: 145668.45 | AL20: 0.05669568 | AM20: 112965.97 | AN20: 0.052422731 | AO20: 76669.686 | AP20: 0.044356954 | AQ20: 68058.465 | AR20: 0.050410267 | AS20: 34120.148 | AT20: 0.07228769 | AU20: 505251.07 | AV20: 0.04442044 | AW20: 396993.48 | AX20: 0.04361419 | AY20: 117096.72 | AZ20: 0.046752354 | BA20: 68202.978 | BB20: 0.069093864 | BC20: 103183.5 | BD20: 0.056184871
A21: 1989 | C21: 441827.41 | D21: 0.043307941 | E21: 437293.02 | F21: 0.048744391 | G21: 296330.74 | H21: 0.035197378 | I21: 238374.3 | J21: 0.025277525 | K21: 58296.76 | L21: 0.087659129 | M21: 140681.44 | N21: 0.074802961 | O21: 114736.17 | P21: 0.046538407 | Q21: 56947.903 | R21: 0.072721684 | S21: 61474.392 | T21: 0.029051714 | AA21: 168283.62 | AB21: 0.057902811 | AC21: 115765.37 | AD21: 0.061983082 | AE21: 81627.05 | AF21: 0.05647717 | AG21: 67625.599 | AH21: 0.044676706 | AI21: 52693.901 | AJ21: 0.048006896 | AK21: 156071.9 | AL21: 0.071418664 | AM21: 122908.73 | AN21: 0.08801556 | AO21: 81596.322 | AP21: 0.064257939 | AQ21: 72100.454 | AR21: 0.059389944 | AS21: 34526.713 | AT21: 0.011915687 | AU21: 526145.31 | AV21: 0.041354174 | AW21: 412473.26 | AX21: 0.038992526 | AY21: 122738.67 | AZ21: 0.048181958 | BA21: 71495.761 | BB21: 0.04827917 | BC21: 108006.56 | BD21: 0.0467425
A22: 1990 | C22: 458062.92 | D22: 0.036746256 | E22: 460751.04 | F22: 0.053643727 | G22: 302525.78 | H22: 0.020905831 | I22: 242133.73 | J22: 0.015771121 | K22: 61005.098 | L22: 0.046457788 | M22: 156806.01 | N22: 0.11461761 | O22: 120100.74 | P22: 0.046755702 | Q22: 57675.252 | R22: 0.012772178 | S22: 65798.241 | T22: 0.070335775 | AA22: 171647.12 | AB22: 0.019987105 | AC22: 120868.19 | AD22: 0.044079011 | AE22: 86013.551 | AF22: 0.053738328 | AG22: 70636.681 | AH22: 0.044525782 | AI22: 50434.997 | AJ22: -0.04286841 | AK22: 165209.22 | AL22: 0.058545583 | AM22: 131500.29 | AN22: 0.069901956 | AO22: 84833.2 | AP22: 0.039669417 | AQ22: 74316.65 | AR22: 0.030737621 | AS22: 35070.652 | AT22: 0.015754165 | AU22: 539518.02 | AV22: 0.025416382 | AW22: 424727.46 | AX22: 0.029709068 | AY22: 124374.6 | AZ22: 0.013328527 | BA22: 74609.691 | BB22: 0.043554052 | BC22: 110906.66 | BD22: 0.026851191
A23: 1991 | C23: 453867.9 | D23: -0.0091581657 | E23: 453539.34 | F23: -0.015652065 | G23: 308697.28 | H23: 0.020399916 | I23: 246541.71 | J23: 0.018204756 | K23: 62897.792 | L23: 0.03102517 | M23: 144361.18 | N23: -0.079364455 | O23: 117882.71 | P23: -0.018468071 | Q23: 55738.814 | R23: -0.033574859 | S23: 65273.915 | T23: -0.0079687066 | AA23: 168915.45 | AB23: -0.01591448 | AC23: 117118.47 | AD23: -0.031023186 | AE23: 83935.899 | AF23: -0.024154947 | AG23: 70113.009 | AH23: -0.007413602 | AI23: 51664.175 | AJ23: 0.024371525 | AK23: 159948.53 | AL23: -0.031842606 | AM23: 126399.55 | AN23: -0.038788862 | AO23: 83632.793 | AP23: -0.014150203 | AQ23: 73341.299 | AR23: -0.013124258 | AS23: 34870.957 | AT23: -0.0056940896 | AU23: 542732.7 | AV23: 0.005958421 | AW23: 427797.48 | AX23: 0.007228215 | AY23: 124653.46 | AZ23: 0.0022421489 | BA23: 73948.309 | BB23: -0.0088645569 | BC23: 109664.66 | BD23: -0.011198641
A24: 1992 | C24: 453669.41 | D24: -0.00043732993 | E24: 448496.88 | F24: -0.011118016 | G24: 310141.88 | H24: 0.0046796375 | I24: 247697.98 | J24: 0.004689957 | K24: 63189.064 | L24: 0.0046308763 | M24: 138209.52 | N24: -0.042613041 | O24: 108324.99 | P24: -0.081078206 | Q24: 55262.091 | R24: -0.0085528026 | S24: 56803.796 | T24: -0.12976269 | AA24: 175599.66 | AB24: 0.039571319 | AC24: 122481.9 | AD24: 0.045794904 | AE24: 86926.728 | AF24: 0.035632302 | AG24: 73158.612 | AH24: 0.043438486 | AI24: 52918.439 | AJ24: 0.024277255 | AK24: 161990.35 | AL24: 0.012765499 | AM24: 125613.57 | AN24: -0.0062182147 | AO24: 79732.479 | AP24: -0.04663618 | AQ24: 70207.643 | AR24: -0.042727027 | AS24: 37588.519 | AT24: 0.077931959 | AU24: 537751.01 | AV24: -0.009178892 | AW24: 417955.55 | AX24: -0.023006052 | AY24: 128638.71 | AZ24: 0.031970597 | BA24: 76611.653 | BB24: 0.036016295 | BC24: 108562.38 | BD24: -0.010051384
... A57: 2025 | C57: 808086.66 | D57: 0.013000779 | E57: 746182.83 | F57: 0.041115025 | G57: 499181.31 | H57: 0.014293556 | I57: 406109.28 | J57: 0.015447625 | K57: 93190.386 | L57: 0.0095172853 | M57: 247571.56 | N57: 0.10255984 | O57: 209556.21 | P57: -0.0053573433 | Q57: 57341.504 | R57: -0.004642869 | S57: 152607.75 | T57: -0.0056536532 | AA57: 569495.79 | AB57: 0.04806187 | AC57: 424416.1 | AD57: 0.070680118 | AE57: 335767.65 | AF57: 0.045540524 | AG57: 280769.18 | AH57: 0.020198516 | AI57: 145284.89 | AJ57: -0.012176919 | AK57: 506294.62 | AL57: 0.097005667 | AM57: 350465.45 | AN57: 0.16684452 | AO57: 249011.27 | AP57: 0.090479543 | AQ57: 237456.3 | AR57: 0.083175018 | AS57: 156182.18 | AT57: -0.030905173 | AU57: 1169330 | AV57: 0.0092913927 | AW57: 708658.74 | AX57: 0.0083651718 | AY57: 461081.48 | AZ57: 0.010682027 | BA57: 316442.08 | BB57: 0.022086611 | BC57: 393038.48 | BD57: 0.03303889

Sheet defl_y
A1: =IF(INDIRECT("beschriftung!"&ADDRESS(beschriftung!$C$1*12+ROW(beschriftung!$A1)-1,COLUMN(beschriftung!B$1)))="","",INDIRECT("beschriftung!"&ADDRESS(beschriftung!$C$1*12+ROW(beschriftung!$A1)-1,COLUMN(beschriftung!B$1)))) -> ESA 2010, Annual aggregates of Gross Domestic Product, expenditure approach (SFSO, SECO), raw data
A2: =IF(INDIRECT("beschriftung!"&ADDRESS(beschriftung!$C$1*12+ROW(beschriftung!$A4)-1,COLUMN(beschriftung!B$1)))="","",INDIRECT("beschriftung!"&ADDRESS(beschriftung!$C$1*12+ROW(beschriftung!$A4)-1,COLUMN(beschriftung!B$1)))) -> Implicit chain price indexes, year-on-year growth rates
A3: =IF(INDIRECT("beschriftung!"&ADDRESS(beschriftung!$C$1*12+ROW(beschriftung!$A5)-1,COLUMN(beschriftung!B$1)))="","",INDIRECT("beschriftung!"&ADDRESS(beschriftung!$C$1*12+ROW(beschriftung!$A5)-1,COLUMN(beschriftung!B$1))))
C4: =IF(INDIRECT("beschriftung!"&ADDRESS(beschriftung!$C$1*12+ROW(beschriftung!$A5)-1,COLUMN(beschriftung!C$1)))="","",INDIRECT("beschriftung!"&ADDRESS(beschriftung!$C$1*12+ROW(beschriftung!$A5)-1,COLUMN(beschriftung!C$1)))) -> Gross domestic product
E5: =IF(INDIRECT("beschriftung!"&ADDRESS(beschriftung!$C$1*12+ROW(beschriftung!$A6)-1,COLUMN(beschriftung!E$1)))="","",INDIRECT("beschriftung!"&ADDRESS(beschriftung!$C$1*12+ROW(beschriftung!$A6)-1,COLUMN(beschriftung!E$1)))) -> Internal demand | Y5: =IF(INDIRECT("beschriftung!"&ADDRESS(beschriftung!$C$1*12+ROW(beschriftung!$A6)-1,COLUMN(beschriftung!Y$1)))="","",INDIRECT("beschriftung!"&ADDRESS(beschriftung!$C$1*12+ROW(beschriftung!$A6)-1,COLUMN(beschriftung!Y$1)))) -> Trade balance (goods and services) | AU5: =IF(INDIRECT("beschriftung!"&ADDRESS(beschriftung!$C$1*12+ROW(beschriftung!$A6)-1,COLUMN(beschriftung!AU$1)))="","",INDIRECT("beschriftung!"&ADDRESS(beschriftung!$C$1*12+ROW(beschriftung!$A6)-1,COLUMN(beschriftung!AU$1)))) -> Global demand excluding inventories change, stat. discrepancies and valuables
G6: =IF(INDIRECT("beschriftung!"&ADDRESS(beschriftung!$C$1*12+ROW(beschriftung!$A7)-1,COLUMN(beschriftung!G$1)))="","",INDIRECT("beschriftung!"&ADDRESS(beschriftung!$C$1*12+ROW(beschriftung!$A7)-1,COLUMN(beschriftung!G$1)))) -> Final consumption expenditure | M6: =IF(INDIRECT("beschriftung!"&ADDRESS(beschriftung!$C$1*12+ROW(beschriftung!$A7)-1,COLUMN(beschriftung!M$1)))="","",INDIRECT("beschriftung!"&ADDRESS(beschriftung!$C$1*12+ROW(beschriftung!$A7)-1,COLUMN(beschriftung!M$1)))) -> Gross capital formation | AA6: =IF(INDIRECT("beschriftung!"&ADDRESS(beschriftung!$C$1*12+ROW(beschriftung!$A7)-1,COLUMN(beschriftung!AA$1)))="","",INDIRECT("beschriftung!"&ADDRESS(beschriftung!$C$1*12+ROW(beschriftung!$A7)-1,COLUMN(beschriftung!AA$1)))) -> Exports of goods and services | AK6: =IF(INDIRECT("beschriftung!"&ADDRESS(beschriftung!$C$1*12+ROW(beschriftung!$A7)-1,COLUMN(beschriftung!AK$1)))="","",INDIRECT("beschriftung!"&ADDRESS(beschriftung!$C$1*12+ROW(beschriftung!$A7)-1,COLUMN(beschriftung!AK$1)))) -> Imports of goods and services | AW6: =IF(INDIRECT("beschriftung!"&ADDRESS(beschriftung!$C$1*12+ROW(beschriftung!$A7)-1,COLUMN(beschriftung!AW$1)))="","",INDIRECT("beschriftung!"&ADDRESS(beschriftung!$C$1*12+ROW(beschriftung!$A7)-1,COLUMN(beschriftung!AW$1)))) -> Final domestic demand | AY6: =IF(INDIRECT("beschriftung!"&ADDRESS(beschriftung!$C$1*12+ROW(beschriftung!$A7)-1,COLUMN(beschriftung!AY$1)))="","",INDIRECT("beschriftung!"&ADDRESS(beschriftung!$C$1*12+ROW(beschriftung!$A7)-1,COLUMN(beschriftung!AY$1)))) -> Exports of goods and services (excluding valuables) | BC6: =IF(INDIRECT("beschriftung!"&ADDRESS(beschriftung!$C$1*12+ROW(beschriftung!$A7)-1,COLUMN(beschriftung!BC$1)))="","",INDIRECT("beschriftung!"&ADDRESS(beschriftung!$C$1*12+ROW(beschriftung!$A7)-1,COLUMN(beschriftung!BC$1)))) -> Imports of goods and services (excluding valuables)
I7: =IF(INDIRECT("beschriftung!"&ADDRESS(beschriftung!$C$1*12+ROW(beschriftung!$A8)-1,COLUMN(beschriftung!I$1)))="","",INDIRECT("beschriftung!"&ADDRESS(beschriftung!$C$1*12+ROW(beschriftung!$A8)-1,COLUMN(beschriftung!I$1)))) -> Households and NPISH | K7: =IF(INDIRECT("beschriftung!"&ADDRESS(beschriftung!$C$1*12+ROW(beschriftung!$A8)-1,COLUMN(beschriftung!K$1)))="","",INDIRECT("beschriftung!"&ADDRESS(beschriftung!$C$1*12+ROW(beschriftung!$A8)-1,COLUMN(beschriftung!K$1)))) -> General government | O7: =IF(INDIRECT("beschriftung!"&ADDRESS(beschriftung!$C$1*12+ROW(beschriftung!$A8)-1,COLUMN(beschriftung!O$1)))="","",INDIRECT("beschriftung!"&ADDRESS(beschriftung!$C$1*12+ROW(beschriftung!$A8)-1,COLUMN(beschriftung!O$1)))) -> Gross fixed capital formation | U7: =IF(INDIRECT("beschriftung!"&ADDRESS(beschriftung!$C$1*12+ROW(beschriftung!$A8)-1,COLUMN(beschriftung!U$1)))="","",INDIRECT("beschriftung!"&ADDRESS(beschriftung!$C$1*12+ROW(beschriftung!$A8)-1,COLUMN(beschriftung!U$1)))) -> Changes in inventories and statistical discrepancies | W7: =IF(INDIRECT("beschriftung!"&ADDRESS(beschriftung!$C$1*12+ROW(beschriftung!$A8)-1,COLUMN(beschriftung!W$1)))="","",INDIRECT("beschriftung!"&ADDRESS(beschriftung!$C$1*12+ROW(beschriftung!$A8)-1,COLUMN(beschriftung!W$1)))) -> Acquisitions less disposals of valuables (including non-monetary gold) | AC7: =IF(INDIRECT("beschriftung!"&ADDRESS(beschriftung!$C$1*12+ROW(beschriftung!$A8)-1,COLUMN(beschriftung!AC$1)))="","",INDIRECT("beschriftung!"&ADDRESS(beschriftung!$C$1*12+ROW(beschriftung!$A8)-1,COLUMN(beschriftung!AC$1)))) -> Exports (exp.) of goods | AI7: =IF(INDIRECT("beschriftung!"&ADDRESS(beschriftung!$C$1*12+ROW(beschriftung!$A8)-1,COLUMN(beschriftung!AI$1)))="","",INDIRECT("beschriftung!"&ADDRESS(beschriftung!$C$1*12+ROW(beschriftung!$A8)-1,COLUMN(beschriftung!AI$1)))) -> Exports of services | AM7: =IF(INDIRECT("beschriftung!"&ADDRESS(beschriftung!$C$1*12+ROW(beschriftung!$A8)-1,COLUMN(beschriftung!AM$1)))="","",INDIRECT("beschriftung!"&ADDRESS(beschriftung!$C$1*12+ROW(beschriftung!$A8)-1,COLUMN(beschriftung!AM$1)))) -> Imports (imp.) of goods | AS7: =IF(INDIRECT("beschriftung!"&ADDRESS(beschriftung!$C$1*12+ROW(beschriftung!$A8)-1,COLUMN(beschriftung!AS$1)))="","",INDIRECT("beschriftung!"&ADDRESS(beschriftung!$C$1*12+ROW(beschriftung!$A8)-1,COLUMN(beschriftung!AS$1)))) -> Imports of services | BA7: =IF(INDIRECT("beschriftung!"&ADDRESS(beschriftung!$C$1*12+ROW(beschriftung!$A8)-1,COLUMN(beschriftung!BA$1)))="","",INDIRECT("beschriftung!"&ADDRESS(beschriftung!$C$1*12+ROW(beschriftung!$A8)-1,COLUMN(beschriftung!BA$1)))) -> thereof exports of goods excluding valuables
Q8: =IF(INDIRECT("beschriftung!"&ADDRESS(beschriftung!$C$1*12+ROW(beschriftung!$A9)-1,COLUMN(beschriftung!Q$1)))="","",INDIRECT("beschriftung!"&ADDRESS(beschriftung!$C$1*12+ROW(beschriftung!$A9)-1,COLUMN(beschriftung!Q$1)))) -> Construction | S8: =IF(INDIRECT("beschriftung!"&ADDRESS(beschriftung!$C$1*12+ROW(beschriftung!$A9)-1,COLUMN(beschriftung!S$1)))="","",INDIRECT("beschriftung!"&ADDRESS(beschriftung!$C$1*12+ROW(beschriftung!$A9)-1,COLUMN(beschriftung!S$1)))) -> Fixed assets and software | AE8: =IF(INDIRECT("beschriftung!"&ADDRESS(beschriftung!$C$1*12+ROW(beschriftung!$A9)-1,COLUMN(beschriftung!AE$1)))="","",INDIRECT("beschriftung!"&ADDRESS(beschriftung!$C$1*12+ROW(beschriftung!$A9)-1,COLUMN(beschriftung!AE$1)))) -> thereof exp. of goods excluding non-monetary gold | AG8: =IF(INDIRECT("beschriftung!"&ADDRESS(beschriftung!$C$1*12+ROW(beschriftung!$A9)-1,COLUMN(beschriftung!AG$1)))="","",INDIRECT("beschriftung!"&ADDRESS(beschriftung!$C$1*12+ROW(beschriftung!$A9)-1,COLUMN(beschriftung!AG$1)))) -> thereof exp. of goods excluding valuables and merchanting | AO8: =IF(INDIRECT("beschriftung!"&ADDRESS(beschriftung!$C$1*12+ROW(beschriftung!$A9)-1,COLUMN(beschriftung!AO$1)))="","",INDIRECT("beschriftung!"&ADDRESS(beschriftung!$C$1*12+ROW(beschriftung!$A9)-1,COLUMN(beschriftung!AO$1)))) -> thereof imp. of goods excluding non-monetary gold | AQ8: =IF(INDIRECT("beschriftung!"&ADDRESS(beschriftung!$C$1*12+ROW(beschriftung!$A9)-1,COLUMN(beschriftung!AQ$1)))="","",INDIRECT("beschriftung!"&ADDRESS(beschriftung!$C$1*12+ROW(beschriftung!$A9)-1,COLUMN(beschriftung!AQ$1)))) -> thereof imp. of goods excluding valuables
C11: B1GQ | E11: P3_P5 | G11: P3 | I11: P31_S14_S15 | K11: P3_S13 | M11: P5 | O11: P51G | Q11: P5111_N111_112G | S11: P5111_N113T117G | U11: P52_YA0 | W11: P53 | Y11: B11 | AA11: P6 | AC11: P61 | AE11: P61XF11 | AI11: P62 | AK11: P7 | AM11: P71 | AO11: P71XF11 | AS11: P72 | AU11: P3_P51G_P6 | AW11: P3_P51G
A12: 1980 | C12: 56.690595 | E12: 58.717374 | G12: 56.911768 | I12: 59.437689 | K12: 46.048709 | M12: 62.372732 | O12: 75.853812 | Q12: 62.741654 | S12: 83.155578 | AA12: 87.135494 | AC12: 98.997822 | AE12: 92.828749 | AG12: 88.408002 | AI12: 61.502044 | AK12: 99.503609 | AM12: 105.50479 | AO12: 114.37159 | AQ12: 111.29604 | AS12: 74.675057 | AU12: 66.345938 | AW12: 61.931712 | AY12: 76.332968 | BA12: 85.695658 | BC12: 98.115258
A13: 1981 | C13: 59.899911 | D13: 0.056611074 | E13: 62.433528 | F13: 0.063288834 | G13: 60.36625 | H13: 0.060698911 | I13: 62.980273 | J13: 0.05960164 | K13: 49.146065 | L13: 0.067262585 | M13: 66.652737 | N13: 0.068619817 | O13: 81.146264 | P13: 0.06977173 | Q13: 67.370786 | R13: 0.073780838 | S13: 88.713809 | T13: 0.066841352 | AA13: 84.58519 | AB13: -0.029268264 | AC13: 94.070398 | AD13: -0.049773054 | AE13: 92.89106 | AF13: 0.00067124531 | AG13: 92.142697 | AH13: 0.042243853 | AI13: 64.076391 | AJ13: 0.041857921 | AK13: 97.773909 | AL13: -0.017383285 | AM13: 102.21995 | AN13: -0.03113452 | AO13: 117.72304 | AP13: 0.029303233 | AQ13: 118.30327 | AR13: 0.062960244 | AS13: 78.421649 | AT13: 0.050171932 | AU13: 70.196218 | AV13: 0.05803339 | AW13: 65.866519 | AX13: 0.063534599 | AY13: 79.561243 | AZ13: 0.04229201 | BA13: 89.338991 | BB13: 0.042514791 | BC13: 103.98113 | BD13: 0.059785527
A14: 1982 | C14: 64.301381 | D14: 0.07348041 | E14: 65.686176 | F14: 0.052097774 | G14: 64.054172 | H14: 0.061092433 | I14: 66.633619 | J14: 0.058007783 | K14: 53.045421 | L14: 0.079342198 | M14: 68.913826 | N14: 0.033923424 | O14: 85.107008 | P14: 0.048809945 | Q14: 70.609437 | R14: 0.048072036 | S14: 93.092825 | T14: 0.049361152 | AA14: 84.029764 | AB14: -0.0065664696 | AC14: 90.085966 | AD14: -0.042355847 | AE14: 92.837536 | AF14: -0.00057619881 | AG14: 96.912207 | AH14: 0.051762218 | AI14: 70.579835 | AJ14: 0.10149517 | AK14: 93.087666 | AL14: -0.047929385 | AM14: 96.269091 | AN14: -0.05821619 | AO14: 113.82335 | AP14: -0.033126014 | AQ14: 117.74663 | AR14: -0.0047052153 | AS14: 78.154254 | AT14: -0.0034097066 | AU14: 74.438361 | AV14: 0.060432645 | AW14: 69.643974 | AX14: 0.057350164 | AY14: 85.091552 | AZ14: 0.069510088 | BA14: 94.003376 | BB14: 0.052209957 | BC14: 103.5274 | BD14: -0.0043636174
A15: 1983 | C15: 65.82332 | D15: 0.023668841 | E15: 67.175285 | F15: 0.022670057 | G15: 66.138294 | H15: 0.032536877 | I15: 68.801005 | J15: 0.03252692 | K15: 54.774377 | L15: 0.032593864 | M15: 69.101437 | N15: 0.0027224038 | O15: 86.692273 | P15: 0.018626726 | Q15: 70.795294 | R15: 0.0026321814 | S15: 95.971935 | T15: 0.03092731 | AA15: 86.446303 | AB15: 0.028758138 | AC15: 93.552165 | AD15: 0.038476566 | AE15: 93.630047 | AF15: 0.0085365376 | AG15: 97.825596 | AH15: 0.0094249128 | AI15: 70.992235 | AJ15: 0.0058430319 | AK15: 95.530908 | AL15: 0.026246679 | AM15: 99.383522 | AN15: 0.032351299 | AO15: 112.98329 | AP15: -0.0073803826 | AQ15: 116.43408 | AR15: -0.011147234 | AS15: 78.302037 | AT15: 0.001890913 | AU15: 76.159198 | AV15: 0.023117612 | AW15: 71.613126 | AX15: 0.028274543 | AY15: 85.787599 | AZ15: 0.0081799779 | BA15: 94.901238 | BB15: 0.0095513873 | BC15: 102.72469 | BD15: -0.0077535974
A16: 1984 | C16: 68.298038 | D16: 0.037596379 | E16: 69.8784 | F16: 0.040239716 | G16: 68.192074 | H16: 0.031052808 | I16: 70.932709 | J16: 0.030983618 | K16: 56.496974 | L16: 0.031448969 | M16: 73.319745 | N16: 0.061045152 | O16: 88.149293 | P16: 0.016806799 | Q16: 70.929073 | R16: 0.0018896673 | S16: 98.677575 | T16: 0.028191991 | AA16: 87.635445 | AB16: 0.01375584 | AC16: 94.636986 | AD16: 0.011595898 | AE16: 97.444728 | AF16: 0.040742066 | AG16: 102.06647 | AH16: 0.043351333 | AI16: 72.382291 | AJ16: 0.019580384 | AK16: 97.264932 | AL16: 0.018151442 | AM16: 100.5661 | AN16: 0.011899114 | AO16: 116.22212 | AP16: 0.028666497 | AQ16: 121.25746 | AR16: 0.041425851 | AS16: 81.771669 | AT16: 0.044310873 | AU16: 78.341567 | AV16: 0.028655348 | AW16: 73.521665 | AX16: 0.026650687 | AY16: 88.732992 | AZ16: 0.034333551 | BA16: 98.986838 | BB16: 0.043051065 | BC16: 107.05636 | BD16: 0.042167797
A17: 1985 | C17: 69.848903 | D17: 0.022707306 | E17: 72.340062 | F17: 0.035227797 | G17: 69.935684 | H17: 0.025569095 | I17: 72.822822 | J17: 0.026646553 | K17: 57.603055 | L17: 0.019577702 | M17: 77.454713 | N17: 0.056396379 | O17: 91.374289 | P17: 0.036585612 | Q17: 72.403668 | R17: 0.020789712 | S17: 103.39869 | T17: 0.047843827 | AA17: 86.890361 | AB17: -0.0085020879 | AC17: 92.946046 | AD17: -0.017867652 | AE17: 99.271855 | AF17: 0.018750388 | AG17: 104.81273 | AH17: 0.026906601 | AI17: 73.563183 | AJ17: 0.016314661 | AK17: 98.838589 | AL17: 0.016179079 | AM17: 101.46878 | AN17: 0.0089760091 | AO17: 121.29237 | AP17: 0.04362551 | AQ17: 127.28294 | AR17: 0.049691668 | AS17: 85.47121 | AT17: 0.045242332 | AU17: 80.488006 | AV17: 0.027398476 | AW17: 75.651129 | AX17: 0.028963765 | AY17: 90.793869 | AZ17: 0.023225596 | BA17: 101.68235 | BB17: 0.027231021 | BC17: 112.25183 | BD17: 0.048530232
A18: 1986 | C18: 71.968533 | D18: 0.030345939 | E18: 72.60012 | F18: 0.0035949347 | G18: 71.017982 | H18: 0.015475627 | I18: 73.746086 | J18: 0.012678233 | K18: 59.393177 | L18: 0.03107686 | M18: 75.962872 | N18: -0.019260819 | O18: 91.944258 | P18: 0.0062377407 | Q18: 74.538333 | R18: 0.029482827 | S18: 102.51343 | T18: -0.00856164 | AA18: 82.614925 | AB18: -0.049204952 | AC18: 86.506368 | AD18: -0.06928404 | AE18: 96.776709 | AF18: -0.025134475 | AG18: 103.86706 | AH18: -0.0090224609 | AI18: 73.902496 | AJ18: 0.0046125318 | AK18: 88.823666 | AL18: -0.10132604 | AM18: 89.865351 | AN18: -0.11435467 | AO18: 108.84762 | AP18: -0.10260128 | AQ18: 114.96921 | AR18: -0.096742958 | AS18: 81.663739 | AT18: -0.044546828 | AU18: 81.151211 | AV18: 0.0082397985 | AW18: 76.599054 | AX18: 0.012530218 | AY18: 90.459539 | AZ18: -0.0036822882 | BA18: 100.84083 | BB18: -0.0082759832 | BC18: 102.84763 | BD18: -0.083777695
A19: 1987 | C19: 73.547151 | D19: 0.021934824 | E19: 73.505203 | F19: 0.012466694 | G19: 71.578947 | H19: 0.0078989191 | I19: 74.305359 | J19: 0.0075837598 | K19: 59.965537 | L19: 0.0096367982 | M19: 77.61816 | N19: 0.021790759 | O19: 92.629196 | P19: 0.0074494952 | Q19: 76.209249 | R19: 0.022416867 | S19: 102.27116 | T19: -0.0023632924 | AA19: 82.336265 | AB19: -0.0033729951 | AC19: 85.806279 | AD19: -0.0080929229 | AE19: 96.516249 | AF19: -0.0026913485 | AG19: 103.89431 | AH19: 0.00026233441 | AI19: 74.459587 | AJ19: 0.0075381915 | AK19: 86.501416 | AL19: -0.026144501 | AM19: 87.195848 | AN19: -0.029705589 | AO19: 104.61231 | AP19: -0.038910425 | AQ19: 110.39143 | AR19: -0.039817486 | AS19: 80.608206 | AT19: -0.012925351 | AU19: 81.687023 | AV19: 0.0066026396 | AW19: 77.193109 | AX19: 0.0077553756 | AY19: 90.756552 | AZ19: 0.0032833781 | BA19: 100.92607 | BB19: 0.00084533092 | BC19: 99.467789 | BD19: -0.032862609
A20: 1988 | C20: 75.599291 | D20: 0.027902384 | E20: 76.192554 | F20: 0.036560005 | G20: 73.02239 | H20: 0.020165742 | I20: 75.609758 | J20: 0.017554578 | K20: 62.016416 | L20: 0.034200955 | M20: 83.022272 | N20: 0.069624315 | O20: 95.892161 | P20: 0.0352261 | Q20: 79.298031 | R20: 0.040530281 | S20: 105.51455 | T20: 0.03171368 | AA20: 83.541736 | AB20: 0.014640832 | AC20: 86.318879 | AD20: 0.0059739283 | AE20: 98.760391 | AF20: 0.023251443 | AG20: 105.40407 | AH20: 0.014531716 | AI20: 77.162045 | AJ20: 0.036294289 | AK20: 89.544232 | AL20: 0.035176489 | AM20: 90.283887 | AN20: 0.035414982 | AO20: 109.43416 | AP20: 0.046092514 | AQ20: 115.09988 | AR20: 0.042652328 | AS20: 83.374869 | AT20: 0.034322348 | AU20: 83.686177 | AV20: 0.024473332 | AW20: 79.135017 | AX20: 0.0251565 | AY20: 92.798877 | AZ20: 0.022503329 | BA20: 102.44022 | BB20: 0.015002581 | BC20: 103.48829 | BD20: 0.040420085
A21: 1989 | C21: 78.213863 | D21: 0.034584604 | E21: 78.464897 | F21: 0.02982369 | G21: 75.339183 | H21: 0.031727162 | I21: 77.985278 | J21: 0.031418168 | K21: 64.079552 | L21: 0.033267573 | M21: 85.205521 | N21: 0.026297156 | O21: 100.48495 | P21: 0.047895304 | Q21: 82.931753 | R21: 0.045823615 | S21: 110.72039 | T21: 0.049337613 | AA21: 90.175428 | AB21: 0.079405726 | AC21: 94.762846 | AD21: 0.097822939 | AE21: 106.44689 | AF21: 0.077829783 | AG21: 112.56885 | AH21: 0.067974403 | AI21: 79.796559 | AJ21: 0.034142625 | AK21: 95.662131 | AL21: 0.068322648 | AM21: 95.997067 | AN21: 0.063280166 | AO21: 118.77076 | AP21: 0.085317084 | AQ21: 124.00566 | AR21: 0.077374367 | AS21: 90.691884 | AT21: 0.087760439 | AU21: 87.194816 | AV21: 0.041926153 | AW21: 82.077015 | AX21: 0.037176944 | AY21: 97.95258 | AZ21: 0.055536263 | BA21: 109.34603 | BB21: 0.067413022 | BC21: 111.77244 | BD21: 0.080049223
A22: 1990 | C22: 81.814533 | D22: 0.046036213 | E22: 81.526059 | F22: 0.039013141 | G22: 79.295549 | H22: 0.052514045 | I22: 82.109458 | J22: 0.052884076 | K22: 67.330093 | L22: 0.050726651 | M22: 86.567275 | N22: 0.015981986 | O22: 102.38517 | P22: 0.018910488 | Q22: 87.42022 | R22: 0.05412241 | S22: 110.25448 | T22: -0.0042079343 | AA22: 88.499054 | AB22: -0.01859015 | AC22: 91.400598 | AD22: -0.035480656 | AE22: 105.80094 | AF22: -0.0060682586 | AG22: 113.82136 | AH22: 0.011126631 | AI22: 82.148972 | AJ22: 0.029480125 | AK22: 92.474387 | AL22: -0.033322946 | AM22: 91.794501 | AN22: -0.043778068 | AO22: 116.54973 | AP22: -0.018700119 | AQ22: 123.34258 | AR22: -0.0053472124 | AS22: 91.433073 | AT22: 0.0081725996 | AU22: 90.23551 | AV22: 0.034872409 | AW22: 85.432391 | AX22: 0.040880822 | AY22: 99.684353 | AZ22: 0.017679707 | BA22: 110.64271 | BB22: 0.01185847 | BC22: 111.5625 | BD22: -0.0018783224
A23: 1991 | C23: 86.239967 | D23: 0.054091048 | E23: 85.489948 | F23: 0.048621128 | G23: 83.646015 | H23: 0.054863946 | I23: 86.44039 | J23: 0.052745838 | K23: 71.705792 | L23: 0.064988758 | M23: 89.717722 | N23: 0.036393054 | O23: 104.42762 | P23: 0.0199487 | Q23: 88.707486 | R23: 0.014725041 | S23: 112.84386 | T23: 0.023485483 | AA23: 90.385396 | AB23: 0.021314828 | AC23: 92.655312 | AD23: 0.013727632 | AE23: 108.14108 | AF23: 0.022118296 | AG23: 116.71751 | AH23: 0.025444725 | AI23: 85.472013 | AJ23: 0.0404514 | AK23: 93.148663 | AL23: 0.0072914948 | AM23: 91.281017 | AN23: -0.0055938356 | AO23: 116.30384 | AP23: -0.0021097501 | AQ23: 123.39874 | AR23: 0.00045538274 | AS23: 96.387155 | AT23: 0.054182609 | AU23: 93.866759 | AV23: 0.04024191 | AW23: 89.134486 | AX23: 0.043333623 | AY23: 102.78937 | AZ23: 0.031148463 | BA23: 113.55513 | BB23: 0.026322759 | BC23: 113.17535 | BD23: 0.014456951
A24: 1992 | C24: 88.072251 | D24: 0.02124635 | E24: 87.230615 | F24: 0.02036108 | G24: 87.01605 | H24: 0.040289249 | I24: 89.73889 | J24: 0.038159247 | K24: 75.316499 | L24: 0.050354467 | M24: 87.803925 | N24: -0.021331318 | O24: 104.06051 | P24: -0.0035154169 | Q24: 86.366485 | R24: -0.026390115 | S24: 114.42125 | T24: 0.013978524 | AA24: 90.805157 | AB24: 0.004644129 | AC24: 93.118999 | AD24: 0.0050044311 | AE24: 109.24353 | AF24: 0.010194512 | AG24: 118.12267 | AH24: 0.01203896 | AI24: 85.791688 | AJ24: 0.0037401088 | AK24: 93.291527 | AL24: 0.0015337179 | AM24: 91.627036 | AN24: 0.0037907027 | AO24: 118.77187 | AP24: 0.021220559 | AQ24: 126.38976 | AR24: 0.024238623 | AS24: 95.846507 | AT24: -0.0056091279 | AU24: 95.972216 | AV24: 0.02243027 | AW24: 91.540058 | AX24: 0.026988119 | AY24: 103.77499 | AZ24: 0.0095887635 | BA24: 114.98928 | BB24: 0.012629546 | BC24: 114.92246 | BD24: 0.015437161
... A57: 2025 | C57: 107.35788 | D57: 0.002873305 | E57: 105.86633 | F57: 0.010259315 | G57: 107.00297 | H57: 0.0072297711 | I57: 105.80037 | J57: 0.0048500399 | K57: 112.10782 | L57: 0.01713647 | M57: 103.33075 | N57: 0.01664403 | O57: 107.62377 | P57: 0.0038691052 | Q57: 115.89165 | R57: 0.0083007302 | S57: 104.23997 | T57: 0.0020293344 | AA57: 118.90209 | AB57: 0.062583684 | AC57: 121.20428 | AD57: 0.086859163 | AE57: 107.93328 | AF57: 0.00090835872 | AG57: 100.09667 | AH57: 0.0053499263 | AI57: 112.00886 | AJ57: -0.0074917301 | AK57: 118.42 | AL57: 0.081963041 | AM57: 121.02159 | AN57: 0.11249089 | AO57: 102.78009 | AP57: -0.010489031 | AQ57: 101.71624 | AR57: -0.019974157 | AS57: 112.3145 | AT57: 0.014641638 | AU57: 107.98978 | AV57: 0.0030131292 | AW57: 107.19844 | AX57: 0.0062297055 | AY57: 109.10995 | AZ57: -0.0018051906 | BA57: 107.55644 | BB57: 0.00093677984 | BC57: 106.08296 | BD57: -0.0057028266

Sheet gc_y
A1: =IF(INDIRECT("beschriftung!"&ADDRESS(beschriftung!$C$1*12+ROW(beschriftung!$A1)-1,COLUMN(beschriftung!B$1)))="","",INDIRECT("beschriftung!"&ADDRESS(beschriftung!$C$1*12+ROW(beschriftung!$A1)-1,COLUMN(beschriftung!B$1)))) -> ESA 2010, Annual aggregates of Gross Domestic Product, expenditure approach (SFSO, SECO), raw data
A2: =IF(INDIRECT("beschriftung!"&ADDRESS(beschriftung!$C$1*12+ROW(beschriftung!$A6)-1,COLUMN(beschriftung!B$1)))="","",INDIRECT("beschriftung!"&ADDRESS(beschriftung!$C$1*12+ROW(beschriftung!$A6)-1,COLUMN(beschriftung!B$1)))) -> Contributions to real GDP-growth
A3: =IF(INDIRECT("beschriftung!"&ADDRESS(beschriftung!$C$1*12+ROW(beschriftung!$A5)-1,COLUMN(beschriftung!B$1)))="","",INDIRECT("beschriftung!"&ADDRESS(beschriftung!$C$1*12+ROW(beschriftung!$A5)-1,COLUMN(beschriftung!B$1))))
C4: =IF(INDIRECT("beschriftung!"&ADDRESS(beschriftung!$C$1*12+ROW(beschriftung!$A5)-1,COLUMN(beschriftung!C$1)))="","",INDIRECT("beschriftung!"&ADDRESS(beschriftung!$C$1*12+ROW(beschriftung!$A5)-1,COLUMN(beschriftung!C$1)))) -> Gross domestic product
E5: =IF(INDIRECT("beschriftung!"&ADDRESS(beschriftung!$C$1*12+ROW(beschriftung!$A6)-1,COLUMN(beschriftung!E$1)))="","",INDIRECT("beschriftung!"&ADDRESS(beschriftung!$C$1*12+ROW(beschriftung!$A6)-1,COLUMN(beschriftung!E$1)))) -> Internal demand | Y5: =IF(INDIRECT("beschriftung!"&ADDRESS(beschriftung!$C$1*12+ROW(beschriftung!$A6)-1,COLUMN(beschriftung!Y$1)))="","",INDIRECT("beschriftung!"&ADDRESS(beschriftung!$C$1*12+ROW(beschriftung!$A6)-1,COLUMN(beschriftung!Y$1)))) -> Trade balance (goods and services) | AU5: =IF(INDIRECT("beschriftung!"&ADDRESS(beschriftung!$C$1*12+ROW(beschriftung!$A6)-1,COLUMN(beschriftung!AU$1)))="","",INDIRECT("beschriftung!"&ADDRESS(beschriftung!$C$1*12+ROW(beschriftung!$A6)-1,COLUMN(beschriftung!AU$1)))) -> Global demand excluding inventories change, stat. discrepancies and valuables
G6: =IF(INDIRECT("beschriftung!"&ADDRESS(beschriftung!$C$1*12+ROW(beschriftung!$A7)-1,COLUMN(beschriftung!G$1)))="","",INDIRECT("beschriftung!"&ADDRESS(beschriftung!$C$1*12+ROW(beschriftung!$A7)-1,COLUMN(beschriftung!G$1)))) -> Final consumption expenditure | M6: =IF(INDIRECT("beschriftung!"&ADDRESS(beschriftung!$C$1*12+ROW(beschriftung!$A7)-1,COLUMN(beschriftung!M$1)))="","",INDIRECT("beschriftung!"&ADDRESS(beschriftung!$C$1*12+ROW(beschriftung!$A7)-1,COLUMN(beschriftung!M$1)))) -> Gross capital formation | AA6: =IF(INDIRECT("beschriftung!"&ADDRESS(beschriftung!$C$1*12+ROW(beschriftung!$A7)-1,COLUMN(beschriftung!AA$1)))="","",INDIRECT("beschriftung!"&ADDRESS(beschriftung!$C$1*12+ROW(beschriftung!$A7)-1,COLUMN(beschriftung!AA$1)))) -> Exports of goods and services | AK6: =IF(INDIRECT("beschriftung!"&ADDRESS(beschriftung!$C$1*12+ROW(beschriftung!$A7)-1,COLUMN(beschriftung!AK$1)))="","",INDIRECT("beschriftung!"&ADDRESS(beschriftung!$C$1*12+ROW(beschriftung!$A7)-1,COLUMN(beschriftung!AK$1)))) -> Imports of goods and services | AW6: =IF(INDIRECT("beschriftung!"&ADDRESS(beschriftung!$C$1*12+ROW(beschriftung!$A7)-1,COLUMN(beschriftung!AW$1)))="","",INDIRECT("beschriftung!"&ADDRESS(beschriftung!$C$1*12+ROW(beschriftung!$A7)-1,COLUMN(beschriftung!AW$1)))) -> Final domestic demand | AY6: =IF(INDIRECT("beschriftung!"&ADDRESS(beschriftung!$C$1*12+ROW(beschriftung!$A7)-1,COLUMN(beschriftung!AY$1)))="","",INDIRECT("beschriftung!"&ADDRESS(beschriftung!$C$1*12+ROW(beschriftung!$A7)-1,COLUMN(beschriftung!AY$1)))) -> Exports of goods and services (excluding valuables) | BC6: =IF(INDIRECT("beschriftung!"&ADDRESS(beschriftung!$C$1*12+ROW(beschriftung!$A7)-1,COLUMN(beschriftung!BC$1)))="","",INDIRECT("beschriftung!"&ADDRESS(beschriftung!$C$1*12+ROW(beschriftung!$A7)-1,COLUMN(beschriftung!BC$1)))) -> Imports of goods and services (excluding valuables)
I7: =IF(INDIRECT("beschriftung!"&ADDRESS(beschriftung!$C$1*12+ROW(beschriftung!$A8)-1,COLUMN(beschriftung!I$1)))="","",INDIRECT("beschriftung!"&ADDRESS(beschriftung!$C$1*12+ROW(beschriftung!$A8)-1,COLUMN(beschriftung!I$1)))) -> Households and NPISH | K7: =IF(INDIRECT("beschriftung!"&ADDRESS(beschriftung!$C$1*12+ROW(beschriftung!$A8)-1,COLUMN(beschriftung!K$1)))="","",INDIRECT("beschriftung!"&ADDRESS(beschriftung!$C$1*12+ROW(beschriftung!$A8)-1,COLUMN(beschriftung!K$1)))) -> General government | O7: =IF(INDIRECT("beschriftung!"&ADDRESS(beschriftung!$C$1*12+ROW(beschriftung!$A8)-1,COLUMN(beschriftung!O$1)))="","",INDIRECT("beschriftung!"&ADDRESS(beschriftung!$C$1*12+ROW(beschriftung!$A8)-1,COLUMN(beschriftung!O$1)))) -> Gross fixed capital formation | U7: =IF(INDIRECT("beschriftung!"&ADDRESS(beschriftung!$C$1*12+ROW(beschriftung!$A8)-1,COLUMN(beschriftung!U$1)))="","",INDIRECT("beschriftung!"&ADDRESS(beschriftung!$C$1*12+ROW(beschriftung!$A8)-1,COLUMN(beschriftung!U$1)))) -> Changes in inventories and statistical discrepancies | W7: =IF(INDIRECT("beschriftung!"&ADDRESS(beschriftung!$C$1*12+ROW(beschriftung!$A8)-1,COLUMN(beschriftung!W$1)))="","",INDIRECT("beschriftung!"&ADDRESS(beschriftung!$C$1*12+ROW(beschriftung!$A8)-1,COLUMN(beschriftung!W$1)))) -> Acquisitions less disposals of valuables (including non-monetary gold) | AC7: =IF(INDIRECT("beschriftung!"&ADDRESS(beschriftung!$C$1*12+ROW(beschriftung!$A8)-1,COLUMN(beschriftung!AC$1)))="","",INDIRECT("beschriftung!"&ADDRESS(beschriftung!$C$1*12+ROW(beschriftung!$A8)-1,COLUMN(beschriftung!AC$1)))) -> Exports (exp.) of goods | AI7: =IF(INDIRECT("beschriftung!"&ADDRESS(beschriftung!$C$1*12+ROW(beschriftung!$A8)-1,COLUMN(beschriftung!AI$1)))="","",INDIRECT("beschriftung!"&ADDRESS(beschriftung!$C$1*12+ROW(beschriftung!$A8)-1,COLUMN(beschriftung!AI$1)))) -> Exports of services | AM7: =IF(INDIRECT("beschriftung!"&ADDRESS(beschriftung!$C$1*12+ROW(beschriftung!$A8)-1,COLUMN(beschriftung!AM$1)))="","",INDIRECT("beschriftung!"&ADDRESS(beschriftung!$C$1*12+ROW(beschriftung!$A8)-1,COLUMN(beschriftung!AM$1)))) -> Imports (imp.) of goods | AS7: =IF(INDIRECT("beschriftung!"&ADDRESS(beschriftung!$C$1*12+ROW(beschriftung!$A8)-1,COLUMN(beschriftung!AS$1)))="","",INDIRECT("beschriftung!"&ADDRESS(beschriftung!$C$1*12+ROW(beschriftung!$A8)-1,COLUMN(beschriftung!AS$1)))) -> Imports of services | BA7: =IF(INDIRECT("beschriftung!"&ADDRESS(beschriftung!$C$1*12+ROW(beschriftung!$A8)-1,COLUMN(beschriftung!BA$1)))="","",INDIRECT("beschriftung!"&ADDRESS(beschriftung!$C$1*12+ROW(beschriftung!$A8)-1,COLUMN(beschriftung!BA$1)))) -> thereof exports of goods excluding valuables
Q8: =IF(INDIRECT("beschriftung!"&ADDRESS(beschriftung!$C$1*12+ROW(beschriftung!$A9)-1,COLUMN(beschriftung!Q$1)))="","",INDIRECT("beschriftung!"&ADDRESS(beschriftung!$C$1*12+ROW(beschriftung!$A9)-1,COLUMN(beschriftung!Q$1)))) -> Construction | S8: =IF(INDIRECT("beschriftung!"&ADDRESS(beschriftung!$C$1*12+ROW(beschriftung!$A9)-1,COLUMN(beschriftung!S$1)))="","",INDIRECT("beschriftung!"&ADDRESS(beschriftung!$C$1*12+ROW(beschriftung!$A9)-1,COLUMN(beschriftung!S$1)))) -> Fixed assets and software | AE8: =IF(INDIRECT("beschriftung!"&ADDRESS(beschriftung!$C$1*12+ROW(beschriftung!$A9)-1,COLUMN(beschriftung!AE$1)))="","",INDIRECT("beschriftung!"&ADDRESS(beschriftung!$C$1*12+ROW(beschriftung!$A9)-1,COLUMN(beschriftung!AE$1)))) -> thereof exp. of goods excluding non-monetary gold | AG8: =IF(INDIRECT("beschriftung!"&ADDRESS(beschriftung!$C$1*12+ROW(beschriftung!$A9)-1,COLUMN(beschriftung!AG$1)))="","",INDIRECT("beschriftung!"&ADDRESS(beschriftung!$C$1*12+ROW(beschriftung!$A9)-1,COLUMN(beschriftung!AG$1)))) -> thereof exp. of goods excluding valuables and merchanting | AO8: =IF(INDIRECT("beschriftung!"&ADDRESS(beschriftung!$C$1*12+ROW(beschriftung!$A9)-1,COLUMN(beschriftung!AO$1)))="","",INDIRECT("beschriftung!"&ADDRESS(beschriftung!$C$1*12+ROW(beschriftung!$A9)-1,COLUMN(beschriftung!AO$1)))) -> thereof imp. of goods excluding non-monetary gold | AQ8: =IF(INDIRECT("beschriftung!"&ADDRESS(beschriftung!$C$1*12+ROW(beschriftung!$A9)-1,COLUMN(beschriftung!AQ$1)))="","",INDIRECT("beschriftung!"&ADDRESS(beschriftung!$C$1*12+ROW(beschriftung!$A9)-1,COLUMN(beschriftung!AQ$1)))) -> thereof imp. of goods excluding valuables
C11: B1GQ | E11: P3_P5 | G11: P3 | I11: P31_S14_S15 | K11: P3_S13 | M11: P5 | O11: P51G | Q11: P5111_N111_112G | S11: P5111_N113T117G | U11: P52_YA0 | W11: P53 | Y11: B11 | AA11: P6 | AC11: P61 | AE11: P61XF11 | AI11: P62 | AK11: P7 | AM11: P71 | AO11: P71XF11 | AS11: P72 | AU11: P3_P51G_P6 | AW11: P3_P51G
A12: 1980
A13: 1981 | E13: -0.017337177 | G13: 0.007715848 | I13: 0.0055495027 | K13: 0.0021663453 | M13: -0.025053025 | O13: 0.0040081957 | Q13: 0.0052132881 | S13: -0.0012050924 | U13: -0.010282123 | W13: -0.018779098 | Y13: 0.033350535 | AA13: 0.068937306 | AC13: 0.060575826 | AE13: 0.022225782 | AG13: 0.0088335352 | AI13: 0.0083614795 | AK13: -0.03558677 | AM13: -0.030845205 | AO13: 0.0012708278 | AQ13: 0.0015563688 | AS13: -0.004741565 | AU13: 0.029480678 | AW13: 0.011724044 | AY13: 0.017756634 | BA13: 0.0093951544 | BC13: -0.0031851962
A14: 1982 | E14: 0.0067428514 | G14: 0.0020612929 | I14: 0.0014478075 | K14: 0.0006134854 | M14: 0.0046815586 | O14: -0.012745121 | Q14: -0.0043031453 | S14: -0.0084419762 | U14: 0.00067756809 | W14: 0.016749112 | Y14: -0.019837026 | AA14: -0.0093699731 | AC14: -0.011118324 | AE14: -0.0011731215 | AG14: -0.0074796495 | AI14: 0.0017483509 | AK14: -0.010467053 | AM14: -0.0052248225 | AO14: 0.0025062926 | AQ14: 0.0086380824 | AS14: -0.0052422303 | AU14: -0.017167595 | AW14: -0.010683829 | AY14: -0.0064837661 | BA14: -0.0082321169 | BC14: 0.0033958521
A15: 1983 | E15: 0.023034546 | G15: 0.0098198852 | I15: 0.0072353761 | K15: 0.0025845091 | M15: 0.013214661 | O15: 0.010183471 | Q15: 0.0065993256 | S15: 0.0035841449 | U15: -0.0076329119 | W15: 0.010664102 | Y15: -0.016643752 | AA15: -0.012127807 | AC15: -0.018060011 | AE15: 0.0023904747 | AG15: 0.0028341752 | AI15: 0.0059322049 | AK15: -0.0045159451 | AM15: -0.0019000915 | AO15: -0.014950402 | AQ15: -0.011959728 | AS15: -0.0026158537 | AU15: 0.028599288 | AW15: 0.020003356 | AY15: 0.0085959324 | BA15: 0.0026637275 | BC15: -0.014575582
A16: 1984 | E16: -0.010661135 | G16: 0.011048786 | I16: 0.0094503885 | K16: 0.0015983972 | M16: -0.021709921 | O16: 0.012722433 | Q16: 0.0069889247 | S16: 0.0057335083 | U16: 0.0053409194 | W16: -0.039773273 | Y16: 0.040745699 | AA16: 0.066461262 | AC16: 0.057201118 | AE16: 0.01930128 | AG16: 0.01271216 | AI16: 0.0092601442 | AK16: -0.025715563 | AM16: -0.021957288 | AO16: -0.026120467 | AQ16: -0.017992151 | AS16: -0.0037582752 | AU16: 0.046494071 | AW16: 0.023771219 | AY16: 0.022722852 | BA16: 0.013462708 | BC16: -0.021750426
A17: 1985 | E17: 0.02649476 | G17: 0.017331722 | I17: 0.012215333 | K17: 0.0051163884 | M17: 0.0091630381 | O17: 0.010657076 | Q17: 0.0013615488 | S17: 0.0092955275 | U17: -0.0032417871 | W17: 0.0017477489 | Y17: 0.0102412 | AA17: 0.037001254 | AC17: 0.025974943 | AE17: 0.018776731 | AG17: 0.017427538 | AI17: 0.011026311 | AK17: -0.026760054 | AM17: -0.0211117 | AO17: -0.0096915877 | AQ17: -0.011666952 | AS17: -0.0056483546 | AU17: 0.057293053 | AW17: 0.027988798 | AY17: 0.029304255 | BA17: 0.018277944 | BC17: -0.017315307
A18: 1986 | E18: 0.062226235 | G18: 0.019089357 | I18: 0.015846442 | K18: 0.0032429151 | M18: 0.043136878 | O18: 0.020877452 | Q18: 0.0018810268 | S18: 0.018996425 | U18: 8.4537392e-05 | W18: 0.022174889 | Y18: -0.043639907 | AA18: 0.0072660326 | AC18: 0.0095631101 | AE18: 0.0065147932 | AG18: 0.0049576132 | AI18: -0.0022970775 | AK18: -0.05090594 | AM18: -0.049316224 | AO18: -0.025786021 | AQ18: -0.021548556 | AS18: -0.0015897164 | AU18: 0.041640063 | AW18: 0.039966809 | AY18: 0.0016732535 | BA18: 0.003970331 | BC18: -0.023138272
A19: 1987 | E19: 0.020490527 | G19: 0.019159446 | I19: 0.016796151 | K19: 0.0023632944 | M19: 0.0013310809 | O19: 0.012610072 | Q19: 0.0043795972 | S19: 0.0082304749 | U19: -0.0016702002 | W19: -0.009608791 | Y19: -0.0046357448 | AA19: -0.010298608 | AC19: -0.013585959 | AE19: 0.0027894011 | AG19: -0.00033247455 | AI19: 0.0032873503 | AK19: 0.0056628636 | AM19: 0.010352409 | AO19: -0.015666398 | AQ19: -0.013961634 | AS19: -0.0046895455 | AU19: 0.036176162 | AW19: 0.031769518 | AY19: 0.004406644 | BA19: 0.0011192937 | BC19: -0.01865118
A20: 1988 | E20: 0.024330346 | G20: 0.01662591 | I20: 0.01197163 | K20: 0.0046542798 | M20: 0.0077044363 | O20: 0.025840923 | Q20: 0.0092097273 | S20: 0.016631196 | U20: -0.0073261535 | W20: -0.010810333 | Y20: 0.0084456166 | AA20: 0.030863204 | AC20: 0.02987532 | AE20: 0.016787097 | AG20: 0.014864029 | AI20: 0.00098788408 | AK20: -0.022417588 | AM20: -0.016269454 | AO20: -0.011295861 | AQ20: -0.011955773 | AS20: -0.0061481337 | AU20: 0.058206023 | AW20: 0.042466833 | AY20: 0.01573919 | BA20: 0.014751306 | BC20: -0.018103907
A21: 1989 | E21: 0.048370681 | G21: 0.022980635 | I21: 0.013879459 | K21: 0.0091011768 | M21: 0.025390045 | O21: 0.015282061 | Q21: 0.0095622291 | S21: 0.0057198323 | U21: 0.0042819568 | W21: 0.0058260272 | Y21: -0.0050627401 | AA21: 0.024034846 | AC21: 0.018217222 | AE21: 0.01346083 | AG21: 0.0095215985 | AI21: 0.0058176245 | AK21: -0.029097586 | AM21: -0.028038803 | AO21: -0.016840132 | AQ21: -0.014531554 | AS21: -0.0010587838 | AU21: 0.054616322 | AW21: 0.038262697 | AY21: 0.016353625 | BA21: 0.010536001 | BC21: -0.015590338
A22: 1990 | E22: 0.053263598 | G22: 0.01350606 | I22: 0.0084839522 | K22: 0.0050221076 | M22: 0.039757538 | O22: 0.0155991 | Q22: 0.0017455293 | S22: 0.013853571 | U22: 0.012384232 | W22: 0.011774206 | Y22: -0.016517342 | AA22: 0.0087769489 | AC22: 0.013993044 | AE22: 0.013511851 | AG22: 0.0098085432 | AI22: -0.005216095 | AK22: -0.02529429 | AM22: -0.023866769 | AO22: -0.011124988 | AQ22: -0.0079526773 | AS22: -0.0014275215 | AU22: 0.033742223 | AW22: 0.02910516 | AY22: 0.0046370637 | BA22: 0.0098531587 | BC22: -0.0093801988
A23: 1991 | E23: -0.015688407 | G23: 0.013058221 | I23: 0.0096577899 | K23: 0.0034004306 | M23: -0.028746627 | O23: -0.0060596656 | Q23: -0.004517103 | S23: -0.0015425626 | U23: -0.020595795 | W23: -0.0020911661 | Y23: 0.0065302409 | AA23: -0.006450777 | AC23: -0.0091451718 | AE23: -0.0058655253 | AG23: -0.0015904782 | AI23: 0.0026943949 | AK23: 0.012981018 | AM23: 0.012493808 | AO23: 0.0037332254 | AQ23: 0.0032100981 | AS23: 0.00048720963 | AU23: 0.0077403219 | AW23: 0.0069985549 | AY23: 0.00074176706 | BA23: -0.0019526278 | BC23: 0.0036973077
A24: 1992 | E24: -0.011013345 | G24: 0.0030871109 | I24: 0.0025535122 | K24: 0.0005335987 | M24: -0.014100456 | O24: -0.025499494 | Q24: -0.0010804095 | S24: -0.024419085 | U24: 0.0083222486 | W24: 0.0030767897 | Y24: 0.010576015 | AA24: 0.015435124 | AC24: 0.012696231 | AE24: 0.0082631242 | AG24: 0.009081786 | AI24: 0.0027388923 | AK24: -0.0048591086 | AM24: 0.0018329628 | AO24: 0.011589257 | AQ24: 0.0098792496 | AS24: -0.0066920714 | AU24: -0.011946757 | AW24: -0.022412383 | AY24: 0.010465627 | BA24: 0.0077267343 | BC24: 0.0031871782
... A57: 2025 | E57: 0.036160639 | G57: 0.0087511721 | I57: 0.0076172294 | K57: 0.0011339427 | M57: 0.027409467 | O57: -0.0014170268 | Q57: -0.00036000013 | S57: -0.0010570266 | U57: 0.015133833 | W57: 0.013692661 | Y57: -0.02315986 | AA57: 0.034221152 | AC57: 0.036587949 | AE57: 0.018468052 | AG57: 0.0064811281 | AI57: -0.0023667966 | AK57: -0.057381012 | AM57: -0.06383731 | AO57: -0.025130682 | AQ57: -0.022161274 | AS57: 0.0064562979 | AU57: 0.013571923 | AW57: 0.0073341454 | AY57: 0.0062377773 | BA57: 0.0086045739 | BC57: -0.015704976

Sheet beschriftung
A1: deutsch | C1: 4
A2: français
A3: italiano
A4: english
A11: deutsch
A12: ESVG 2010, Quartalsaggregate des Bruttoinlandprodukts, Verwendungsansatz, unbereinigte Daten | B12: ESVG 2010, Jahresaggregate des Bruttoinlandproduktes, Verwendungsansatz (BFS, SECO), unbereinigte Daten
A13: In Mio. Franken, zu laufenden Preisen und Veränderungsraten in % gegenüber dem gleichen Quartal des Vorjahres | B13: In Mio. Franken, zu laufenden Preisen und Veränderungsraten in % gegenüber dem Vorjahr
A14: In Mio. Franken, reale nicht additive Volumen (annual overlap, Referenzjahr 2020) und Veränderungsraten in % gegenüber dem gleichen Quartal des Vorjahres | B14: In Mio. Franken, reale nicht additive Volumen (annual overlap, Referenzjahr 2020) und Veränderungsraten in % gegenüber dem Vorjahr
A15: Implizite Preisindizes und Veränderungsraten in % gegenüber dem gleichen Quartal des Vorjahres | B15: Implizite Preisindizes und Veränderungsraten in % gegenüber dem Vorjahr
C16: Bruttoinlandprodukt
A17: Reale Wachstumsbeiträge zum Bruttoinlandprodukt | B17: Reale Wachstumsbeiträge zum Bruttoinlandprodukt | E17: Inlandnachfrage | Y17: Handelsbilanz (Waren und Dienstleistungen) | AU17: Gesamtnachfrage ohne Vorratsveränderung, statistische Abw. u. Wertsachen
G18: Konsumausgaben | M18: Bruttoinvestitionen | AA18: Waren- und Dienstleistungsexporte | AK18: Waren- und Dienstleistungsimporte | AW18: Inländische Endnachfrage | AY18: Waren- und Dienstleistungsexporte (ohne Wertsachen) | BC18: Waren- und Dienstleistungsimporte (ohne Wertsachen)
I19: Private Haushalte und POoE | K19: Staat | O19: Bruttoanlageinvestitionen | U19: Vorratsveränderungen und statistische Abweichungen | W19: Nettozugang an Wertsachen (inkl. Nichtwährungsgold) | AA19: NA | AC19: Warenexporte | AI19: Dienstleistungsexporte | AM19: Warenimporte | AS19: Dienstleistungsimporte | BA19: davon Warenexporte ohne Wertsachen
Q20: Bau | S20: Ausrüstungen | AE20: davon Warenexporte ohne Nichtwährungsgold | AG20: davon Warenexp. ohne Wertsachen u. Transithandel | AK20: NA | AO20: davon Warenimporte ohne Nichtwährungsgold | AQ20: davon Warenimporte ohne Wertsachen
A21: Jahr | B21: Quartal
A23: français
A24: SEC 2010, PIB trimestriel et ses composantes, approche par la dépense, données brutes | B24: SEC 2010, PIB annuel et ses composantes, approche par la dépense (OFS, SECO), données brutes
A25: En mio. de francs, aux prix courants, variations en % par rapport au même trimestre de l'année précédente | B25: En mio. de francs, aux prix courants, variations en % par rapport de l'année précédente
A26: En mio. de francs, aux prix de l'année précédente - séries chaînées ("annual overlap"), année de référence 2020, volumes non-additifs, variations en % par rapport au même trimestre de l'année précédente | B26: En mio. de francs, aux prix de l'année précédente - séries chaînées ("annual overlap"), année de référence 2020, volumes non-additifs, variations en % par rapport de l'année précédente
A27: indices des prix, variations en % par rapport au même trimestre de l'année précédente | B27: Indices des prix, variations en % par rapport de l'année précédente
C28: Produit intérieur brut
A29: contributions à la croissance réelle du PIB | B29: contributions à la croissance réelle du PIB | E29: Demande intérieure | Y29: Balance commerciale (biens et services) | AU29: Demande globale sans variations des stocks, diff. statistique et objets de valeur
G30: Dépenses de consommation finale | M30: Formation brute de capital | AA30: Exportations de biens et de services | AK30: Importations de biens et de services | AW30: Demande intérieure finale | AY30: Exportations de biens et de services (sans objets de valeur) | BC30: Importations de biens et de services (sans objets de valeur)
I31: Ménages et ISBLSM | K31: Administrations publiques | O31: Formation brute de capital fixe | U31: Variation des stocks et divergence statistique | W31: Acquisitions moins cessions d'objets de valeur (y compris or non monétaire) | AA31: NA | AC31: Exportations (exp.) de biens | AI31: Exportations de services | AM31: Importations (imp.) de biens | AS31: Importations de services | BA31: dont exportations de biens sans objets de valeur
Q32: Construction | S32: Biens d'équipement | AE32: dont exp. de biens sans or non monétaire | AG32: dont exp. de biens sans objets de valeur et commerce de transit | AK32: NA | AO32: dont imp. de biens sans or non monétaire | AQ32: dont imp. de biens sans objets de valeur
A33: Année | B33: Trimestre
A35: italiano
A36: SEC 2010, Prodotto Interno Lordo e aggregati trimestrali, ottica della spesa, dati grezzi | B36: SEC 2010, Prodotto Interno Lordo e aggregati annuali, ottica della spesa (UST, SECO), dati grezzi
A37: In milioni di franchi, a prezzi correnti, variazione in % rispetto all'anno precedente | B37: In milioni di franchi, a prezzi correnti, variazione in % rispetto all'anno precedente
A38: In milioni di franchi, ai prezzi dell'anno precedente, indici a catena, anno di referenza 2020, variazione in % rispetto all'anno precedente | B38: In milioni di franchi, ai prezzi dell'anno precedente, indici a catena, anno di referenza 2020, variazione in % rispetto all'anno precedente
A39: Indici dei prezzi, variazione in % rispetto all'anno precedente | B39: Indici dei prezzi, variazione in % rispetto all'anno precedente
C40: Prodotto interno lordo
A41: Contributi alla crescita reale del PIL | B41: Contributi alla crescita reale del PIL | E41: Domanda interna | Y41: Bilancia commerciale (beni e servizi) | AU41: Domanda globale senza variaz. scorte, divergenze statistiche e ogg. di valore
G42: Spesa per consumi finali | M42: Investimenti lordi | AA42: Esportazioni di beni e servizi | AK42: Importazioni di beni e servizi | AW42: Domanda interna finale | AY42: Esportazioni di beni e servizi (senza oggetti di valore) | BC42: Importazioni di beni e servizi (senza oggetti di valore)
I43: Economie domestiche e ISLED | K43: Amministrazioni pubbliche | O43: Investimenti fissi lordi | U43: Variazione delle scorte e divergenze statistiche | W43: Acquisizioni meno cessioni di oggetti di valore (inclusivo oro non monetario) | AA43: NA | AC43: Esportazioni (esp.) di beni | AI43: Esportazioni di servizi | AM43: Importazioni (imp.) di beni | AS43: Importazioni di servizi | BA43: di cui esportazioni di beni senza oggetti di valore
Q44: Costruzione | S44: Beni di equipaggiamento | AE44: di cui esp. di beni senza oro non monetario | AG44: di cui esp. di beni senza oggetti di valore e commercio di transito | AK44: NA | AO44: di cui imp. di beni senza oro non monetario | AQ44: di cui imp. di beni senza oggetti di valore
A45: Anno | B45: Trimestre
A47: english
A48: ESA 2010, Quarterly aggregates of Gross Domestic Product, expenditure approach, raw data | B48: ESA 2010, Annual aggregates of Gross Domestic Product, expenditure approach (SFSO, SECO), raw data
A49: In Mio. Swiss Francs, at current prices, percentage change to previous year | B49: In Mio. Swiss Francs, at current prices, percentage change to previous year
A50: In Mio. Swiss Francs, at prices of preceding year, chained values, reference year 2020, percentage change to previous year | B50: In Mio. Swiss Francs, at prices of preceding year, chained values, reference year 2020, percentage change to previous year
A51: Implicit chain price indexes, year-on-year growth rates | B51: Implicit chain price indexes, year-on-year growth rates
C52: Gross domestic product
A53: Contributions to real GDP-growth | B53: Contributions to real GDP-growth | E53: Internal demand | Y53: Trade balance (goods and services) | AU53: Global demand excluding inventories change, stat. discrepancies and valuables
G54: Final consumption expenditure | M54: Gross capital formation | AA54: Exports of goods and services | AK54: Imports of goods and services | AW54: Final domestic demand | AY54: Exports of goods and services (excluding valuables) | BC54: Imports of goods and services (excluding valuables)
I55: Households and NPISH | K55: General government | O55: Gross fixed capital formation | U55: Changes in inventories and statistical discrepancies | W55: Acquisitions less disposals of valuables (including non-monetary gold) | AA55: NA | AC55: Exports (exp.) of goods | AI55: Exports of services | AM55: Imports (imp.) of goods | AS55: Imports of services | BA55: thereof exports of goods excluding valuables
Q56: Construction | S56: Fixed assets and software | AE56: thereof exp. of goods excluding non-monetary gold | AG56: thereof exp. of goods excluding valuables and merchanting | AK56: NA | AO56: thereof imp. of goods excluding non-monetary gold | AQ56: thereof imp. of goods excluding valuables
A57: Year | B57: Quarter
