Workbook

Sheet swiss_qna
A2: Staatssekretariat für Wirtschaft SECO
A3: Secrétariat d'Etat à l'économie SECO
A4: Segreteria di Stato dell’economia SECO
A5: Secretariat da stadi per l'economia SECO
A6: State Secretariat for Economic Affairs SECO
A8: You may choose the language to label the Swiss GDP and its income components in the dropdown-menu below.
A9: Pages labelled at the end with "_q" contain quarterly data, pages with "_y" contain yearly figures.
A10: Pages labelled at the beginning with "nom" contain figures at current prices.
A12: Sie können im Dropdown-Menu die Sprache wählen, im welcher Sie das BIP der Schweiz gemäss Einkommensseite beschriftet haben möchten.
A13: Seiten mit der Endbezeichnung "_q" enthalten Quartalszahlen, diejenigen mit "_y" Jahreszahlen.
A14: Seiten mit der Anfangsbezeichnung "nom" enthalten Werte zu laufenden Preisen.
A16: Vous pouvez choisir ci-dessous la langue avec laquelle vous souhaitez visualiser le PIB de la Suisse selon l'approche par les revenus.
... A22: Le pagine contrassegnate all'inizio con "nom" contengono dati ai prezzi correnti.

Sheet nom_q
A1: =INDIRECT("beschriftung!"&ADDRESS(beschriftung!$C$1*12+ROW(beschriftung!$A1)-1,COLUMN(beschriftung!A$1))) -> ESA 2010, Quarterly aggregates of Gross Domestic Product, income approach, raw data
A2: =INDIRECT("beschriftung!"&ADDRESS(beschriftung!$C$1*12+ROW(beschriftung!$A2)-1,COLUMN(beschriftung!A$1))) -> In Mio. Swiss Francs, at current prices, percentage change to previous year
C4: =INDIRECT("beschriftung!"&ADDRESS(beschriftung!$C$1*12+ROW(beschriftung!$A5)-1,COLUMN(beschriftung!C$1))) -> Gross domestic product | O4: =INDIRECT("beschriftung!"&ADDRESS(beschriftung!$C$1*12+ROW(beschriftung!$A5)-1,COLUMN(beschriftung!O$1))) -> Gross national income | AA4: =INDIRECT("beschriftung!"&ADDRESS(beschriftung!$C$1*12+ROW(beschriftung!$A5)-1,COLUMN(beschriftung!AA$1))) -> Disposable income, gross
E5: =INDIRECT("beschriftung!"&ADDRESS(beschriftung!$C$1*12+ROW(beschriftung!$A7)-1,COLUMN(beschriftung!E$1))) -> Compensation of employees | G5: =INDIRECT("beschriftung!"&ADDRESS(beschriftung!$C$1*12+ROW(beschriftung!$A7)-1,COLUMN(beschriftung!G$1))) -> Net operating surplus and net mixed income | I5: =INDIRECT("beschriftung!"&ADDRESS(beschriftung!$C$1*12+ROW(beschriftung!$A7)-1,COLUMN(beschriftung!I$1))) -> Consumption of fixed capital | K5: =INDIRECT("beschriftung!"&ADDRESS(beschriftung!$C$1*12+ROW(beschriftung!$A7)-1,COLUMN(beschriftung!K$1))) -> Taxes on production and imports | M5: =INDIRECT("beschriftung!"&ADDRESS(beschriftung!$C$1*12+ROW(beschriftung!$A7)-1,COLUMN(beschriftung!M$1))) -> Subsidies | Q5: =INDIRECT("beschriftung!"&ADDRESS(beschriftung!$C$1*12+ROW(beschriftung!$A7)-1,COLUMN(beschriftung!Q$1))) -> Compensation of employees received from the rest of the world | S5: =INDIRECT("beschriftung!"&ADDRESS(beschriftung!$C$1*12+ROW(beschriftung!$A7)-1,COLUMN(beschriftung!S$1))) -> Compensation of employees paid to the rest of the world | U5: =INDIRECT("beschriftung!"&ADDRESS(beschriftung!$C$1*12+ROW(beschriftung!$A7)-1,COLUMN(beschriftung!U$1))) -> Taxes on production and imports received from the rest of the world | W5: =INDIRECT("beschriftung!"&ADDRESS(beschriftung!$C$1*12+ROW(beschriftung!$A7)-1,COLUMN(beschriftung!W$1))) -> Property income received from the rest of the world | Y5: =INDIRECT("beschriftung!"&ADDRESS(beschriftung!$C$1*12+ROW(beschriftung!$A7)-1,COLUMN(beschriftung!Y$1))) -> Property income paid to the rest of the world | AB5: =IF(INDIRECT("beschriftung!"&ADDRESS(beschriftung!$C$1*12+ROW($A6)-1,COLUMN(AB$1)))="","",INDIRECT("beschriftung!"&ADDRESS(beschriftung!$C$1*12+ROW($A6)-1,COLUMN(AB$1)))) | AC5: =INDIRECT("beschriftung!"&ADDRESS(beschriftung!$C$1*12+ROW(beschriftung!$A7)-1,COLUMN(beschriftung!AC$1))) -> Current transfers receivable from the rest of the world | AE5: =INDIRECT("beschriftung!"&ADDRESS(beschriftung!$C$1*12+ROW(beschriftung!$A7)-1,COLUMN(beschriftung!AE$1))) -> Current transfers payable to the rest of the world
C11: B1GQ | E11: D1 | G11: B2_B3N | I11: P51C | K11: D2 | M11: D3 | O11: B5GQ | Q11: D1r | S11: D1p | U11: D2r | W11: D4r | Y11: D4p | AA11: B6G | AC11: D5r_D6r_D7r | AE11: D5p_D6p_D7p
A12: 1980 | B12: 1 | C12: 49949.522
A13: 1980 | B13: 2 | C13: 51718.735
A14: 1980 | B14: 3 | C14: 52002.73
A15: 1980 | B15: 4 | C15: 54793.818
A16: 1981 | B16: 1 | C16: 52977.659 | D16: 0.060623949
A17: 1981 | B17: 2 | C17: 55522.014 | D17: 0.073537736
A18: 1981 | B18: 3 | C18: 56051.232 | D18: 0.077851716
A19: 1981 | B19: 4 | C19: 59242.518 | D19: 0.081189828
A20: 1982 | B20: 1 | C20: 57055.029 | D20: 0.076963957
A21: 1982 | B21: 2 | C21: 59324.427 | D21: 0.068484787
A22: 1982 | B22: 3 | C22: 59074.572 | D22: 0.053938874
A23: 1982 | B23: 4 | C23: 61638.11 | D23: 0.040437042
A24: 1983 | B24: 1 | C24: 59277.027 | D24: 0.038944827
A25: 1983 | B25: 2 | C25: 60666.89 | D25: 0.022629169
A26: 1983 | B26: 3 | C26: 60588.291 | D26: 0.025623865
A27: 1983 | B27: 4 | C27: 63722.697 | D27: 0.033819774
... A51: 1989 | B51: 4 | C51: 90562.872 | D51: 0.073541637
A52: 1990 | B52: 1 | C52: 90810.988 | D52: 0.10290247 | E52: 54221.762 | G52: 14341.212 | I52: 20232.855 | K52: 4667.3754 | M52: -2652.2168 | O52: 92684.73 | Q52: 286.38404 | S52: 2215.1329 | U52: 4.8156919 | W52: 9364.5256 | Y52: 5566.8501 | AA52: 92023.113 | AC52: 3420.8993 | AE52: 4082.5168
A53: 1990 | B53: 2 | C53: 93568.518 | D53: 0.085344841 | E53: 49681.891 | G53: 21038.464 | I53: 20827.777 | K53: 4599.9941 | M53: -2579.609 | O53: 95396.553 | Q53: 292.3986 | S53: 2362.3356 | U53: 5.2137211 | W53: 9697.2069 | Y53: 5804.4485 | AA53: 94636.546 | AC53: 3547.1862 | AE53: 4307.1926
A54: 1990 | B54: 3 | C54: 93527.046 | D54: 0.081758201 | E54: 49017.301 | G54: 21146.163 | I54: 21263.545 | K54: 4716.8751 | M54: -2616.8369 | O54: 95186.501 | Q54: 300.34231 | S54: 2433.7939 | U54: 5.6061808 | W54: 9582.2514 | Y54: 5794.9506 | AA54: 94397.374 | AC54: 3650.2426 | AE54: 4439.3702
A55: 1990 | B55: 4 | C55: 96855.485 | D55: 0.069483361 | E55: 50810.058 | G55: 22518.781 | I55: 21620.495 | K55: 4584.5415 | M55: -2678.3916 | O55: 98421.992 | Q55: 309.09982 | S55: 2456.8705 | U55: 5.6550611 | W55: 9368.461 | Y55: 5659.8381 | AA55: 97669.103 | AC55: 3730.9497 | AE55: 4483.8386
A56: 1991 | B56: 1 | C56: 95642.069 | D56: 0.053199304 | E56: 57595.745 | F56: 0.062225634 | G56: 14259.998 | H56: -0.0056629897 | I56: 21866.1 | J56: 0.080722398 | K56: 4790.2943 | L56: 0.026335775 | M56: -2870.0683 | N56: 0.082139407 | O56: 97691.502 | P56: 0.054019381 | Q56: 319.30213 | R56: 0.11494386 | S56: 2545.8538 | T56: 0.14930071 | U56: 5.1141203 | V56: 0.06196999 | W56: 9552.6311 | X56: 0.020087019 | Y56: 5281.7608 | Z56: -0.051211968 | AA56: 97052.276 | AB56: 0.05465109 | AC56: 3789.39 | AD56: 0.10771749 | AE56: 4428.6158 | AF56: 0.084775898
A57: 1991 | B57: 2 | C57: 97602.376 | D57: 0.043111278 | E57: 53862.601 | F57: 0.08414957 | G57: 19970.495 | H57: -0.050762699 | I57: 22109.887 | J57: 0.061557702 | K57: 4644.4602 | L57: 0.0096665381 | M57: -2985.0673 | N57: 0.15717818 | O57: 99614.511 | P57: 0.044214994 | Q57: 328.19726 | R57: 0.12243102 | S57: 2665.9726 | T57: 0.12853254 | U57: 5.571246 | V57: 0.068573831 | W57: 9607.1704 | X57: -0.0092847818 | Y57: 5262.8316 | Z57: -0.093310653 | AA57: 99004.6 | AB57: 0.046156101 | AC57: 3887.5236 | AD57: 0.095945728 | AE57: 4497.4341 | AF57: 0.044168316
A58: 1991 | B58: 3 | C58: 97494.694 | D58: 0.042422466 | E58: 52670.36 | F58: 0.074525928 | G58: 20711.888 | H58: -0.020536803 | I58: 22417.721 | J58: 0.054279578 | K58: 4781.4323 | L58: 0.013686434 | M58: -3086.7077 | N58: 0.17955676 | O58: 99501.478 | P58: 0.045331818 | Q58: 334.54654 | R58: 0.11388418 | S58: 2662.6702 | T58: 0.094040934 | U58: 5.9975922 | V58: 0.069817836 | W58: 9415.5081 | X58: -0.017401261 | Y58: 5086.5975 | Z58: -0.12223626 | AA58: 98844.566 | AB58: 0.047111404 | AC58: 4026.0555 | AD58: 0.1029556 | AE58: 4682.9674 | AF58: 0.054872013
A59: 1991 | B59: 4 | C59: 100676.39 | D59: 0.039449529 | E59: 54609.639 | F59: 0.074780084 | G59: 21885.657 | H59: -0.028115399 | I59: 22669.651 | J59: 0.048525994 | K59: 4610.1158 | L59: 0.0055783844 | M59: -3098.6746 | N59: 0.1569162 | O59: 102626.76 | P59: 0.042721781 | Q59: 339.21827 | R59: 0.097439245 | S59: 2592.3033 | T59: 0.055124104 | U59: 6.0074662 | V59: 0.062316768 | W59: 9199.026 | X59: -0.018085684 | Y59: 5001.5816 | Z59: -0.11630306 | AA59: 101833.68 | AB59: 0.04263968 | AC59: 4207.1345 | AD59: 0.12763101 | AE59: 5000.2069 | AF59: 0.11516212
A60: 1992 | B60: 1 | C60: 98942.184 | D60: 0.034504846 | E60: 59043.864 | F60: 0.025142803 | G60: 15311.083 | H60: 0.073708597 | I60: 22868.149 | J60: 0.045826599 | K60: 4835.632 | L60: 0.0094644951 | M60: -3116.543 | N60: 0.085877664 | O60: 100908.26 | P60: 0.032927734 | Q60: 346.56338 | R60: 0.085377625 | S60: 2646.4727 | T60: 0.039522653 | U60: 5.3419273 | V60: 0.044544706 | W60: 9029.6929 | X60: -0.054742837 | Y60: 4769.0479 | Z60: -0.097072348 | AA60: 99853.364 | AB60: 0.028861639 | AC60: 4434.4295 | AD60: 0.17022251 | AE60: 5489.3274 | AF60: 0.23951311
A61: 1992 | B61: 2 | C61: 100200.69 | D61: 0.026621419 | E61: 55660.639 | F61: 0.033381934 | G61: 20063.924 | H61: 0.0046783649 | I61: 22957.654 | J61: 0.038343329 | K61: 4632.3542 | L61: -0.0026065389 | M61: -3113.8813 | N61: 0.043152801 | O61: 102069.82 | P61: 0.024648139 | Q61: 345.51526 | R61: 0.052767052 | S61: 2627.6182 | T61: -0.014386641 | U61: 5.7528756 | V61: 0.032601266 | W61: 8895.9732 | X61: -0.074027751 | Y61: 4750.4899 | Z61: -0.097350966 | AA61: 100890.37 | AB61: 0.019047342 | AC61: 4618.5641 | AD61: 0.18804788 | AE61: 5798.0124 | AF61: 0.2891823
A62: 1992 | B62: 3 | C62: 98954.02 | D62: 0.014968265 | E62: 54820.655 | F62: 0.040825508 | G62: 19671.467 | H62: -0.050233033 | I62: 22970.859 | J62: 0.024674168 | K62: 4641.2204 | L62: -0.029324233 | M62: -3150.1814 | N62: 0.020563549 | O62: 100912.75 | P62: 0.014183422 | Q62: 347.10801 | R62: 0.037547743 | S62: 2596.8346 | T62: -0.024725412 | U62: 6.1621057 | V62: 0.027429925 | W62: 8828.7873 | X62: -0.062314305 | Y62: 4626.4932 | Z62: -0.090454244 | AA62: 99711.265 | AB62: 0.0087682992 | AC62: 4763.3163 | AD62: 0.18312237 | AE62: 5964.801 | AF62: 0.2737225
A63: 1992 | B63: 4 | C63: 101459.97 | D63: 0.0077831729 | E63: 56219.141 | F63: 0.029472852 | G63: 20859.538 | H63: -0.046885439 | I63: 22913.651 | J63: 0.010763277 | K63: 4625.3681 | L63: 0.0033084369 | M63: -3157.7281 | N63: 0.019057654 | O63: 103124.74 | P63: 0.0048524106 | Q63: 349.80087 | R63: 0.031197004 | S63: 2542.489 | T63: -0.019216217 | U63: 6.1686388 | V63: 0.026828708 | W63: 8494.4434 | X63: -0.076593169 | Y63: 4643.1517 | Z63: -0.071663318 | AA63: 101994.7 | AB63: 0.001581173 | AC63: 4871.0571 | AD63: 0.15780873 | AE63: 6001.1 | AF63: 0.20017032
A64: 1993 | B64: 1 | C64: 98779.554 | D64: -0.0016436845 | E64: 59736.428 | F64: 0.01172965 | G64: 14301.904 | H64: -0.065911617 | I64: 23039.072 | J64: 0.0074742907 | K64: 4909.6136 | L64: 0.015299259 | M64: -3207.4632 | N64: 0.029173392 | O64: 101170.57 | P64: 0.002599504 | Q64: 370.27913 | R64: 0.06843119 | S64: 2559.1128 | T64: -0.033009928 | U64: 5.5047885 | V64: 0.030487349 | W64: 9208.1373 | X64: 0.019761957 | Y64: 4633.7896 | Z64: -0.028361695 | AA64: 100220.04 | AB64: 0.0036721711 | AC64: 4942.835 | AD64: 0.11464957 | AE64: 5893.3656 | AF64: 0.07360432
A65: 1993 | B65: 2 | C65: 101557.58 | D65: 0.013541746 | E65: 56385.511 | F65: 0.013023068 | G65: 20578.786 | H65: 0.025661071 | I65: 22987.506 | J65: 0.0013003278 | K65: 4829.1659 | L65: 0.042486334 | M65: -3223.3873 | N65: 0.035167045 | O65: 103957.62 | P65: 0.018495157 | Q65: 374.28123 | R65: 0.083255276 | S65: 2534.149 | T65: -0.035571864 | U65: 5.903988 | V65: 0.026267266 | W65: 8936.4552 | X65: 0.0045505914 | Y65: 4382.4531 | Z65: -0.07747343 | AA65: 103076.64 | AB65: 0.021669754 | AC65: 4967.6845 | AD65: 0.075590674 | AE65: 5848.6606 | AF65: 0.0087354376
A66: 1993 | B66: 3 | C66: 102202.9 | D66: 0.03283222 | E66: 55201.946 | F66: 0.0069552544 | G66: 22442.097 | H66: 0.14084512 | I66: 22938.999 | J66: -0.0013870024 | K66: 4885.1359 | L66: 0.05255416 | M66: -3265.2778 | N66: 0.036536436 | O66: 104399.43 | P66: 0.034551389 | Q66: 379.0438 | R66: 0.092005323 | S66: 2526.3031 | T66: -0.027160571 | U66: 6.252912 | V66: 0.014736234 | W66: 8531.5315 | X66: -0.033668926 | Y66: 4193.9999 | Z66: -0.093481882 | AA66: 103505.17 | AB66: 0.038048867 | AC66: 4943.6926 | AD66: 0.037867787 | AE66: 5837.9522 | AF66: -0.021266213
A67: 1993 | B67: 4 | C67: 105779.57 | D67: 0.042574419 | E67: 57150.166 | F67: 0.016560649 | G67: 24029.95 | H67: 0.1519886 | I67: 22963.449 | J67: 0.0021732727 | K67: 4876.6243 | L67: 0.054321339 | M67: -3240.6201 | N67: 0.026250513 | O67: 108356.15 | P67: 0.050728896 | Q67: 382.55529 | R67: 0.093637351 | S67: 2507.7762 | T67: -0.013653106 | U67: 6.136499 | V67: -0.0052101779 | W67: 8830.4459 | X67: 0.039555558 | Y67: 4134.7842 | Z67: -0.10948759 | AA67: 107384.64 | AB67: 0.052845294 | AC67: 4867.201 | AD67: -0.00079163588 | AE67: 5838.7083 | AF67: -0.027060316
... A194: 2025 | B194: 3 | C194: 215197.09 | D194: 0.0054406724 | E194: 119686.46 | F194: 0.029258163 | G194: 35746.864 | H194: -0.092571314 | I194: 54453.573 | J194: 0.023031406 | K194: 11656.027 | L194: 0.03040229 | M194: -6345.8299 | N194: 0.026012732 | O194: 204772.33 | P194: -0.0029359426 | Q194: 874.55313 | R194: 0.0043728332 | S194: 8880.2266 | T194: -0.0011895043 | U194: 122.58006 | V194: 0.096139998 | W194: 41660.919 | X194: -0.11344396 | Y194: 44202.592 | Z194: -0.074115771 | AA194: 200887.9 | AB194: 0.0016480932 | AC194: 15427.668 | AD194: -0.054279762 | AE194: 19312.093 | AF194: -0.086080847

Sheet nom_y
A1: =INDIRECT("beschriftung!"&ADDRESS(beschriftung!$C$1*12+ROW(beschriftung!$A1)-1,COLUMN(beschriftung!A$1))) -> ESA 2010, Quarterly aggregates of Gross Domestic Product, income approach, raw data
A2: =INDIRECT("beschriftung!"&ADDRESS(beschriftung!$C$1*12+ROW(beschriftung!$A2)-1,COLUMN(beschriftung!B$1))) -> In Mio. Swiss Francs, at current prices, percentage change to previous year
C4: =INDIRECT("beschriftung!"&ADDRESS(beschriftung!$C$1*12+ROW(beschriftung!$A5)-1,COLUMN(beschriftung!C$1))) -> Gross domestic product | D4: =IF(INDIRECT("beschriftung.!"&ADDRESS(#REF!*12+ROW($A5)-1,COLUMN(D$1)))="","",INDIRECT("beschriftung.!"&ADDRESS(#REF!*12+ROW($A5)-1,COLUMN(D$1)))) -> #REF! | E4: =IF(INDIRECT("beschriftung.!"&ADDRESS(#REF!*12+ROW($A5)-1,COLUMN(E$1)))="","",INDIRECT("beschriftung.!"&ADDRESS(#REF!*12+ROW($A5)-1,COLUMN(E$1)))) -> #REF! | F4: =IF(INDIRECT("beschriftung.!"&ADDRESS(#REF!*12+ROW($A5)-1,COLUMN(F$1)))="","",INDIRECT("beschriftung.!"&ADDRESS(#REF!*12+ROW($A5)-1,COLUMN(F$1)))) -> #REF! | G4: =IF(INDIRECT("beschriftung.!"&ADDRESS(#REF!*12+ROW($A5)-1,COLUMN(G$1)))="","",INDIRECT("beschriftung.!"&ADDRESS(#REF!*12+ROW($A5)-1,COLUMN(G$1)))) -> #REF! | H4: =IF(INDIRECT("beschriftung.!"&ADDRESS(#REF!*12+ROW($A5)-1,COLUMN(H$1)))="","",INDIRECT("beschriftung.!"&ADDRESS(#REF!*12+ROW($A5)-1,COLUMN(H$1)))) -> #REF! | I4: =IF(INDIRECT("beschriftung.!"&ADDRESS(#REF!*12+ROW($A5)-1,COLUMN(I$1)))="","",INDIRECT("beschriftung.!"&ADDRESS(#REF!*12+ROW($A5)-1,COLUMN(I$1)))) -> #REF! | J4: =IF(INDIRECT("beschriftung.!"&ADDRESS(#REF!*12+ROW($A5)-1,COLUMN(J$1)))="","",INDIRECT("beschriftung.!"&ADDRESS(#REF!*12+ROW($A5)-1,COLUMN(J$1)))) -> #REF! | K4: =IF(INDIRECT("beschriftung.!"&ADDRESS(#REF!*12+ROW($A5)-1,COLUMN(K$1)))="","",INDIRECT("beschriftung.!"&ADDRESS(#REF!*12+ROW($A5)-1,COLUMN(K$1)))) -> #REF! | ... N4: =IF(INDIRECT("beschriftung.!"&ADDRESS(#REF!*12+ROW($A5)-1,COLUMN(N$1)))="","",INDIRECT("beschriftung.!"&ADDRESS(#REF!*12+ROW($A5)-1,COLUMN(N$1)))) -> #REF! | O4: =IF(INDIRECT("beschriftung!"&ADDRESS(beschriftung!$C$1*12+ROW($A5)-1,COLUMN(O$1)))="","",INDIRECT("beschriftung!"&ADDRESS(beschriftung!$C$1*12+ROW($A5)-1,COLUMN(O$1)))) -> Gross national income | P4: =IF(INDIRECT("beschriftung.!"&ADDRESS(#REF!*12+ROW($A5)-1,COLUMN(P$1)))="","",INDIRECT("beschriftung.!"&ADDRESS(#REF!*12+ROW($A5)-1,COLUMN(P$1)))) -> #REF! | Q4: =IF(INDIRECT("beschriftung.!"&ADDRESS(#REF!*12+ROW($A5)-1,COLUMN(Q$1)))="","",INDIRECT("beschriftung.!"&ADDRESS(#REF!*12+ROW($A5)-1,COLUMN(Q$1)))) -> #REF! | R4: =IF(INDIRECT("beschriftung.!"&ADDRESS(#REF!*12+ROW($A5)-1,COLUMN(R$1)))="","",INDIRECT("beschriftung.!"&ADDRESS(#REF!*12+ROW($A5)-1,COLUMN(R$1)))) -> #REF! | S4: =IF(INDIRECT("beschriftung.!"&ADDRESS(#REF!*12+ROW($A5)-1,COLUMN(S$1)))="","",INDIRECT("beschriftung.!"&ADDRESS(#REF!*12+ROW($A5)-1,COLUMN(S$1)))) -> #REF! | T4: =IF(INDIRECT("beschriftung.!"&ADDRESS(#REF!*12+ROW($A5)-1,COLUMN(T$1)))="","",INDIRECT("beschriftung.!"&ADDRESS(#REF!*12+ROW($A5)-1,COLUMN(T$1)))) -> #REF! | W4: =IF(INDIRECT("beschriftung.!"&ADDRESS(#REF!*12+ROW($A5)-1,COLUMN(W$1)))="","",INDIRECT("beschriftung.!"&ADDRESS(#REF!*12+ROW($A5)-1,COLUMN(W$1)))) -> #REF! | X4: =IF(INDIRECT("beschriftung.!"&ADDRESS(#REF!*12+ROW($A5)-1,COLUMN(X$1)))="","",INDIRECT("beschriftung.!"&ADDRESS(#REF!*12+ROW($A5)-1,COLUMN(X$1)))) -> #REF! | Y4: =IF(INDIRECT("beschriftung.!"&ADDRESS(#REF!*12+ROW($A5)-1,COLUMN(Y$1)))="","",INDIRECT("beschriftung.!"&ADDRESS(#REF!*12+ROW($A5)-1,COLUMN(Y$1)))) -> #REF! | Z4: =IF(INDIRECT("beschriftung.!"&ADDRESS(#REF!*12+ROW($A5)-1,COLUMN(Z$1)))="","",INDIRECT("beschriftung.!"&ADDRESS(#REF!*12+ROW($A5)-1,COLUMN(Z$1)))) -> #REF! | AA4: =INDIRECT("beschriftung!"&ADDRESS(beschriftung!$C$1*12+ROW(beschriftung!$A5)-1,COLUMN(beschriftung!AA$1))) -> Disposable income, gross
E5: =INDIRECT("beschriftung!"&ADDRESS(beschriftung!$C$1*12+ROW(beschriftung!$A7)-1,COLUMN(beschriftung!E$1))) -> Compensation of employees | G5: =INDIRECT("beschriftung!"&ADDRESS(beschriftung!$C$1*12+ROW(beschriftung!$A7)-1,COLUMN(beschriftung!G$1))) -> Net operating surplus and net mixed income | I5: =INDIRECT("beschriftung!"&ADDRESS(beschriftung!$C$1*12+ROW(beschriftung!$A7)-1,COLUMN(beschriftung!I$1))) -> Consumption of fixed capital | K5: =INDIRECT("beschriftung!"&ADDRESS(beschriftung!$C$1*12+ROW(beschriftung!$A7)-1,COLUMN(beschriftung!K$1))) -> Taxes on production and imports | M5: =INDIRECT("beschriftung!"&ADDRESS(beschriftung!$C$1*12+ROW(beschriftung!$A7)-1,COLUMN(beschriftung!M$1))) -> Subsidies | O5: =IF(INDIRECT("beschriftung!"&ADDRESS(beschriftung!$C$1*12+ROW($A6)-1,COLUMN(O$1)))="","",INDIRECT("beschriftung!"&ADDRESS(beschriftung!$C$1*12+ROW($A6)-1,COLUMN(O$1)))) | P5: =IF(INDIRECT("beschriftung.!"&ADDRESS(#REF!*12+ROW($A6)-1,COLUMN(P$1)))="","",INDIRECT("beschriftung.!"&ADDRESS(#REF!*12+ROW($A6)-1,COLUMN(P$1)))) -> #REF! | Q5: =INDIRECT("beschriftung!"&ADDRESS(beschriftung!$C$1*12+ROW(beschriftung!$A7)-1,COLUMN(beschriftung!Q$1))) -> Compensation of employees received from the rest of the world | S5: =INDIRECT("beschriftung!"&ADDRESS(beschriftung!$C$1*12+ROW(beschriftung!$A7)-1,COLUMN(beschriftung!S$1))) -> Compensation of employees paid to the rest of the world | U5: =INDIRECT("beschriftung!"&ADDRESS(beschriftung!$C$1*12+ROW(beschriftung!$A7)-1,COLUMN(beschriftung!U$1))) -> Taxes on production and imports received from the rest of the world | W5: =INDIRECT("beschriftung!"&ADDRESS(beschriftung!$C$1*12+ROW(beschriftung!$A7)-1,COLUMN(beschriftung!W$1))) -> Property income received from the rest of the world | Y5: =INDIRECT("beschriftung!"&ADDRESS(beschriftung!$C$1*12+ROW(beschriftung!$A7)-1,COLUMN(beschriftung!Y$1))) -> Property income paid to the rest of the world | AB5: =IF(INDIRECT("beschriftung!"&ADDRESS(beschriftung!$C$1*12+ROW($A6)-1,COLUMN(AB$1)))="","",INDIRECT("beschriftung!"&ADDRESS(beschriftung!$C$1*12+ROW($A6)-1,COLUMN(AB$1)))) | AC5: =INDIRECT("beschriftung!"&ADDRESS(beschriftung!$C$1*12+ROW(beschriftung!$A7)-1,COLUMN(beschriftung!AC$1))) -> Current transfers receivable from the rest of the world | AE5: =INDIRECT("beschriftung!"&ADDRESS(beschriftung!$C$1*12+ROW(beschriftung!$A7)-1,COLUMN(beschriftung!AE$1))) -> Current transfers payable to the rest of the world | AG5: =IF(INDIRECT("beschriftung!"&ADDRESS(beschriftung!$C$1*12+ROW($A6)-1,COLUMN(AG$1)))="","",INDIRECT("beschriftung!"&ADDRESS(beschriftung!$C$1*12+ROW($A6)-1,COLUMN(AG$1))))
O6: =INDIRECT("beschriftung.!"&ADDRESS(#REF!*12+ROW(#REF!)-1,COLUMN(#REF!))) -> #REF!
C11: B1GQ | E11: D1 | G11: B2_B3N | I11: P51C | K11: D2 | M11: D3 | O11: B5GQ | Q11: D1r | S11: D1p | U11: D2r | W11: D4r | Y11: D4p | AA11: B6G | AC11: D5r_D6r_D7r | AE11: D5p_D6p_D7p
A12: 1980 | C12: 208464.8
A13: 1981 | C13: 223793.42 | D13: 0.073530966
A14: 1982 | C14: 237092.14 | D14: 0.05942407
A15: 1983 | C15: 244254.91 | D15: 0.030210899
A16: 1984 | C16: 261062.58 | D16: 0.068812014
A17: 1985 | C17: 276798.76 | D17: 0.06027744
A18: 1986 | C18: 290499.27 | D18: 0.049496287
A19: 1987 | C19: 301578.15 | D19: 0.038137378
A20: 1988 | C20: 320153.22 | D20: 0.061592874
A21: 1989 | C21: 345570.29 | D21: 0.079390333
A22: 1990 | C22: 374762.04 | D22: 0.084474128 | E22: 203731.01 | G22: 79044.621 | I22: 83944.672 | K22: 18568.786 | M22: -10527.054 | O22: 381689.78 | Q22: 1188.2248 | S22: 9468.1329 | U22: 21.290655 | W22: 38012.445 | Y22: 22826.087 | AA22: 378726.14 | AC22: 14349.278 | AE22: 17312.918
A23: 1991 | C23: 391415.53 | D23: 0.044437508 | E23: 218738.35 | F23: 0.073662489 | G23: 76828.038 | H23: -0.028042167 | I23: 89063.359 | J23: 0.060976912 | K23: 18826.303 | L23: 0.013868246 | M23: -12040.518 | N23: 0.14376895 | O23: 399434.25 | P23: 0.046489245 | Q23: 1321.2642 | R23: 0.11196487 | S23: 10466.8 | T23: 0.10547665 | U23: 22.690425 | V23: 0.065745735 | W23: 37774.336 | X23: -0.0062639833 | Y23: 20632.772 | Z23: -0.09608812 | AA23: 396735.13 | AB23: 0.047551483 | AC23: 15910.104 | AD23: 0.10877383 | AE23: 18609.224 | AF23: 0.074875073
A24: 1992 | C24: 399556.86 | D24: 0.020799728 | E24: 225744.3 | F24: 0.032028917 | G24: 75906.012 | H24: -0.012001164 | I24: 91710.313 | J24: 0.029719899 | K24: 18734.575 | L24: -0.0048723218 | M24: -12538.334 | N24: 0.041345058 | O24: 407015.58 | P24: 0.018980172 | Q24: 1388.9875 | R24: 0.051256456 | S24: 10413.415 | T24: -0.0051004487 | U24: 23.425547 | V24: 0.032397927 | W24: 35248.897 | X24: -0.066855941 | Y24: 18789.183 | Z24: -0.089352462 | AA24: 402449.7 | AB24: 0.014404012 | AC24: 18687.367 | AD24: 0.17455973 | AE24: 23253.241 | AF24: 0.24955454
A25: 1993 | C25: 408319.61 | D25: 0.021931151 | E25: 228474.05 | F25: 0.012092236 | G25: 81352.738 | H25: 0.071756182 | I25: 91929.026 | J25: 0.0023848206 | K25: 19500.54 | L25: 0.0408851 | M25: -12936.748 | N25: 0.031775715 | O25: 417883.77 | P25: 0.026702145 | Q25: 1506.1594 | R25: 0.084357795 | S25: 10127.341 | T25: -0.027471636 | U25: 23.798187 | V25: 0.015907421 | W25: 35506.57 | X25: 0.0073101013 | Y25: 17345.027 | Z25: -0.076861024 | AA25: 414186.49 | AB25: 0.029163368 | AC25: 19721.413 | AD25: 0.055333956 | AE25: 23418.687 | AF25: 0.0071149652
A26: 1994 | C26: 418401.77 | D26: 0.024691836 | E26: 229826.66 | F26: 0.0059201981 | G26: 89929.65 | H26: 0.10542868 | I26: 91906.195 | J26: -0.00024834847 | K26: 19748.384 | L26: 0.012709589 | M26: -13009.124 | N26: 0.0055946138 | O26: 424935.12 | P26: 0.016873961 | Q26: 1640.0618 | R26: 0.088903202 | S26: 9877.1956 | T26: -0.024700008 | U26: 26.283674 | V26: 0.10444016 | W26: 34856.508 | X26: -0.018308211 | Y26: 20112.305 | Z26: 0.15954302 | AA26: 420058.62 | AB26: 0.014177498 | AC26: 18385.296 | AD26: -0.067749562 | AE26: 23261.796 | AF26: -0.0066993823
A27: 1995 | C27: 423515.36 | D27: 0.012221718 | E27: 235263.12 | F27: 0.023654599 | G27: 88845.813 | H27: -0.012052051 | I27: 90073.677 | J27: -0.019939009 | K27: 22653.291 | L27: 0.14709598 | M27: -13320.546 | N27: 0.023938719 | O27: 432741.11 | P27: 0.018369827 | Q27: 1721.0554 | R27: 0.049384479 | S27: 9901.9736 | T27: 0.0025086091 | U27: 41.552108 | V27: 0.58090944 | W27: 35560.395 | X27: 0.020193854 | Y27: 18195.28 | Z27: -0.095316039 | AA27: 427767.63 | AB27: 0.018352233 | AC27: 17912.052 | AD27: -0.025740359 | AE27: 22885.523 | AF27: -0.016175567
A28: 1996 | C28: 426881.83 | D28: 0.0079488794 | E28: 235831.06 | F28: 0.0024140534 | G28: 92158.899 | H28: 0.037290287 | I28: 90384.262 | J28: 0.0034481275 | K28: 22723.88 | L28: 0.0031160183 | M28: -14216.271 | N28: 0.06724384 | O28: 437218.98 | P28: 0.010347703 | Q28: 1718.171 | R28: -0.001675965 | S28: 9931.0075 | T28: 0.0029321292 | U28: 41.29161 | V28: -0.0062691886 | W28: 39219.445 | X28: 0.10289678 | Y28: 20710.747 | Z28: 0.13824836 | AA28: 432126.62 | AB28: 0.010190076 | AC28: 19392.819 | AD28: 0.082668786 | AE28: 24485.182 | AF28: 0.0698983
A29: 1997 | C29: 433747.49 | D29: 0.01608329 | E29: 238617.77 | F29: 0.011816573 | G29: 95351.808 | H29: 0.034645689 | I29: 90688.429 | J29: 0.0033652605 | K29: 23522.551 | L29: 0.035146781 | M29: -14433.068 | N29: 0.015249932 | O29: 451652.82 | P29: 0.033012843 | Q29: 1773.8915 | R29: 0.03243014 | S29: 9599.9291 | T29: -0.033337839 | U29: 42.704433 | V29: 0.03421574 | W29: 48909.573 | X29: 0.24707456 | Y29: 23220.909 | Z29: 0.12120091 | AA29: 447126.9 | AB29: 0.034712702 | AC29: 19779.571 | AD29: 0.019943036 | AE29: 24305.493 | AF29: -0.0073386959
A30: 1998 | C30: 444954.84 | D30: 0.025838422 | E30: 242856.12 | F30: 0.017762079 | G30: 98586.619 | H30: 0.033925015 | I30: 93257.574 | J30: 0.028329356 | K30: 25752.902 | L30: 0.094817579 | M30: -15498.373 | N30: 0.073809985 | O30: 465197.75 | P30: 0.029989682 | Q30: 1799.0638 | R30: 0.0141904 | S30: 9509.9275 | T30: -0.0093752373 | U30: 45.790094 | V30: 0.072256222 | W30: 65493.945 | X30: 0.33908235 | Y30: 37585.967 | Z30: 0.61862603 | AA30: 459892.8 | AB30: 0.028550949 | AC30: 21106.251 | AD30: 0.067073255 | AE30: 26411.201 | AF30: 0.086635046
A31: 1999 | C31: 453531.11 | D31: 0.01927446 | E31: 247677.31 | F31: 0.019852056 | G31: 93727.482 | H31: -0.049287996 | I31: 98103.477 | J31: 0.051962566 | K31: 27883.297 | L31: 0.082724474 | M31: -13860.463 | N31: -0.1056827 | O31: 477426.83 | P31: 0.026287931 | Q31: 1851.8887 | R31: 0.029362461 | S31: 9610.4926 | T31: 0.010574745 | U31: 48.931972 | V31: 0.068614797 | W31: 73979.299 | X31: 0.12955937 | Y31: 42373.901 | Z31: 0.12738621 | AA31: 473559.48 | AB31: 0.0297171 | AC31: 22615.962 | AD31: 0.071529096 | AE31: 26483.318 | AF31: 0.0027305636
A32: 2000 | C32: 476794.43 | D32: 0.05129378 | E32: 257661.96 | F32: 0.040313105 | G32: 97948.327 | H32: 0.045033158 | I32: 104324.53 | J32: 0.063413182 | K32: 30694.882 | L32: 0.100834 | M32: -13835.262 | N32: -0.001818165 | O32: 506964.46 | P32: 0.061868382 | Q32: 1906.6539 | R32: 0.02957263 | S32: 10460.247 | T32: 0.088419462 | U32: 90.606671 | V32: 0.85168648 | W32: 102832.14 | X32: 0.39001232 | Y32: 64199.124 | Z32: 0.51506286 | AA32: 504602.34 | AB32: 0.06555219 | AC32: 28163.252 | AD32: 0.24528204 | AE32: 30525.372 | AF32: 0.15262643
A33: 2001 | C33: 489674.26 | D33: 0.027013369 | E33: 272298.95 | F33: 0.056806986 | G33: 90871.449 | H33: -0.072251139 | I33: 110615.69 | J33: 0.060303727 | K33: 30761.562 | L33: 0.0021723706 | M33: -14873.398 | N33: 0.075035496 | O33: 507948.68 | P33: 0.0019413976 | Q33: 2282.302 | R33: 0.19701955 | S33: 11676.661 | T33: 0.11628917 | U33: 201.60129 | V33: 1.225016 | W33: 87436.5 | X33: -0.14971621 | Y33: 59969.32 | Z33: -0.065885697 | AA33: 506797.67 | AB33: 0.0043506125 | AC33: 33272.017 | AD33: 0.18139826 | AE33: 34423.028 | AF33: 0.12768576
A34: 2002 | C34: 489292.8 | D34: -0.00077900453 | E34: 280029.43 | F34: 0.028389666 | G34: 81309.62 | H34: -0.10522369 | I34: 113730.16 | J34: 0.028155817 | K34: 29854.062 | L34: -0.029501097 | M34: -15630.479 | N34: 0.050901687 | O34: 501380.75 | P34: -0.012930306 | Q34: 2227.6105 | R34: -0.023963342 | S34: 12349.713 | T34: 0.057640813 | U34: 203.62697 | V34: 0.010047941 | W34: 64190.881 | X34: -0.26585715 | Y34: 42184.456 | Z34: -0.29656604 | AA34: 495387.88 | AB34: -0.022513505 | AC34: 37216.645 | AD34: 0.11855694 | AE34: 43209.516 | AF34: 0.25525031
... A56: 2024 | C56: 853956.98 | D56: 0.023696254 | E56: 492615.44 | F56: 0.033608443 | G56: 129289.82 | H56: -0.031260506 | I56: 211775.65 | J56: 0.032487731 | K56: 45008.232 | L56: 0.049604882 | M56: -24732.157 | N56: 0.036424001 | O56: 827378.8 | P56: 0.035495483 | Q56: 3465.2883 | R56: 0.039833716 | S56: 35383.483 | T56: 0.047522311 | U56: 431 | V56: 0.043583535 | W56: 192185.46 | X56: 0.049126441 | Y56: 187276.46 | Z56: -0.0055728897 | AA56: 808430.44 | AB56: 0.033279814 | AC56: 64815.424 | AD56: 0.073366969 | AE56: 83763.784 | AF56: 0.087701749

Sheet Feuil1
A1: ESA 2010, Quarterly aggregates of Gross Domestic Product, income approach, raw data
A2: In Mio. Swiss Francs, at current prices, percentage change to previous year
C4: Gross domestic product | D4: =IF(INDIRECT("beschriftung.!"&ADDRESS(#REF!*12+ROW($A5)-1,COLUMN(D$1)))="","",INDIRECT("beschriftung.!"&ADDRESS(#REF!*12+ROW($A5)-1,COLUMN(D$1)))) -> #REF! | E4: =IF(INDIRECT("beschriftung.!"&ADDRESS(#REF!*12+ROW($A5)-1,COLUMN(E$1)))="","",INDIRECT("beschriftung.!"&ADDRESS(#REF!*12+ROW($A5)-1,COLUMN(E$1)))) -> #REF! | F4: =IF(INDIRECT("beschriftung.!"&ADDRESS(#REF!*12+ROW($A5)-1,COLUMN(F$1)))="","",INDIRECT("beschriftung.!"&ADDRESS(#REF!*12+ROW($A5)-1,COLUMN(F$1)))) -> #REF! | G4: =IF(INDIRECT("beschriftung.!"&ADDRESS(#REF!*12+ROW($A5)-1,COLUMN(G$1)))="","",INDIRECT("beschriftung.!"&ADDRESS(#REF!*12+ROW($A5)-1,COLUMN(G$1)))) -> #REF! | H4: =IF(INDIRECT("beschriftung.!"&ADDRESS(#REF!*12+ROW($A5)-1,COLUMN(H$1)))="","",INDIRECT("beschriftung.!"&ADDRESS(#REF!*12+ROW($A5)-1,COLUMN(H$1)))) -> #REF! | I4: =IF(INDIRECT("beschriftung.!"&ADDRESS(#REF!*12+ROW($A5)-1,COLUMN(I$1)))="","",INDIRECT("beschriftung.!"&ADDRESS(#REF!*12+ROW($A5)-1,COLUMN(I$1)))) -> #REF! | J4: =IF(INDIRECT("beschriftung.!"&ADDRESS(#REF!*12+ROW($A5)-1,COLUMN(J$1)))="","",INDIRECT("beschriftung.!"&ADDRESS(#REF!*12+ROW($A5)-1,COLUMN(J$1)))) -> #REF! | K4: =IF(INDIRECT("beschriftung.!"&ADDRESS(#REF!*12+ROW($A5)-1,COLUMN(K$1)))="","",INDIRECT("beschriftung.!"&ADDRESS(#REF!*12+ROW($A5)-1,COLUMN(K$1)))) -> #REF! | ... N4: =IF(INDIRECT("beschriftung.!"&ADDRESS(#REF!*12+ROW($A5)-1,COLUMN(N$1)))="","",INDIRECT("beschriftung.!"&ADDRESS(#REF!*12+ROW($A5)-1,COLUMN(N$1)))) -> #REF! | O4: Gross national income | P4: =IF(INDIRECT("beschriftung.!"&ADDRESS(#REF!*12+ROW($A5)-1,COLUMN(P$1)))="","",INDIRECT("beschriftung.!"&ADDRESS(#REF!*12+ROW($A5)-1,COLUMN(P$1)))) -> #REF! | Q4: =IF(INDIRECT("beschriftung.!"&ADDRESS(#REF!*12+ROW($A5)-1,COLUMN(Q$1)))="","",INDIRECT("beschriftung.!"&ADDRESS(#REF!*12+ROW($A5)-1,COLUMN(Q$1)))) -> #REF! | R4: =IF(INDIRECT("beschriftung.!"&ADDRESS(#REF!*12+ROW($A5)-1,COLUMN(R$1)))="","",INDIRECT("beschriftung.!"&ADDRESS(#REF!*12+ROW($A5)-1,COLUMN(R$1)))) -> #REF! | S4: =IF(INDIRECT("beschriftung.!"&ADDRESS(#REF!*12+ROW($A5)-1,COLUMN(S$1)))="","",INDIRECT("beschriftung.!"&ADDRESS(#REF!*12+ROW($A5)-1,COLUMN(S$1)))) -> #REF! | T4: =IF(INDIRECT("beschriftung.!"&ADDRESS(#REF!*12+ROW($A5)-1,COLUMN(T$1)))="","",INDIRECT("beschriftung.!"&ADDRESS(#REF!*12+ROW($A5)-1,COLUMN(T$1)))) -> #REF! | W4: =IF(INDIRECT("beschriftung.!"&ADDRESS(#REF!*12+ROW($A5)-1,COLUMN(W$1)))="","",INDIRECT("beschriftung.!"&ADDRESS(#REF!*12+ROW($A5)-1,COLUMN(W$1)))) -> #REF! | X4: =IF(INDIRECT("beschriftung.!"&ADDRESS(#REF!*12+ROW($A5)-1,COLUMN(X$1)))="","",INDIRECT("beschriftung.!"&ADDRESS(#REF!*12+ROW($A5)-1,COLUMN(X$1)))) -> #REF! | Y4: =IF(INDIRECT("beschriftung.!"&ADDRESS(#REF!*12+ROW($A5)-1,COLUMN(Y$1)))="","",INDIRECT("beschriftung.!"&ADDRESS(#REF!*12+ROW($A5)-1,COLUMN(Y$1)))) -> #REF! | Z4: =IF(INDIRECT("beschriftung.!"&ADDRESS(#REF!*12+ROW($A5)-1,COLUMN(Z$1)))="","",INDIRECT("beschriftung.!"&ADDRESS(#REF!*12+ROW($A5)-1,COLUMN(Z$1)))) -> #REF! | AA4: Disposable income, gross
E5: Compensation of employees | G5: Net operating surplus and net mixed income | I5: Consumption of fixed capital | K5: Taxes on production and imports | M5: Subsidies | P5: #REF! | Q5: Compensation of employees received from the rest of the world | S5: Compensation of employees paid to the rest of the world | U5: Taxes on production and imports received from the rest of the world | W5: Property income received from the rest of the world | Y5: Property income paid to the rest of the world | AC5: Current transfers receivable from the rest of the world | AE5: Current transfers payable to the rest of the world
O6: #REF!
C11: B1GQ | E11: D1 | G11: B2_B3N | I11: P51C | K11: D2 | M11: D3 | O11: B5GQ | Q11: D1r | S11: D1p | U11: D2r | W11: D4r | Y11: D4p | AA11: B6G | AC11: D5r_D6r_D7r | AE11: D5p_D6p_D7p
A12: 1980 | C12: 208464.8
A13: 1981 | C13: 223793.42 | D13: 0.073530966
A14: 1982 | C14: 237092.14 | D14: 0.05942407
A15: 1983 | C15: 244254.91 | D15: 0.030210899
A16: 1984 | C16: 261062.58 | D16: 0.068812014
A17: 1985 | C17: 276798.76 | D17: 0.06027744
A18: 1986 | C18: 290499.27 | D18: 0.049496287
A19: 1987 | C19: 301578.15 | D19: 0.038137378
A20: 1988 | C20: 320153.22 | D20: 0.061592874
A21: 1989 | C21: 345570.29 | D21: 0.079390333 | AG21: part salaire | AH21: part profits
A22: 1990 | C22: 374762.04 | D22: 0.084474128 | E22: 203731.01 | G22: 79044.621 | I22: 83944.672 | K22: 18568.786 | M22: -10527.054 | O22: 381689.78 | Q22: 1188.2248 | S22: 9468.1329 | U22: 21.290655 | W22: 38012.445 | Y22: 22826.087 | AA22: 378726.14 | AC22: 14349.278 | AE22: 17312.918 | AG22: =E22/C22 -> 0.54362767 | AH22: =(G22+I22+K22+M22)/C22 -> 0.45637233 | AI22: =AG22+AH22 -> 1
A23: 1991 | C23: 391415.53 | D23: 0.044437508 | E23: 218738.35 | F23: 0.073662489 | G23: 76828.038 | H23: -0.028042167 | I23: 89063.359 | J23: 0.060976912 | K23: 18826.303 | L23: 0.013868246 | M23: -12040.518 | N23: 0.14376895 | O23: 399434.25 | P23: 0.046489245 | Q23: 1321.2642 | R23: 0.11196487 | S23: 10466.8 | T23: 0.10547665 | U23: 22.690425 | V23: 0.065745735 | W23: 37774.336 | X23: -0.0062639833 | Y23: 20632.772 | Z23: -0.09608812 | AA23: 396735.13 | AB23: 0.047551483 | AC23: 15910.104 | AD23: 0.10877383 | AE23: 18609.224 | AF23: 0.074875073 | AG23: =E23/C23 -> 0.55883921 | AH23: =(G23+I23+K23+M23)/C23 -> 0.44116079 | AI23: =AG23+AH23 -> 1
A24: 1992 | C24: 399556.86 | D24: 0.020799728 | E24: 225744.3 | F24: 0.032028917 | G24: 75906.012 | H24: -0.012001164 | I24: 91710.313 | J24: 0.029719899 | K24: 18734.575 | L24: -0.0048723218 | M24: -12538.334 | N24: 0.041345058 | O24: 407015.58 | P24: 0.018980172 | Q24: 1388.9875 | R24: 0.051256456 | S24: 10413.415 | T24: -0.0051004487 | U24: 23.425547 | V24: 0.032397927 | W24: 35248.897 | X24: -0.066855941 | Y24: 18789.183 | Z24: -0.089352462 | AA24: 402449.7 | AB24: 0.014404012 | AC24: 18687.367 | AD24: 0.17455973 | AE24: 23253.241 | AF24: 0.24955454 | AG24: =E24/C24 -> 0.56498666 | AH24: =(G24+I24+K24+M24)/C24 -> 0.43501334 | AI24: =AG24+AH24 -> 1
A25: 1993 | C25: 408319.61 | D25: 0.021931151 | E25: 228474.05 | F25: 0.012092236 | G25: 81352.738 | H25: 0.071756182 | I25: 91929.026 | J25: 0.0023848206 | K25: 19500.54 | L25: 0.0408851 | M25: -12936.748 | N25: 0.031775715 | O25: 417883.77 | P25: 0.026702145 | Q25: 1506.1594 | R25: 0.084357795 | S25: 10127.341 | T25: -0.027471636 | U25: 23.798187 | V25: 0.015907421 | W25: 35506.57 | X25: 0.0073101013 | Y25: 17345.027 | Z25: -0.076861024 | AA25: 414186.49 | AB25: 0.029163368 | AC25: 19721.413 | AD25: 0.055333956 | AE25: 23418.687 | AF25: 0.0071149652 | AG25: =E25/C25 -> 0.5595471 | AH25: =(G25+I25+K25+M25)/C25 -> 0.4404529 | AI25: =AG25+AH25 -> 1
A26: 1994 | C26: 418401.77 | D26: 0.024691836 | E26: 229826.66 | F26: 0.0059201981 | G26: 89929.65 | H26: 0.10542868 | I26: 91906.195 | J26: -0.00024834847 | K26: 19748.384 | L26: 0.012709589 | M26: -13009.124 | N26: 0.0055946138 | O26: 424935.12 | P26: 0.016873961 | Q26: 1640.0618 | R26: 0.088903202 | S26: 9877.1956 | T26: -0.024700008 | U26: 26.283674 | V26: 0.10444016 | W26: 34856.508 | X26: -0.018308211 | Y26: 20112.305 | Z26: 0.15954302 | AA26: 420058.62 | AB26: 0.014177498 | AC26: 18385.296 | AD26: -0.067749562 | AE26: 23261.796 | AF26: -0.0066993823 | AG26: =E26/C26 -> 0.54929659 | AH26: =(G26+I26+K26+M26)/C26 -> 0.45070341 | AI26: =AG26+AH26 -> 1
A27: 1995 | C27: 423515.36 | D27: 0.012221718 | E27: 235263.12 | F27: 0.023654599 | G27: 88845.813 | H27: -0.012052051 | I27: 90073.677 | J27: -0.019939009 | K27: 22653.291 | L27: 0.14709598 | M27: -13320.546 | N27: 0.023938719 | O27: 432741.11 | P27: 0.018369827 | Q27: 1721.0554 | R27: 0.049384479 | S27: 9901.9736 | T27: 0.0025086091 | U27: 41.552108 | V27: 0.58090944 | W27: 35560.395 | X27: 0.020193854 | Y27: 18195.28 | Z27: -0.095316039 | AA27: 427767.63 | AB27: 0.018352233 | AC27: 17912.052 | AD27: -0.025740359 | AE27: 22885.523 | AF27: -0.016175567 | AG27: =E27/C27 -> 0.5555008 | AH27: =(G27+I27+K27+M27)/C27 -> 0.4444992 | AI27: =AG27+AH27 -> 1
A28: 1996 | C28: 426881.83 | D28: 0.0079488794 | E28: 235831.06 | F28: 0.0024140534 | G28: 92158.899 | H28: 0.037290287 | I28: 90384.262 | J28: 0.0034481275 | K28: 22723.88 | L28: 0.0031160183 | M28: -14216.271 | N28: 0.06724384 | O28: 437218.98 | P28: 0.010347703 | Q28: 1718.171 | R28: -0.001675965 | S28: 9931.0075 | T28: 0.0029321292 | U28: 41.29161 | V28: -0.0062691886 | W28: 39219.445 | X28: 0.10289678 | Y28: 20710.747 | Z28: 0.13824836 | AA28: 432126.62 | AB28: 0.010190076 | AC28: 19392.819 | AD28: 0.082668786 | AE28: 24485.182 | AF28: 0.0698983 | AG28: =E28/C28 -> 0.55245045 | AH28: =(G28+I28+K28+M28)/C28 -> 0.44754955 | AI28: =AG28+AH28 -> 1
A29: 1997 | C29: 433747.49 | D29: 0.01608329 | E29: 238617.77 | F29: 0.011816573 | G29: 95351.808 | H29: 0.034645689 | I29: 90688.429 | J29: 0.0033652605 | K29: 23522.551 | L29: 0.035146781 | M29: -14433.068 | N29: 0.015249932 | O29: 451652.82 | P29: 0.033012843 | Q29: 1773.8915 | R29: 0.03243014 | S29: 9599.9291 | T29: -0.033337839 | U29: 42.704433 | V29: 0.03421574 | W29: 48909.573 | X29: 0.24707456 | Y29: 23220.909 | Z29: 0.12120091 | AA29: 447126.9 | AB29: 0.034712702 | AC29: 19779.571 | AD29: 0.019943036 | AE29: 24305.493 | AF29: -0.0073386959 | AG29: =E29/C29 -> 0.55013061 | AH29: =(G29+I29+K29+M29)/C29 -> 0.44986939 | AI29: =AG29+AH29 -> 1
A30: 1998 | C30: 444954.84 | D30: 0.025838422 | E30: 242856.12 | F30: 0.017762079 | G30: 98586.619 | H30: 0.033925015 | I30: 93257.574 | J30: 0.028329356 | K30: 25752.902 | L30: 0.094817579 | M30: -15498.373 | N30: 0.073809985 | O30: 465197.75 | P30: 0.029989682 | Q30: 1799.0638 | R30: 0.0141904 | S30: 9509.9275 | T30: -0.0093752373 | U30: 45.790094 | V30: 0.072256222 | W30: 65493.945 | X30: 0.33908235 | Y30: 37585.967 | Z30: 0.61862603 | AA30: 459892.8 | AB30: 0.028550949 | AC30: 21106.251 | AD30: 0.067073255 | AE30: 26411.201 | AF30: 0.086635046 | AG30: =E30/C30 -> 0.54579948 | AH30: =(G30+I30+K30+M30)/C30 -> 0.45420052 | AI30: =AG30+AH30 -> 1
A31: 1999 | C31: 453531.11 | D31: 0.01927446 | E31: 247677.31 | F31: 0.019852056 | G31: 93727.482 | H31: -0.049287996 | I31: 98103.477 | J31: 0.051962566 | K31: 27883.297 | L31: 0.082724474 | M31: -13860.463 | N31: -0.1056827 | O31: 477426.83 | P31: 0.026287931 | Q31: 1851.8887 | R31: 0.029362461 | S31: 9610.4926 | T31: 0.010574745 | U31: 48.931972 | V31: 0.068614797 | W31: 73979.299 | X31: 0.12955937 | Y31: 42373.901 | Z31: 0.12738621 | AA31: 473559.48 | AB31: 0.0297171 | AC31: 22615.962 | AD31: 0.071529096 | AE31: 26483.318 | AF31: 0.0027305636 | AG31: =E31/C31 -> 0.54610877 | AH31: =(G31+I31+K31+M31)/C31 -> 0.45389123 | AI31: =AG31+AH31 -> 1
A32: 2000 | C32: 476794.43 | D32: 0.05129378 | E32: 257661.96 | F32: 0.040313105 | G32: 97948.327 | H32: 0.045033158 | I32: 104324.53 | J32: 0.063413182 | K32: 30694.882 | L32: 0.100834 | M32: -13835.262 | N32: -0.001818165 | O32: 506964.46 | P32: 0.061868382 | Q32: 1906.6539 | R32: 0.02957263 | S32: 10460.247 | T32: 0.088419462 | U32: 90.606671 | V32: 0.85168648 | W32: 102832.14 | X32: 0.39001232 | Y32: 64199.124 | Z32: 0.51506286 | AA32: 504602.34 | AB32: 0.06555219 | AC32: 28163.252 | AD32: 0.24528204 | AE32: 30525.372 | AF32: 0.15262643 | AG32: =E32/C32 -> 0.54040471 | AH32: =(G32+I32+K32+M32)/C32 -> 0.45959529 | AI32: =AG32+AH32 -> 1
A33: 2001 | C33: 489674.26 | D33: 0.027013369 | E33: 272298.95 | F33: 0.056806986 | G33: 90871.449 | H33: -0.072251139 | I33: 110615.69 | J33: 0.060303727 | K33: 30761.562 | L33: 0.0021723706 | M33: -14873.398 | N33: 0.075035496 | O33: 507948.68 | P33: 0.0019413976 | Q33: 2282.302 | R33: 0.19701955 | S33: 11676.661 | T33: 0.11628917 | U33: 201.60129 | V33: 1.225016 | W33: 87436.5 | X33: -0.14971621 | Y33: 59969.32 | Z33: -0.065885697 | AA33: 506797.67 | AB33: 0.0043506125 | AC33: 33272.017 | AD33: 0.18139826 | AE33: 34423.028 | AF33: 0.12768576 | AG33: =E33/C33 -> 0.55608183 | AH33: =(G33+I33+K33+M33)/C33 -> 0.44391817 | AI33: =AG33+AH33 -> 1
A34: 2002 | C34: 489292.8 | D34: -0.00077900453 | E34: 280029.43 | F34: 0.028389666 | G34: 81309.62 | H34: -0.10522369 | I34: 113730.16 | J34: 0.028155817 | K34: 29854.062 | L34: -0.029501097 | M34: -15630.479 | N34: 0.050901687 | O34: 501380.75 | P34: -0.012930306 | Q34: 2227.6105 | R34: -0.023963342 | S34: 12349.713 | T34: 0.057640813 | U34: 203.62697 | V34: 0.010047941 | W34: 64190.881 | X34: -0.26585715 | Y34: 42184.456 | Z34: -0.29656604 | AA34: 495387.88 | AB34: -0.022513505 | AC34: 37216.645 | AD34: 0.11855694 | AE34: 43209.516 | AF34: 0.25525031 | AG34: =E34/C34 -> 0.57231464 | AH34: =(G34+I34+K34+M34)/C34 -> 0.42768536 | AI34: =AG34+AH34 -> 1
... A56: 2024 | C56: 853956.98 | D56: 0.023696254 | E56: 492615.44 | F56: 0.033608443 | G56: 129289.82 | H56: -0.031260506 | I56: 211775.65 | J56: 0.032487731 | K56: 45008.232 | L56: 0.049604882 | M56: -24732.157 | N56: 0.036424001 | O56: 827378.8 | P56: 0.035495483 | Q56: 3465.2883 | R56: 0.039833716 | S56: 35383.483 | T56: 0.047522311 | U56: 431 | V56: 0.043583535 | W56: 192185.46 | X56: 0.049126441 | Y56: 187276.46 | Z56: -0.0055728897 | AA56: 808430.44 | AB56: 0.033279814 | AC56: 64815.424 | AD56: 0.073366969 | AE56: 83763.784 | AF56: 0.087701749 | AG56: =E56/C56 -> 0.57686212 | AH56: =(G56+I56+K56+M56)/C56 -> 0.42313788 | AI56: =AG56+AH56 -> 1

Sheet beschriftung
A1: deutsch | C1: 4
A2: français
A3: italiano
A4: english
A11: deutsch
A12: ESVG 2010, Quartalsaggregate des Bruttoinlandprodukts, Einkommensansatz, unbereinigte Daten | B12: ESVG 2010, Jahresaggregate des Bruttoinlandproduktes, Einkommensansatz (BFS, SECO), unbereinigte Daten
A13: In Mio. Franken, zu laufenden Preisen und Veränderungsraten in % gegenüber dem gleichen Quartal des Vorjahres | B13: In Mio. Franken, zu laufenden Preisen und Veränderungsraten in % gegenüber dem Vorjahr
C16: Bruttoinlandprodukt | O16: Bruttonationaleinkommen | AA16: Verfügbares Bruttoeinkommen
AO17: NA | AQ17: NA | AR17: NA
E18: Arbeitnehmerentgelt | G18: Nettobetriebs- überschuss und Nettoselbständigen- einkommen | I18: Abschreibungen | K18: Produktions und Importabgaben | M18: Subventionen | Q18: Arbeitnehmerentgelt aus der übrigen Welt | S18: Arbeitnehmerentgelt an die übrige Welt | U18: Produktions- und Importabgaben aus der übrigen Welt | W18: Vermögenseinkommen aus der übrigen Welt | Y18: Vermögenseinkommen an die übrige Welt | AC18: Transfers aus der übrigen Welt | AE18: Transfers an die übrige Welt
M19: NA | Y19: NA | AC19: NA | AE19: NA
A21: Jahr | B21: Quartal
A23: français
A24: SEC 2010, PIB trimestriel et ses composantes, approche par les revenus, données brutes | B24: SEC 2010, PIB annuel et ses composantes, approche par les revenus (OFS, SECO), données brutes
A25: En mio. de francs, aux prix courants, variations en % par rapport au même trimestre de l'année précédente | B25: En mio. de francs, aux prix courants, variations en % par rapport de l'année précédente
C28: Produit intérieur brut | O28: Revenu national brut | AA28: Revenu disponible brut
AO29: NA | AQ29: NA | AR29: NA
E30: Rémunération des salariés | G30: Excédent net d'exploitation et revenu mixte net | I30: Consommation de capital fixe | K30: Impôts sur la production et les importations | M30: Subventions | Q30: Rémunération des salariés reçue du reste du monde | S30: Rémunération des salariés versée au reste du monde | U30: Impôts sur la production et les importations reçus du reste du monde | W30: Revenus de la propriété reçus du reste du monde | Y30: Revenus de la propriété versés au reste du monde | AC30: Transferts courants à recevoir du reste du monde | AE30: Transferts courants à payer au reste du monde
M31: NA
A33: Année | B33: Trimestre
A35: italiano
A36: SEC 2010, Prodotto Interno Lordo e aggregati trimestrali, ottica dei redditi distribuiti, dati grezzi | B36: SEC 2010, Prodotto Interno Lordo e aggregati annuali, ottica dei redditi distribuiti (UST, SECO), dati grezzi
A37: In milioni di franchi, a prezzi correnti, variazione in % rispetto all'anno precedente | B37: In milioni di franchi, a prezzi correnti, variazione in % rispetto all'anno precedente
C40: Prodotto interno lordo | O40: Reddito nazionale lordo | AA40: Reddito disponibile lordo
AO41: NA | AQ41: NA | AR41: NA
E42: Redditi da lavoro dipendente | G42: Risultato di gestione netto e reddito misto netto | I42: Ammortamenti (consumo di capitale fisso) | K42: Imposte sulla produzione e sulle importazioni | M42: Sovvenzioni | Q42: Redditi da lavoro dipendente ricevuti dal resto del mondo | S42: Redditi da lavoro dipendente versati al resto del mondo | U42: Imposte sulla produzione e sulle importazioni ricevute dal resto del mondo | W42: Redditi da capitale ricevuti dal resto del mondo | Y42: Redditi da capitale versati al resto del mondo | AC42: Trasferimenti correnti ricevuti dal resto del mondo | AE42: Trasferimenti correnti versati al resto del mondo
M43: NA
A45: Anno | B45: Trimestre
A47: english
A48: ESA 2010, Quarterly aggregates of Gross Domestic Product, income approach, raw data | B48: ESA 2010, Annual aggregates of Gross Domestic Product, income approach (SFSO, SECO), raw data
A49: In Mio. Swiss Francs, at current prices, percentage change to previous year | B49: In Mio. Swiss Francs, at current prices, percentage change to previous year
C52: Gross domestic product | O52: Gross national income | AA52: Disposable income, gross
AO53: NA | AQ53: NA | AR53: NA
E54: Compensation of employees | G54: Net operating surplus and net mixed income | I54: Consumption of fixed capital | K54: Taxes on production and imports | M54: Subsidies | Q54: Compensation of employees received from the rest of the world | S54: Compensation of employees paid to the rest of the world | U54: Taxes on production and imports received from the rest of the world | W54: Property income received from the rest of the world | Y54: Property income paid to the rest of the world | AC54: Current transfers receivable from the rest of the world | AE54: Current transfers payable to the rest of the world
M55: NA
A57: Year | B57: Quarter
